Workbook

Sheet april 
C2: Money | F2: Savings Account | I2: Name | J2: Value | K2: Paid? | L2: Who
C3: Paid | D3: 3930.71 | F3: Savings Account | G3: 420 | I3: Mortgage | J3: -797 | K3: no
C4: Taken Already | D4: =SUMIF(K3:K29,"Yes*",J3:J29) -> 0 | I4: Car | J4: -244.8 | K4: no | L4: f
C5: Balance | D5: 3930 | F5: train | I5: LifeInsurance/aviva | J5: -25.56 | K5: no
C6: To Be Taken | D6: =SUMIF(K3:K33,"No",J3:J33) -> -3737.73 | F6: francesca christmas | I6: HouseInsurance - Tesco | J6: -24.82 | K6: no
C7: Total | D7: =D6+D5 -> 192.27 | F7: rumpus vet fund | G7: 151 | I7: TvLicence | J7: -13.2 | K7: no
C8: Francesca | D8: =SUMIF(L3:L33,"f",J3:J33) -> -1722.3 | F8: EDF BUFFER | G8: 35 | I8: Gas/Electric | J8: -229 | K8: no
I9: pet insur | J9: -35 | K9: no
D10: 4042 | F10: francesca cashback | I10: spotoify | J10: -16.99 | K10: no
D11: =D5-D10 -> -112 | F11: Saving Total | G11: =SUM(G3:G10) -> 606 | I11: loan | J11: -395 | K11: no
I12: netflix | J12: -13.99 | K12: no
F13: Botox | G13: 290 | I13: plus net | J13: -28.22 | K13: no
I14: council tax | J14: -209 | K14: no
C15: Mortgage | I15: water | J15: -16 | K15: no
C16: Main | D16: 167660.11 | I16: GARDEN | J16: -6.25 | K16: no
C17: Extra | D17: 87559.93 | I17: water | J17: -35 | K17: no
C18: Total Due | D18: =SUM(D16:D17) -> 255220.04 | I18: hp | J18: -3 | K18: no
C19: H2B paybak | D19: =D20*0.2 -> 84000 | F19: loan is 2600.00 | G19: 1082 | I19: HSBC CC | J19: -600 | K19: no | L19: f
C20: Sold Price | D20: 420000 | F20: Paid 1 | G20: 160 | I20: swimming | K20: no
C21: Equity | D21: =SUM(D18:D19)-D20 -> -80779.96 | F21: Paid 1 | I21: Tesco Mobile | J21: -12.5 | K21: no | L21: f
F22: Paid 1 | I22: tesco card | K22: no | L22: f
F23: Paid 1 | I23: food petrol | J23: -750 | K23: no | L23: f
G24: =SUM(G20:G23)-G19 -> -922 | I24: window cleaner | J24: -10 | K24: no
C25: 4170 with oncall | I25: greenbelt | J25: -7.4 | K25: no
C26: 3930.00 without | D26: 60 | I26: next | K26: no | L26: f
I27: car insurance lv | J27: -35 | K27: no
I28: child benefit shit | J28: -85 | K28: no | L28: f
I29: train | J29: -115 | K29: no
I30: gym | J30: -30 | K30: no | L30: f
I31: matts credit | K31: no
I32: edf buffer | K32: no
D33: =SUM(D26:D32) -> 60 | I33: savings | K33: no
K34: no
K35: no

Sheet feb26
A1: Money | E1: Savings Account | H1: Name | I1: Value | J1: Paid? | K1: Who
A2: Paid | B2: 5225 | E2: Rainy Day 🌧️ | F2: 50 | H2: Mortgage | I2: -1117 | J2: no
A3: Taken Already | B3: =SUMIF(J2:J47,"Yes*",I2:I47) -> 0 | E3: botox | H3: stocks and shares isa | I3: -143 | J3: no | K3: s
A4: Balance | B4: 5225 | E4: Dental 🪥 | F4: 120 | H4: LifeInsurance/aviva | I4: -39 | J4: no
A5: To Be Taken | B5: =SUMIF(J2:J47,"No",I2:I47) -> -5207.67 | E5: Vet Fund 😺 | F5: 620 | H5: HouseInsurance - Tesco | I5: -39 | J5: no
A6: Total | B6: =B5+B4 -> 17.33 | E6: christmas | F6: 974 | H6: TvLicence | I6: -15 | J6: no
A7: Francesca pt 1 | B7: =SUMIF(K2:K47,"f1",I2:I47) -> -2017.99 | E7: willow bday | F7: 200 | H7: Gas/Electric | I7: -185 | J7: no
A8: Francesca pt 2 | B8: =SUMIF(K2:K47,"f2",I2:I47) -> -48 | E8: 5 week | F8: 100 | H8: pet insur | I8: -40 | J8: no | K8: s
A9: Matt | B9: =SUMIF(K2:K47,"",I2:I47) -> -2958.68 | H9: spotoify | I9: -22 | J9: no
A10: Savings | B10: =SUMIF(K2:K47,"s",I2:I47) -> -183 | E10: TAX | H10: rumpus food | I10: -55 | J10: no
A11: Mortgage | E11: Saving Total | F11: =SUM(F2:F10) -> 2064 | H11: rumpus arun vet | I11: -7.99 | J11: no | K11: f1
A12: Main | B12: 151455.79 | C12: 27yrs 8 Months | H12: amazon | I12: -8.99 | J12: no
A13: Extra | B13: 80139.8 | C13: 0.0482 | E13: francesca Isa | F13: 22500 | H13: council tax | I13: -239 | J13: no
A14: Total Due | B14: =SUM(B12:B13) -> 231595.59 | E14: savings | F14: 1000 | H14: water | I14: -13 | J14: no
A15: H2B paybak | B15: =B16*0.2 -> 92000 | E15: botox | H15: window clean | I15: -10 | J15: no
A16: Sold Price | B16: 460000 | E16: me | H16: water | I16: -58 | J16: no
A17: Equity | B17: =B16-SUM(B14:B15) -> 136404.41 | E17: matt bday | H17: hp | I17: -1.5 | J17: no
E18: matt gift | H18: DISHWASHER | I18: -5 | J18: no
E19: mattchristmas | H19: fran money for card | I19: -800 | J19: no | K19: f1
E20: christmas | H20: tesco mobiles | I20: -28 | J20: no | K20: f2
E21: FRANNYS MONEY | F21: =SUM(F15:F20) -> 0 | H21: green belt | I21: -14.99 | J21: no
E22: JL092865B | H22: food petrol | I22: -930 | J22: no | K22: f1
H23: willow bday | I23: -150 | J23: no
H24: botox | I24: -75 | J24: no | K24: f1
H25: dental | I25: -20 | J25: no
H26: car insurance lv | I26: -27.7 | J26: no
H27: child benefit shit | I27: -90 | J27: no | K27: f1
H28: zoom | I28: -18 | J28: no
H29: 5 week month | I29: -133 | J29: no
A30: NW | H30: boiler | I30: -14.5 | J30: no
A31: 1104841580 | H31: service | I31: -35 | J31: no | K31: f1
H32: matt | I32: -80 | J32: no
H33: pocket money | I33: -25 | J33: no
H34: help to by | I34: -130 | J34: no
H35: lunch | I35: -20 | J35: no | K35: f2
H36: nails | I36: -80 | J36: no | K36: f1
H37: christmas | I37: -50 | J37: no
H38: green waste | I38: -8 | J38: no
H39: emergancy fund | I39: -300 | J39: no
H40: gym | I40: -30 | J40: no
H41: decorating | I41: -150 | J41: no
J42: no
J43: no
J44: no
J45: no
J46: no
J47: no

Sheet jan26
A1: Money | E1: Savings Account | H1: Name | I1: Value | J1: Paid? | K1: Who
A2: Paid | B2: 5225 | E2: Rainy Day 🌧️ | F2: 50 | H2: Mortgage | I2: -1117 | J2: no
A3: Taken Already | B3: =SUMIF(J2:J47,"Yes*",I2:I47) -> 0 | E3: botox | H3: stocks and shares isa | I3: -143 | J3: no | K3: s
A4: Balance | B4: 5225 | E4: Dental 🪥 | F4: 120 | H4: LifeInsurance/aviva | I4: -39 | J4: no
A5: To Be Taken | B5: =SUMIF(J2:J47,"No",I2:I47) -> -5219.67 | E5: Vet Fund 😺 | F5: 620 | H5: HouseInsurance - Tesco | I5: -39 | J5: no
A6: Total | B6: =B5+B4 -> 5.33 | E6: christmas | F6: 974 | H6: TvLicence | I6: -15 | J6: no
A7: Francesca pt 1 | B7: =SUMIF(K2:K47,"f1",I2:I47) -> -2272.99 | E7: willow bday | F7: 200 | H7: Gas/Electric | I7: -185 | J7: no
A8: Francesca pt 2 | B8: =SUMIF(K2:K47,"f2",I2:I47) -> -48 | E8: 5 week | F8: 100 | H8: pet insur | I8: -40 | J8: no | K8: s
A9: Matt | B9: =SUMIF(K2:K47,"",I2:I47) -> -2715.68 | H9: spotoify | I9: -22 | J9: no
A10: Savings | B10: =SUMIF(K2:K47,"s",I2:I47) -> -183 | E10: TAX | H10: rumpus food | I10: -55 | J10: no
A11: Mortgage | E11: Saving Total | F11: =SUM(F2:F10) -> 2064 | H11: rumpus arun vet | I11: -7.99 | J11: no | K11: f1
A12: Main | B12: 151455.79 | C12: 27yrs 8 Months | H12: amazon | I12: -8.99 | J12: no
A13: Extra | B13: 80139.8 | C13: 0.0482 | E13: francesca Isa | F13: 22500 | H13: council tax | I13: -239 | J13: no
A14: Total Due | B14: =SUM(B12:B13) -> 231595.59 | E14: savings | F14: 1000 | H14: water | I14: -13 | J14: no
A15: H2B paybak | B15: =B16*0.2 -> 92000 | E15: botox | H15: window clean | I15: -10 | J15: no
A16: Sold Price | B16: 460000 | E16: me | H16: water | I16: -58 | J16: no
A17: Equity | B17: =B16-SUM(B14:B15) -> 136404.41 | E17: matt bday | H17: hp | I17: -1.5 | J17: no
E18: matt gift | H18: DISHWASHER | I18: -5 | J18: no
E19: mattchristmas | H19: fran money for card | I19: -1000 | J19: no | K19: f1
E20: christmas | H20: tesco mobiles | I20: -28 | J20: no | K20: f2
E21: FRANNYS MONEY | F21: =SUM(F15:F20) -> 0 | H21: green belt | I21: -14.99 | J21: no
E22: JL092865B | H22: food petrol | I22: -930 | J22: no | K22: f1
H23: willow bday | I23: -150 | J23: no
H24: botox | I24: -130 | J24: no | K24: f1
H25: dental | I25: -20 | J25: no
H26: car insurance lv | I26: -27.7 | J26: no
H27: child benefit shit | I27: -90 | J27: no | K27: f1
H28: zoom | I28: -18 | J28: no
H29: gym | I29: -30 | J29: no
A30: NW | H30: boiler | I30: -14.5 | J30: no
A31: 1104841580 | H31: service | I31: -35 | J31: no | K31: f1
H32: matt | I32: -80 | J32: no
H33: pocket money | I33: -25 | J33: no
H34: help to by | I34: -130 | J34: no
H35: lunch | I35: -20 | J35: no | K35: f2
H36: nails | I36: -80 | J36: no | K36: f1
H37: christmas | I37: -50 | J37: no
H38: green waste | I38: -8 | J38: no
H39: health insurance | I39: -200 | J39: no
H40: bercleys | I40: -140 | J40: no
J41: no
J42: no
J43: no
J44: no
J45: no
J46: no
J47: no

Sheet dec25
A1: Money | E1: Savings Account | H1: Name | I1: Value | J1: Paid? | K1: Who
A2: Paid | B2: 5225 | H2: Mortgage | I2: -1268.67 | J2: no
A3: Taken Already | B3: =SUMIF(J2:J47,"Yes*",I2:I47) -> 0 | H3: isa | J3: no | K3: s
A4: Balance | B4: 5223 | E4: Dental 🪥 | F4: 5 | H4: LifeInsurance/aviva | I4: -39 | J4: no
A5: To Be Taken | B5: =SUMIF(J2:J47,"No",I2:I47) -> -5218.34 | E5: Vet Fund 😺 | F5: 525 | H5: HouseInsurance - Tesco | I5: -39 | J5: no
A6: Total | B6: =B5+B4 -> 4.66 | E6: christmas | F6: 509 | H6: TvLicence | I6: -15 | J6: no
A7: Francesca pt 1 | B7: =SUMIF(K2:K47,"f1",I2:I47) -> -2387.99 | H7: Gas/Electric | I7: -185 | J7: no
A8: Francesca pt 2 | B8: =SUMIF(K2:K47,"f2",I2:I47) -> -148 | H8: pet insur | I8: -40 | J8: no | K8: s
A9: Matt | B9: =SUMIF(K2:K47,"",I2:I47) -> -2642.35 | H9: spotoify | I9: -22 | J9: no
A10: Savings | B10: =SUMIF(K2:K47,"s",I2:I47) -> -40 | E10: TAX | H10: rumpus food | I10: -55 | J10: no
A11: Mortgage | E11: Saving Total | F11: =SUM(F2:F10) -> 1039 | H11: rumpus arun vet | I11: -7.99 | J11: no | K11: f1
A12: Main | B12: 151455.79 | C12: 27yrs 8 Months | H12: amazon | I12: -8.99 | J12: no
A13: Extra | B13: 80139.8 | C13: 0.0482 | E13: francesca Isa | F13: 22500 | H13: council tax | I13: -239 | J13: no
A14: Total Due | B14: =SUM(B12:B13) -> 231595.59 | E14: savings | F14: 1000 | H14: water | I14: -13 | J14: no
A15: H2B paybak | B15: =B16*0.2 -> 92000 | E15: botox | F15: 127 | H15: window clean | I15: -10 | J15: no
A16: Sold Price | B16: 460000 | E16: me | H16: water | I16: -58 | J16: no
A17: Equity | B17: =B16-SUM(B14:B15) -> 136404.41 | E17: matt bday | H17: hp | I17: -1.5 | J17: no
E18: matt gift | H18: DISHWASHER | I18: -5 | J18: no
E19: mattchristmas | H19: fran money for card | I19: -800 | J19: no | K19: f1
E20: christmas | H20: tesco mobiles | I20: -28 | J20: no | K20: f2
E21: FRANNYS MONEY | F21: =SUM(F15:F20) -> 127 | H21: green belt | I21: -14.99 | J21: no
E22: JL092865B | H22: food petrol | I22: -1170 | J22: no | K22: f1
H23: DINNER | I23: -70 | J23: no
H24: hlf term | I24: -200 | J24: no | K24: f1
H25: dental | I25: -20 | J25: no
H26: car insurance lv | I26: -27.7 | J26: no
H27: child benefit shit | I27: -90 | J27: no | K27: f1
H28: zoom | I28: -18 | J28: no
H29: new years | I29: -100 | J29: no | K29: f2
A30: NW | H30: boiler | I30: -14.5 | J30: no
A31: 1104841580 | H31: service | I31: -35 | J31: no | K31: f1
H32: matt | I32: -75 | J32: no
H33: pocket money | I33: -25 | J33: no
H34: help to by | I34: -130 | J34: no
H35: lunch | I35: -20 | J35: no | K35: f2
H36: nails | I36: -85 | J36: no | K36: f1
H37: christmas | I37: -200 | J37: no
H38: green waste | I38: -8 | J38: no
H39: mum and dad bday | I39: -50 | J39: no
H40: gym | I40: -30 | J40: no
J41: no
J42: no
J43: no
J44: no
J45: no
J46: no
J47: no

Sheet nov25
A1: Money | E1: Savings Account | H1: Name | I1: Value | J1: Paid? | K1: Who
A2: Paid | B2: 5237.04 | E2: Rainy Day 🌧️ | F2: 1 | H2: Mortgage | I2: -1268.67 | J2: yes
A3: Taken Already | B3: =SUMIF(J2:J47,"Yes*",I2:I47) -> -5240.45 | H3: westfields | I3: -70 | J3: yes | K3: s
A4: Balance | B4: 35.86 | E4: Dental 🪥 | F4: 5 | H4: LifeInsurance/aviva | I4: -39 | J4: yes
A5: To Be Taken | B5: =SUMIF(J2:J47,"No",I2:I47) -> -32.5 | E5: Vet Fund 😺 | F5: 525 | H5: HouseInsurance - Tesco | I5: -35 | J5: yes
A6: Total | B6: =B5+B4 -> 3.36 | E6: christmas | F6: 240 | H6: TvLicence | I6: -15 | J6: yes
A7: Francesca pt 1 | B7: =SUMIF(K2:K47,"f1",I2:I47) -> -2255.99 | H7: Gas/Electric | I7: -185 | J7: yes
A8: Francesca pt 2 | B8: =SUMIF(K2:K47,"f2",I2:I47) -> 0 | H8: pet insur | I8: -40 | J8: yes | K8: s
A9: Matt | B9: =SUMIF(K2:K47,"",I2:I47) -> -2871.96 | H9: spotoify | I9: -22 | J9: yes
A10: Savings | B10: =SUMIF(K2:K47,"s",I2:I47) -> -110 | E10: TAX | H10: rumpus food | I10: -55 | J10: yes
A11: Mortgage | E11: Saving Total | F11: =SUM(F2:F10) -> 771 | H11: rumpus arun vet | I11: -7.99 | J11: yes | K11: f1
A12: Main | B12: 151455.79 | C12: 27yrs 8 Months | H12: amazon | I12: -8.99 | J12: yes
A13: Extra | B13: 80139.8 | C13: 0.0482 | E13: francesca Isa | F13: 22057 | H13: council tax | I13: -239 | J13: yes
A14: Total Due | B14: =SUM(B12:B13) -> 231595.59 | E14: savings | F14: 1011 | H14: water | I14: -26 | J14: no
A15: H2B paybak | B15: =B16*0.2 -> 92000 | E15: s and shares | F15: 68.26 | H15: window clean | J15: no
A16: Sold Price | B16: 460000 | E16: me | H16: water | I16: -58 | J16: yes
A17: Equity | B17: =B16-SUM(B14:B15) -> 136404.41 | E17: matt bday | H17: hp | I17: -1.5 | J17: no
E18: matt gift | H18: DISHWASHER | I18: -5 | J18: no
E19: mattchristmas | H19: fran money for card | I19: -800 | J19: yes | K19: f1
B20: 579 | E20: christmas | H20: tesco mobiles | I20: -28 | J20: yes | K20: f1
B21: 245 teeth | E21: FRANNYS MONEY | F21: =SUM(F15:F20) -> 68.26 | H21: green belt | I21: -7.6 | J21: yes
B22: 334 | E22: JL092865B | H22: food petrol | I22: -930 | J22: yes | K22: f1
H23: fran credit card | I23: -210 | J23: yes | K23: f1
H24: credit card | I24: -131 | J24: yes
H25: dental | I25: -20 | J25: yes
H26: car insurance lv | I26: -27.7 | J26: yes
H27: child benefit shit | I27: -40 | J27: yes | K27: f1
H28: zoom | I28: -18 | J28: yes
H29: christmas | I29: -470 | J29: yes
A30: NW | H30: boiler | I30: -14.5 | J30: yes
A31: 1104841580 | H31: service | I31: -35 | J31: yes | K31: f1
H32: matt | I32: -60 | J32: yes
H33: pocket money | I33: -25 | J33: yes | K33: w
H34: help to by | I34: -130 | J34: yes
H35: lunch | I35: -20 | J35: yes | K35: f1
H36: nails | I36: -80 | J36: yes | K36: f1
H37: trip for h o p | I37: -10 | J37: yes | K37: w
H38: green waste | I38: -8 | J38: yes
H39: next | I39: -75 | J39: yes | K39: f1
H40: gym | I40: -30 | J40: yes | K40: f1
H41: cash | I41: -10 | J41: yes
H42: tickets | I42: -17 | J42: yes
J43: no
J44: no
J45: no
J46: no
J47: no

Sheet oct25
A1: Money | E1: Savings Account | H1: Name | I1: Value | J1: Paid? | K1: Who
A2: Paid | B2: 5223.85 | E2: Rainy Day 🌧️ | H2: Mortgage | I2: -1268.67 | J2: yes
A3: Taken Already | B3: =SUMIF(J2:J47,"Yes*",I2:I47) -> -5201.35 | H3: insurance | I3: -200 | J3: yes | K3: s
A4: Balance | B4: 84.44 | E4: Dental 🪥 | F4: 60 | H4: LifeInsurance/aviva | I4: -39 | J4: yes
A5: To Be Taken | B5: =SUMIF(J2:J47,"No",I2:I47) -> -80 | E5: Vet Fund 😺 | F5: 580 | H5: HouseInsurance - Tesco | I5: -39 | J5: yes
A6: Total | B6: =B5+B4 -> 4.44 | E6: christmas | F6: 185 | H6: TvLicence | I6: -15 | J6: yes
A7: Francesca pt 1 | B7: =SUMIF(K2:K47,"f1",I2:I47) -> -2031 | H7: Gas/Electric | I7: -185 | J7: yes
A8: Francesca pt 2 | B8: =SUMIF(K2:K47,"f2",I2:I47) -> -480 | H8: pet insur | I8: -20 | J8: yes | K8: s
A9: Matt | B9: =SUMIF(K2:K47,"",I2:I47) -> -2550.35 | H9: spotoify | I9: -20 | J9: yes
A10: Savings | B10: =SUMIF(K2:K47,"s",I2:I47) -> -220 | E10: TAX | H10: rumpus food | I10: -55 | J10: yes
A11: Mortgage | E11: Saving Total | F11: =SUM(F2:F10) -> 825 | H11: rumpus arun vet | I11: -8 | J11: yes | K11: f1
A12: Main | B12: 150603.12 | C12: 27yrs 8 Months | E12: emergancy fund | F12: 1011 | H12: amazon | I12: -8.99 | J12: yes
A13: Extra | B13: 79688.61 | C13: 0.0482 | E13: francesca Isa | F13: 22586.69 | H13: council tax | I13: -239 | J13: yes
A14: Total Due | B14: =SUM(B12:B13) -> 230291.73 | E14: s and shares isa | F14: 69.28 | H14: water | I14: -13 | J14: yes
A15: H2B paybak | B15: =B16*0.2 -> 92000 | H15: window clean | I15: -10 | J15: yes
A16: Sold Price | B16: 460000 | E16: me | H16: water | I16: -58 | J16: yes
A17: Equity | B17: =B16-SUM(B14:B15) -> 137708.27 | E17: matt bday | H17: hp | I17: -1.5 | J17: yes
H18: DISHWASHER | I18: -5 | J18: no
H19: fran money for card | I19: -800 | J19: yes | K19: f1
E20: christmas | H20: tesco mobiles | I20: -28 | J20: yes | K20: f1
E21: total | F21: =SUM(F11:F15) -> 24491.97 | H21: green belt | I21: -14.99 | J21: yes
E22: JL092865B | H22: food petrol | I22: -920 | J22: yes | K22: f1
H23: plummer | I23: -75 | J23: no
H24: credit card | J24: no | K24: f1
H25: dental | I25: -20 | J25: yes
H26: car insurance lv | I26: -27.7 | J26: yes
H27: child benefit shit | I27: -70 | J27: yes | K27: f1
H28: zoom | I28: -18 | J28: yes
H29: christmas | I29: -480 | J29: yes | K29: f2
A30: NW | H30: boiler | I30: -14.5 | J30: yes
A31: 1104841580 | H31: service | I31: -35 | J31: yes | K31: f1
H32: matt | I32: -80 | J32: yes
H33: pocket money | I33: -25 | J33: yes
H34: help to by | I34: -130 | J34: yes
H35: lunch | I35: -20 | J35: yes | K35: f1
H36: nails | I36: -20 | J36: yes | K36: f1
H37: half termm | I37: -100 | J37: yes | K37: f1
H38: green waste | I38: -8 | J38: yes
H39: london | I39: -100 | J39: yes
H40: gym | I40: -30 | J40: yes | K40: f1
H41: rumpus vet refund | I41: -80 | J41: yes
J43: no
J44: no
J45: no
J46: no
J47: no

Sheet sept25
A1: Money | E1: Savings Account | H1: Name | I1: Value | J1: Paid? | K1: Who
A2: Paid | B2: 5251.07 | E2: Rainy Day 🌧️ | F2: 50 | H2: Mortgage | I2: -1268.67 | J2: yes
A3: Taken Already | B3: =SUMIF(J2:J47,"Yes*",I2:I47) -> -5502.34 | J3: no | K3: s
A4: Balance | B4: 7.85 | E4: Dental 🪥 | F4: 110 | H4: LifeInsurance/aviva | I4: -39 | J4: yes
A5: To Be Taken | B5: =SUMIF(J2:J47,"No",I2:I47) -> -5 | E5: Vet Fund 😺 | F5: 520 | H5: HouseInsurance - Tesco | I5: -39 | J5: yes
A6: Total | B6: =B5+B4 -> 2.85 | E6: christmas | F6: 488 | H6: TvLicence | I6: -15 | J6: yes
A7: Francesca pt 1 | B7: =SUMIF(K2:K47,"f1",I2:I47) -> -2550.99 | H7: Gas/Electric | I7: -185 | J7: yes
A8: Francesca pt 2 | B8: =SUMIF(K2:K47,"f2",I2:I47) -> -220 | E8: Savings | H8: pet insur | J8: no | K8: s
A9: Matt | B9: =SUMIF(K2:K47,"",I2:I47) -> -2736.35 | H9: spotoify | I9: -20 | J9: yes
A10: Savings | B10: =SUMIF(K2:K47,"s",I2:I47) -> 0 | E10: TAX | H10: rumpus food | I10: -55 | J10: yes
A11: Mortgage | E11: Saving Total | F11: =SUM(F2:F10) -> 1168 | H11: rumpus arun vet | I11: -7.99 | J11: yes | K11: f1
A12: Main | B12: 151455.79 | C12: 27yrs 8 Months | H12: amazon | I12: -8.99 | J12: yes
A13: Extra | B13: 80139.8 | C13: 0.0482 | E13: francesca Isa | F13: 22590.67 | H13: council tax | I13: -239 | J13: yes
A14: Total Due | B14: =SUM(B12:B13) -> 231595.59 | E14: savings | F14: 1000 | H14: water | I14: -13 | J14: yes
A15: H2B paybak | B15: =B16*0.2 -> 97800 | E15: botox | F15: 126.97 | H15: window clean | J15: no
A16: Sold Price | B16: 489000 | E16: me | H16: water | I16: -58 | J16: yes
A17: Equity | B17: =B16-SUM(B14:B15) -> 159604.41 | E17: matt bday | H17: hp | I17: -1.5 | J17: yes
E18: matt meals | F18: 350 | H18: DISHWASHER | I18: -5 | J18: no
E19: mattchristmas | F19: 110 | H19: fran money for card | I19: -1000 | J19: yes | K19: f1
H20: tesco mobiles | I20: -28 | J20: yes | K20: f1
E21: FRANNYS MONEY | F21: =SUM(F15:F20) -> 586.97 | H21: green belt | I21: -14.99 | J21: yes
E22: JL092865B | H22: food petrol | I22: -1170 | J22: yes | K22: f1
H23: fran | I23: -50 | J23: yes
H24: credit card | I24: -200 | J24: yes | K24: f1
H25: dental | I25: -20 | J25: yes
H26: car insurance lv | I26: -27.7 | J26: yes
H27: child benefit shit | I27: -80 | J27: yes | K27: f1
H28: zoom | I28: -18 | J28: yes
H29: christmas | I29: -210 | J29: yes | K29: f2
A30: NW | H30: boiler | I30: -14.5 | J30: yes
A31: 1104841580 | H31: service | I31: -35 | J31: yes | K31: f1
H32: matt | I32: -50 | J32: yes
H33: pocket money | I33: -25 | J33: yes
H34: help to by | I34: -130 | J34: yes
H35: lunch | I35: -10 | J35: yes | K35: f2
H36: nails | I36: -60 | J36: yes
H37: matt credit | I37: -35 | J37: yes
H38: green waste | I38: -8 | J38: yes
H39: gym | I39: -30 | J39: yes | K39: f1
H40: matt | I40: -321 | J40: yes
H41: advent | I41: -8 | J41: yes
H42: ocado -7 | I42: -7 | J42: yes
J43: no
J44: no
J45: no
J46: no
J47: no

Sheet aug25
A1: Money | E1: Savings Account | H1: Name | I1: Value | J1: Paid? | K1: Who
A2: Paid | B2: 5245.45 | E2: Rainy Day 🌧️ | F2: 60 | H2: Mortgage | I2: -1268.67 | J2: yes
A3: Taken Already | B3: =SUMIF(J2:J47,"Yes*",I2:I47) -> -5212.11 | H3: isa | J3: no | K3: s
A4: Balance | B4: 133.01 | E4: Dental 🪥 | F4: 110 | H4: LifeInsurance/aviva | I4: -39 | J4: yes
A5: To Be Taken | B5: =SUMIF(J2:J47,"No",I2:I47) -> 0 | E5: Vet Fund 😺 | F5: 600 | H5: HouseInsurance - Tesco | I5: -39 | J5: yes
A6: Total | B6: =B5+B4 -> 133.01 | H6: TvLicence | I6: -15 | J6: yes
A7: Francesca pt 1 | B7: =SUMIF(K2:K47,"f1",I2:I47) -> -2137.99 | H7: Gas/Electric | I7: -185 | J7: yes
A8: Francesca pt 2 | B8: =SUMIF(K2:K47,"f2",I2:I47) -> -150 | E8: Savings | H8: pet insur | I8: -40 | J8: yes | K8: s
A9: Matt | B9: =SUMIF(K2:K47,"",I2:I47) -> -2884.12 | H9: spotoify | I9: -20 | J9: yes
A10: Savings | B10: =SUMIF(K2:K47,"s",I2:I47) -> -40 | E10: TAX | H10: rumpus food | I10: -55 | J10: yes
A11: Mortgage | E11: Saving Total | F11: =SUM(F2:F10) -> 770 | H11: rumpus arun vet | I11: -7.99 | J11: yes | K11: f1
A12: Main | B12: 151011.39 | H12: amazon | I12: -8.99 | J12: yes
A13: Extra | B13: 79904.64 | E13: francesca Isa | F13: 20000 | H13: council tax | I13: -239 | J13: yes
A14: Total Due | B14: =SUM(B12:B13) -> 230916.03 | E14: RICS and H2B | F14: 4000 | H14: water | I14: -13 | J14: yes
A15: H2B paybak | B15: =B16*0.2 -> 92000 | E15: botox | F15: 209.5 | H15: window clean | I15: -10 | J15: yes
A16: Sold Price | B16: 460000 | E16: me | H16: water | I16: -58 | J16: yes
A17: Equity | B17: =B16-SUM(B14:B15) -> 137083.97 | E17: matt trip | F17: 500 | H17: hp | I17: -1.5 | J17: yes
E18: matt gift | F18: 400 | H18: DISHWASHER | I18: -5 | J18: yes
E19: mattchristmas | F19: 200 | H19: fran money for card | I19: -800 | J19: yes | K19: f1
E20: christmas | F20: 351 | H20: tesco mobiles | I20: -28 | J20: yes | K20: f1
E21: FRANNYS MONEY | F21: =SUM(F15:F20) -> 1660.5 | H21: green belt | I21: -14.99 | J21: yes
E22: JL092865B | H22: food petrol | I22: -920 | J22: yes | K22: f1
H23: phone | I23: -11 | J23: yes
H24: next | I24: -47 | J24: yes | K24: f1
H25: dental | J25: no
H26: car insurance lv | I26: -27.7 | J26: yes
E27: NW | H27: child benefit shit | I27: -90 | J27: yes | K27: f1
E28: 1104841580 | H28: zoom | I28: -18 | J28: yes
H29: fran credit | I29: -120 | J29: yes | K29: f1
H30: boiler | I30: -14.5 | J30: yes
H31: service | I31: -35 | J31: yes | K31: f1
H32: matt | I32: -17 | J32: yes
H33: pocket money | I33: -25 | J33: yes
H34: help to by | I34: -130 | J34: yes
H35: christmas | I35: -150 | J35: yes | K35: f2
H36: nails | I36: -60 | J36: yes | K36: f1
H37: applee | I37: -11 | J37: yes
H38: green waste | I38: -8 | J38: yes
H39: summer holidays | I39: -400 | J39: yes
H40: gym | I40: -30 | J40: yes | K40: f1
H41: botox | I41: -115.5 | J41: yes
H42: france | I42: -114.27 | J42: yes
H43: lunch | I43: -20 | J43: yes
J44: no
J45: no
J46: no
J47: no

Sheet july25
A1: Money | D1: Savings Account | G1: Name | H1: Value | I1: Paid? | J1: Who
A2: Paid | B2: 5252.27 | D2: Rainy Day 🌧️ | E2: 80 | G2: Mortgage | H2: -1268.67 | I2: yes
A3: Taken Already | B3: =SUMIF(I2:I47,"Yes*",H2:H47) -> -5233.34 | G3: isa | I3: no | J3: s
A4: Balance | B4: 32.22 | D4: Dental 🪥 | E4: 110 | G4: LifeInsurance/aviva | H4: -39 | I4: yes
A5: To Be Taken | B5: =SUMIF(I2:I47,"No",H2:H47) -> 0 | D5: Vet Fund 😺 | E5: 560 | G5: HouseInsurance - Tesco | H5: -39 | I5: yes
A6: Total | B6: =B5+B4 -> 32.22 | G6: TvLicence | H6: -15 | I6: yes
A7: Francesca pt 1 | B7: =SUMIF(J2:J47,"f1",H2:H47) -> -2270.99 | D7: furnitiure | G7: Gas/Electric | H7: -155 | I7: yes
A8: Francesca pt 2 | B8: =SUMIF(J2:J47,"f2",H2:H47) -> -70 | D8: Savings | G8: pet insur | H8: -40 | I8: yes | J8: s
A9: Matt | B9: =SUMIF(J2:J47,"",H2:H47) -> -2852.35 | G9: spotoify | H9: -20 | I9: yes
A10: Savings | B10: =SUMIF(J2:J47,"s",H2:H47) -> -40 | D10: TAX | G10: rumpus food | H10: -55 | I10: yes
D11: Saving Total | E11: =SUM(E2:E10) -> 750 | G11: rumpus arun vet | H11: -7.99 | I11: yes | J11: f1
G12: amazon | H12: -8.99 | I12: yes
A13: Emergency Target | B13: 10000 | D13: francesca Isa | E13: 4025 | G13: council tax | H13: -239 | I13: yes
A14: Emergency Fund | B14: 4000 | G14: water | H14: -13 | I14: yes
A15: Emergency Left | D15: botox | E15: 208 | G15: window clean | H15: -10 | I15: yes
A16: Percentage | B16: =B14/B13 -> 0.4 | D16: me | E16: 200 | G16: water | H16: -57 | I16: yes
D17: matt trip | E17: 500 | G17: hp | H17: -1.5 | I17: yes
A18: Mortgage | D18: matt gift | E18: 400 | G18: DISHWASHER | H18: -5 | I18: yes
A19: Main | B19: 151455.79 | D19: mattchristmas | E19: 200 | G19: fran money for card | H19: -800 | I19: yes | J19: f1
A20: Extra | B20: 80139.8 | D20: christmas | E20: 200 | G20: tesco mobiles | H20: -28 | I20: yes | J20: f1
A21: Total Due | B21: =SUM(B19:B20) -> 231595.59 | D21: FRANNYS MONEY | E21: =SUM(E15:E20) -> 1708 | G21: green belt | H21: -14.99 | I21: yes
A22: H2B paybak | B22: =B23*0.2 -> 92000 | D22: JL092865B | G22: food petrol | H22: -900 | I22: yes | J22: f1
A23: Sold Price | B23: 460000 | G23: phone | H23: -11 | I23: yes
A24: Equity | B24: =B23-SUM(B21:B22) -> 136404.41 | G24: next | H24: -80 | I24: yes
G25: dental | H25: -20 | I25: yes
G26: car insurance lv | H26: -27.7 | I26: yes
G27: child benefit shit | I27: yes | J27: f1
G28: zoom | H28: -18 | I28: yes
I29: no
A30: NW | G30: boiler | H30: -14.5 | I30: yes
A31: 1104841580 | G31: service | H31: -35 | I31: yes | J31: f1
G32: matt | H32: -75 | I32: yes
G33: pocket money | H33: -20 | I33: yes
G34: help to by | H34: -130 | I34: yes
G35: school uniform | H35: -70 | I35: yes | J35: f2
G36: nails | H36: -60 | I36: yes
G37: applee | H37: -11 | I37: yes
G38: green waste | H38: -8 | I38: yes
G39: summer holidays | H39: -500 | I39: yes | J39: f1
G40: matt | H40: -136 | I40: yes
G41: portmerion | H41: -300 | I41: yes
I42: no
I43: no
I44: no
I45: no
I46: no
I47: no

Sheet xmas
A1: mum and dad | B1: 150
A2: natalie and tom
A3: willow
A6: anita and andrew | D6: in willows hsbc
A7: matts parents
A8: misc
A9: willows stocking | H9: lokin | I9: 15
A10: fran | H10: david | I10: 4
A11: get from will mummy | H11: aviv | I11: 10
A12: food | B12: 290 | H12: levi | I12: 10
A13: gift 4 daddy willow | H13: charlotte
D14: current | E14: 240 | H14: georgina
D15: nov | H15: realan | I15: 5
A16: total | B16: =SUM(B1:B15) -> 440 | D16: dec | E16: 200 | H16: jackson | I16: 5
E17: =SUM(E14:E16) -> 440 | H17: li
I18: =SUM(I9:I17) -> 49

Sheet june25
A1: Money | D1: Savings Account | G1: Name | H1: Value | I1: Paid? | J1: Who
A2: Paid | B2: 5155.71 | D2: Rainy Day 🌧️ | E2: 80 | G2: Mortgage | H2: -1268.67 | I2: yes
A3: Taken Already | B3: =SUMIF(I2:I47,"Yes*",H2:H47) -> -5436.97 | G3: isa | I3: no | J3: s
A4: Balance | B4: 31.91 | D4: Dental 🪥 | E4: 90 | G4: LifeInsurance/aviva | H4: -39 | I4: yes
A5: To Be Taken | B5: =SUMIF(I2:I47,"No",H2:H47) -> 0 | D5: Vet Fund 😺 | E5: 560 | G5: HouseInsurance - Tesco | H5: -35 | I5: yes
A6: Total | B6: =B5+B4 -> 31.91 | G6: TvLicence | H6: -9.75 | I6: yes
A7: Francesca pt 1 | B7: =SUMIF(J2:J47,"f1",H2:H47) -> -2392.99 | D7: silverstone | G7: Gas/Electric | H7: -155 | I7: yes
A8: Francesca pt 2 | B8: =SUMIF(J2:J47,"f2",H2:H47) -> -48 | D8: festival | G8: pet insur | I8: no | J8: s
A9: Matt | B9: =SUMIF(J2:J47,"",H2:H47) -> -2995.98 | G9: spotoify | H9: -20 | I9: yes
A10: Savings | B10: =SUMIF(J2:J47,"s",H2:H47) -> 0 | D10: TAX | G10: rumpus food | H10: -55 | I10: yes
D11: Saving Total | E11: =SUM(E2:E10) -> 730 | G11: rumpus arun vet | H11: -7.99 | I11: yes | J11: f1
G12: amazon | H12: -8.99 | I12: yes
A13: Emergency Target | B13: 10000 | D13: francesca Isa | E13: 4508.55 | G13: council tax | H13: -239 | I13: yes
A14: Emergency Fund | B14: 4508.55 | D14: FRANNYS MONEY | G14: water | H14: -13 | I14: yes
A15: Emergency Left | G15: window clean | H15: -10 | I15: yes
A16: Percentage | B16: =B14/B13 -> 0.450855 | G16: water | H16: -53.5 | I16: yes
G17: hp | H17: -1.5 | I17: yes
A18: Mortgage | D18: holiday | G18: DISHWASHER | H18: -5 | I18: yes
A19: Main | B19: 151288.74 | G19: fran money for card | H19: -1000 | I19: yes | J19: f1
A20: Extra | B20: 80051.41 | G20: tesco mobiles | H20: -28 | I20: yes | J20: f2
A21: Total Due | B21: =SUM(B19:B20) -> 231340.15 | G21: green belt | H21: -14.99 | I21: yes
A22: H2B paybak | B22: =B23*0.2 -> 92000 | D22: JL092865B | G22: food petrol | H22: -1150 | I22: yes | J22: f1
A23: Sold Price | B23: 460000 | G23: phone | H23: -11 | I23: yes
A24: Equity | B24: =B23-SUM(B21:B22) -> 136659.85 | G24: mattt | H24: -210 | I24: yes
G25: dental | H25: -20 | I25: yes
G26: car insurance lv | H26: -27.7 | I26: yes
G27: child benefit shit | H27: -80 | I27: yes | J27: f1
G28: zoom | H28: -18 | I28: yes
G29: dad bday | H29: -70 | I29: yes
A30: NW | G30: boiler | H30: -14.5 | I30: yes
A31: 1104841580 | G31: service | H31: -35 | I31: yes | J31: f1
G32: matt | H32: -100 | I32: yes
G33: pocket money | H33: -25 | I33: yes
G34: help to by | H34: -130 | I34: yes
G35: lunch | H35: -20 | I35: yes | J35: f2
G36: nails | H36: -120 | I36: yes | J36: f1
G37: applee | H37: -11 | I37: yes
G38: green waste | H38: -8 | I38: yes
G39: silverstone | H39: -50 | I39: yes
G40: festival of speed | H40: -50 | I40: yes
G41: credit card | H41: -322.38 | I41: yes
I42: no
I43: no
I44: no
I45: no
I46: no
I47: no

Sheet may25
A1: Money | D1: Savings Account | G1: Name | H1: Value | I1: Paid? | J1: Who
A2: Paid | B2: 5155.71 | D2: Rainy Day 🌧️ | E2: 80 | G2: Mortgage | H2: -1268.67 | I2: yes
A3: Taken Already | B3: =SUMIF(I2:I47,"Yes*",H2:H47) -> -5324.94 | G3: isa | H3: -200 | I3: yes | J3: s
A4: Balance | B4: 13.49 | D4: Dental 🪥 | E4: 70 | G4: LifeInsurance/vitality | H4: -39 | I4: yes
A5: To Be Taken | B5: =SUMIF(I2:I47,"No",H2:H47) -> 0 | D5: Vet Fund 😺 | E5: 560 | G5: HouseInsurance - Tesco | H5: -39 | I5: yes
A6: Total | B6: =B5+B4 -> 13.49 | G6: TvLicence | H6: -15 | I6: yes
A7: Francesca pt 1 | B7: =SUMIF(J2:J47,"f1",H2:H47) -> -2236.99 | D7: furnitiure | G7: Gas/Electric | H7: -155 | I7: yes
A8: Francesca pt 2 | B8: =SUMIF(J2:J47,"f2",H2:H47) -> -81 | D8: Savings | G8: pet insur | H8: -40 | I8: yes | J8: s
A9: Matt | B9: =SUMIF(J2:J47,"",H2:H47) -> -2766.95 | G9: spotoify | H9: -20 | I9: yes
A10: Savings | B10: =SUMIF(J2:J47,"s",H2:H47) -> -240 | D10: TAX | G10: rumpus food | H10: -25 | I10: yes
D11: Saving Total | E11: =SUM(E2:E10) -> 710 | G11: rumpus arun vet | H11: -7.99 | I11: yes | J11: f1
G12: amazon | H12: -8.99 | I12: yes
A13: Emergency Target | B13: 10000 | D13: francesca Isa | E13: 4500 | G13: council tax | H13: -239 | I13: yes
A14: Emergency Fund | B14: 4324 | D14: FRANNYS MONEY | G14: water | H14: -13 | I14: yes
A15: Emergency Left | G15: window clean | H15: -10 | I15: yes
A16: Percentage | B16: =B14/B13 -> 0.4324 | G16: water | H16: -53.5 | I16: yes
G17: hp | H17: -1.8 | I17: yes
A18: Mortgage | D18: holiday | G18: DISHWASHER | H18: -5 | I18: yes
A19: Main | B19: 151455.79 | G19: fran money for card | H19: -800 | I19: yes | J19: f1
A20: Extra | B20: 80139.8 | G20: tesco mobiles | H20: -28 | I20: yes | J20: f2
A21: Total Due | B21: =SUM(B19:B20) -> 231595.59 | G21: green belt | H21: -14.99 | I21: yes
A22: H2B paybak | B22: =B23*0.2 -> 92000 | D22: JL092865B | G22: food petrol | H22: -900 | I22: yes | J22: f1
A23: Sold Price | B23: 460000 | G23: phone | H23: -11 | I23: yes
A24: Equity | B24: =B23-SUM(B21:B22) -> 136404.41 | G24: fran credit | H24: -314 | I24: yes | J24: f1
G25: dental | H25: -20 | I25: yes
G26: car insurance lv | H26: -27.7 | I26: yes
G27: child benefit shit | H27: -80 | I27: yes | J27: f1
G28: zoom | H28: -18 | I28: yes
G29: gym | H29: -33 | I29: yes | J29: f2
A30: NW | G30: boiler | H30: -14.3 | I30: yes
A31: 1104841580 | G31: service | H31: -35 | I31: yes | J31: f1
G32: matt | H32: -100 | I32: yes
G33: pocket money | H33: -20 | I33: yes
G34: help to by | H34: -130 | I34: yes
G35: lunch | H35: -20 | I35: yes | J35: f2
G36: credit card | H36: -189 | I36: yes
G37: applee | H37: -11 | I37: yes
G38: green waste | H38: -8 | I38: yes
G39: half term | H39: -100 | I39: yes | J39: f1
G40: willows wardrobe | H40: -210 | I40: yes
G41: rainy day | H41: -25 | I41: yes
G42: fathers day | H42: -50 | I42: yes
G43: alison | H43: -25 | I43: yes
I44: no
I45: no
I46: no
I47: no

Sheet april25
A1: Money | D1: Savings Account | G1: Name | H1: Value | I1: Paid? | J1: Who
A2: Paid | B2: 5155.73 | D2: Rainy Day 🌧️ | E2: 75 | G2: Mortgage | H2: -1268.67 | I2: yes
A3: Taken Already | B3: =SUMIF(I2:I47,"Yes*",H2:H47) -> -5218.15 | G3: isa | H3: -270 | I3: yes | J3: s
A4: Balance | B4: 27.57 | D4: Dental 🪥 | E4: 50 | G4: LifeInsurance/aviva | H4: -37 | I4: yes
A5: To Be Taken | B5: =SUMIF(I2:I47,"No",H2:H47) -> 0 | D5: Vet Fund 😺 | E5: 550 | G5: HouseInsurance - Tesco | H5: -39 | I5: yes
A6: Total | B6: =B5+B4 -> 27.57 | G6: TvLicence | H6: -15 | I6: yes
A7: Francesca pt 1 | B7: =SUMIF(J2:J47,"f1",H2:H47) -> -2383 | D7: furnitiure | G7: Gas/Electric | H7: -155 | I7: yes
A8: Francesca pt 2 | B8: =SUMIF(J2:J47,"f2",H2:H47) -> -81 | D8: Savings | G8: pet insur | H8: -50 | I8: yes | J8: s
A9: Matt | B9: =SUMIF(J2:J47,"",H2:H47) -> -2434.15 | G9: spotoify | H9: -20 | I9: yes
A10: Savings | B10: =SUMIF(J2:J47,"s",H2:H47) -> -320 | D10: TAX | G10: rumpus food | H10: -25 | I10: yes
D11: Saving Total | E11: =SUM(E2:E10) -> 675 | I11: no
G12: amazon | H12: -8.99 | I12: yes
A13: Emergency Target | B13: 10000 | D13: francesca Isa | E13: 4324 | G13: council tax | H13: -239 | I13: yes
A14: Emergency Fund | B14: 4324 | D14: FRANNYS MONEY | G14: water | H14: -13 | I14: yes
A15: Emergency Left | G15: window clean | H15: -10 | I15: yes
A16: Percentage | B16: =B14/B13 -> 0.4324 | G16: water | H16: -53.3 | I16: yes
G17: hp | H17: -1.5 | I17: yes
A18: Mortgage | D18: holiday | G18: DISHWASHER | H18: -5 | I18: yes
A19: Main | B19: 153458.32 | G19: fran money for card | H19: -1000 | I19: yes | J19: f1
A20: Extra | B20: 81199.44 | G20: tesco mobiles | H20: -28 | I20: yes | J20: f2
A21: Total Due | B21: =SUM(B19:B20) -> 234657.76 | G21: green belt | H21: -14.99 | I21: yes
A22: H2B paybak | B22: =B23*0.2 -> 90000 | D22: JL092865B | G22: food petrol | H22: -1150 | I22: yes | J22: f1
A23: Sold Price | B23: 450000 | G23: phone | H23: -11 | I23: yes
A24: Equity | B24: =B23-SUM(B21:B22) -> 125342.24 | G24: greenbelt | H24: -14 | I24: yes
G25: dental | H25: -20 | I25: yes
G26: car insurance lv | H26: -27.7 | I26: yes
G27: child benefit shit | H27: -60 | I27: yes | J27: f1
G28: zoom | H28: -18 | I28: yes
G29: gym | H29: -33 | I29: yes | J29: f2
A30: NW | G30: boiler | H30: -12 | I30: yes
A31: 1104841580 | G31: service | H31: -35 | I31: yes | J31: f1
G32: matt | H32: -100 | I32: yes
G33: pocket money | H33: -20 | I33: yes
G34: help to by | H34: -142 | I34: yes
G35: lunch | H35: -20 | I35: yes | J35: f2
G36: credit card | H36: -138 | I36: yes | J36: f1
G37: applee | H37: -11 | I37: yes
G38: green waste | H38: -8 | I38: yes
G39: dishwasher | H39: -5 | I39: yes
G40: fran money for card | H40: -140 | I40: yes
I41: no
I42: no | J42: f1
I43: no | J43: f1
I44: no
I45: no
I46: no
I47: no

Sheet mar25
A1: Money | D1: Savings Account | G1: Name | H1: Value | I1: Paid? | J1: Who
A2: Paid | B2: 5140.92 | D2: Rainy Day 🌧️ | E2: 100 | G2: Mortgage | H2: -1268.67 | I2: yes
A3: Taken Already | B3: =SUMIF(I2:I47,"Yes*",H2:H47) -> -5590.16 | D3: Francesca Birthday | G3: isa | H3: -320 | I3: yes | J3: s
A4: Balance | B4: 48.01 | D4: Dental 🪥 | E4: 80 | G4: LifeInsurance/aviva | H4: -37 | I4: yes
A5: To Be Taken | B5: =SUMIF(I2:I47,"No",H2:H47) -> -19 | D5: Vet Fund 😺 | E5: 500 | G5: HouseInsurance - Tesco | H5: -39 | I5: yes
A6: Total | B6: =B5+B4 -> 29.01 | D6: matt | G6: TvLicence | H6: -15 | I6: yes
A7: Francesca pt 1 | B7: =SUMIF(J2:J47,"f1",H2:H47) -> -1920 | D7: oslo | E7: 150 | G7: Gas/Electric | H7: -155 | I7: yes
A8: Francesca pt 2 | B8: =SUMIF(J2:J47,"f2",H2:H47) -> -226 | D8: TRAIN TICKETS OSLO | G8: pet insur | H8: -50 | I8: yes | J8: s
A9: Matt | B9: =SUMIF(J2:J47,"",H2:H47) -> -3018.16 | D9: money for fran | G9: spotoify | H9: -20 | I9: yes
A10: Savings | B10: =SUMIF(J2:J47,"s",H2:H47) -> -445 | D10: TAX | E10: 162 | G10: rumpus food | H10: -55 | I10: yes | J10: s
D11: Saving Total | E11: =SUM(E2:E10) -> 992 | G11: FRAN BIRTHDAAY | H11: -135 | I11: yes
G12: amazon | H12: -8.99 | I12: yes
A13: Emergency Target | B13: 10000 | D13: francesca Isa | E13: 3917.77 | G13: council tax | H13: -239 | I13: yes
A14: Emergency Fund | B14: 3917.77 | D14: FRANNYS MONEY | G14: water | H14: -13 | I14: yes
A15: Emergency Left | G15: window clean | H15: -10 | I15: yes
A16: Percentage | B16: =B14/B13 -> 0.391777 | D16: nor holiday fund in matt | E16: 800 | G16: water | H16: -31.5 | I16: yes
G17: hp | H17: -1.5 | I17: yes
A18: Mortgage | D18: holiday | G18: DISHWASHER | H18: -5 | I18: no
A19: Main | B19: 153458.32 | G19: fran money for card | H19: -800 | I19: yes | J19: f1
A20: Extra | B20: 81199.44 | G20: tesco mobiles | H20: -28 | I20: yes | J20: f2
A21: Total Due | B21: =SUM(B19:B20) -> 234657.76 | G21: matt credit | H21: -32.5 | I21: yes
A22: H2B paybak | B22: =B23*0.2 -> 90000 | D22: JL092865B | G22: food petrol | H22: -900 | I22: yes | J22: f1
A23: Sold Price | B23: 450000 | G23: phone | H23: -11 | I23: yes
A24: Equity | B24: =B23-SUM(B21:B22) -> 125342.24 | D24: money for car | G24: greenbelt | H24: -14 | I24: no
G25: dental | H25: -20 | I25: yes | J25: s
G26: car insurance lv | H26: -31 | I26: yes
G27: child benefit shit | H27: -80 | I27: yes | J27: f1
G28: zoom | H28: -18 | I28: yes
G29: gym | H29: -33 | I29: yes | J29: f2
A30: NW | G30: boiler | H30: -12 | I30: yes
A31: 1104841580 | G31: SERVICE MONEY | H31: -165 | I31: yes | J31: f2
G32: matt | H32: -100 | I32: yes
G33: pocket money | H33: -20 | I33: yes
G34: help to by | H34: -127 | I34: yes
G35: lunch | I35: no | J35: f1
G36: conv | I36: no
G37: applee | H37: -11 | I37: yes
G38: alison | H38: -120 | I38: yes
G39: 5 week month | H39: -100 | I39: yes
G40: easter | H40: -30 | I40: yes
G41: green waste | H41: -8 | I41: yes
G42: fran credit card | H42: -80 | I42: yes | J42: f1
G43: trousers | H43: -60 | I43: yes | J43: f1
G44: fran birthday | H44: -100 | I44: yes
G45: petrol | H45: -30 | I45: yes
G46: fran money for card | H46: -35 | I46: yes
G47: dinner | H47: -240 | I47: yes

Sheet feb25
A1: Money | D1: Savings Account | G1: Name | H1: Value | I1: Paid? | J1: Who
A2: Paid | B2: 5346.82 | D2: Rainy Day 🌧️ | E2: 100 | G2: Mortgage | H2: -1268.67 | I2: yes
A3: Taken Already | B3: =SUMIF(I2:I47,"Yes*",H2:H47) -> -5598.73 | D3: Francesca Birthday | E3: 300 | I3: no | J3: s
A4: Balance | B4: 13.38 | D4: Dental 🪥 | E4: 89 | G4: LifeInsurance/aviva | H4: -37 | I4: yes
A5: To Be Taken | B5: =SUMIF(I2:I47,"No",H2:H47) -> 0 | D5: Vet Fund 😺 | E5: 550 | G5: HouseInsurance - Tesco | H5: -39 | I5: yes
A6: Total | B6: =B5+B4 -> 13.38 | D6: Willow Dinner | E6: 215 | G6: TvLicence | H6: -15 | I6: yes
A7: Francesca pt 1 | B7: =SUMIF(J2:J47,"f1",H2:H47) -> -1810 | D7: alison | G7: Gas/Electric | H7: -155 | I7: yes
A8: Francesca pt 2 | B8: =SUMIF(J2:J47,"f2",H2:H47) -> -61 | D8: willow bday | E8: 150 | G8: pet insur | H8: -50 | I8: yes | J8: s
A9: Matt | B9: =SUMIF(J2:J47,"",H2:H47) -> -3602.73 | D9: my face | E9: 220 | G9: spotoify | H9: -20 | I9: yes
A10: Savings | B10: =SUMIF(J2:J47,"s",H2:H47) -> -125 | D10: Train | E10: 63 | G10: rumpus food | H10: -55 | I10: yes | J10: s
D11: Saving Total | E11: =SUM(E2:E10) -> 1687 | G11: netflix | I11: no
G12: amazon | H12: -8.99 | I12: yes
A13: Emergency Target | B13: 10000 | D13: francesca Isa | E13: 5145.97 | G13: council tax | H13: -225 | I13: yes
A14: Emergency Fund | B14: =E12+E13 -> 5145.97 | D14: FRANNYS MONEY | E14: 1175 | G14: water | H14: -13 | I14: yes
A15: Emergency Left | B15: =B13-B14 -> 4854.03 | G15: window clean | H15: -10 | I15: yes | J15: f1
A16: Percentage | B16: =B14/B13 -> 0.514597 | D16: nor holiday fund in matt | E16: 799.91 | G16: water | H16: -31.5 | I16: yes
G17: hp | H17: -1.5 | I17: yes
A18: Mortgage | G18: DISHWASHER | H18: -5 | I18: yes
A19: Main | B19: 152191.25 | G19: fran money for card | H19: -800 | I19: yes | J19: f1
A20: Extra | B20: 80528.96 | G20: tesco mobiles | H20: -28 | I20: yes | J20: f2
A21: Total Due | B21: =SUM(B19:B20) -> 232720.21 | G21: credit card | H21: -20 | I21: yes | J21: f1
A22: H2B paybak | B22: =B23*0.2 -> 95000 | G22: food petrol | H22: -900 | I22: yes | J22: f1
A23: Sold Price | B23: 475000 | G23: phone | H23: -11 | I23: yes
A24: Equity | B24: =B23-SUM(B21:B22) -> 147279.79 | G24: greenbelt | H24: -7.6 | I24: yes
G25: dental | H25: -20 | I25: yes | J25: s
G26: car insurance lv | H26: -31 | I26: yes
G27: child benefit shit | H27: -80 | I27: yes | J27: f1
G28: zoom | H28: -18 | I28: yes
A29: JL092865B | G29: gym | H29: -33 | I29: yes | J29: f2
A30: NW | G30: boiler | H30: -12 | I30: yes
A31: 1104841580 | G31: service | H31: -33 | I31: yes
G32: matt | H32: -100 | I32: yes
G33: pocket money | H33: -20 | I33: yes
G34: help to by | H34: -127 | I34: yes
G35: lunch | H35: -20 | I35: yes
G36: backpack | H36: -23 | I36: yes
G37: appl | H37: -11 | I37: yes
G38: matt credit card | H38: -413.46 | I38: yes
G39: face | H39: -220 | I39: yes
G40: washing machine | H40: -332.67 | I40: yes
G41: fran saving | H41: -150 | I41: yes
G42: Alison Cat | H42: -120 | I42: yes
G43: willow birthday | H43: -100 | I43: yes
G44: ebay | H44: -33.34 | I44: yes
I45: no
I46: no
I47: no

Sheet jan25
A1: Money | D1: Savings Account | G1: Name | H1: Value | I1: Paid? | J1: Who | K1: Category
A2: Paid | B2: 5188.49 | G2: Mortgage | H2: -1261.98 | I2: yes | K2: House
A3: Taken Already | B3: =SUMIF(I2:I47,"Yes*",H2:H47) -> -5326.46 | D3: Rainy Day 🌧️ | E3: 50 | G3: dad paint | H3: -350 | I3: yes | J3: s | K3: Savings
A4: Balance | B4: 4.73 | D4: Francesca Birthday | E4: 300 | G4: LifeInsurance/aviva | H4: -37 | I4: yes | K4: Insurance
A5: To Be Taken | B5: =SUMIF(I2:I47,"No",H2:H47) -> 0 | D5: Dental 🪥 | G5: HouseInsurance - Tesco | H5: -39 | I5: yes | K5: Insurance
A6: Total | B6: =B5+B4 -> 4.73 | D6: Vet Fund 😺 | E6: 530 | G6: TvLicence | H6: -15 | I6: yes | K6: HouseBill
A7: Francesca pt 1 | B7: =SUMIF(J2:J47,"f1",H2:H47) -> -2025 | D7: Willow Dinner | E7: 200 | G7: Gas/Electric | H7: -155 | I7: yes | K7: HouseBill
A8: Francesca pt 2 | B8: =SUMIF(J2:J47,"f2",H2:H47) -> -61 | D8: kettle | E8: 221 | G8: pet insur | H8: -50 | I8: yes | J8: s | K8: Insurance
A9: Matt | B9: =SUMIF(J2:J47,"",H2:H47) -> -2773.46 | D9: willow bday | E9: 150 | G9: spotoify | H9: -20 | I9: yes | K9: Subscription
A10: Savings | B10: =SUMIF(J2:J47,"s",H2:H47) -> -467 | G10: rumpus food | H10: -67 | I10: yes | J10: s | K10: Savings
D11: Saving Total | E11: =SUM(E2:E10) -> 1451 | G11: netflix | H11: -4.99 | I11: yes | K11: Subscription
D12: Emergency Fund | G12: amazon | H12: -8.99 | I12: yes | K12: Subscription
A13: Emergency Target | B13: 10000 | D13: francesca Isa | E13: 5145.97 | G13: council tax | H13: -225 | I13: yes | K13: HouseBill
A14: Emergency Fund | B14: =E12+E13 -> 5145.97 | D14: FRANNYS MONEY | E14: 1455 | G14: water | H14: -13 | I14: yes | K14: HouseBill
A15: Emergency Left | B15: =B13-B14 -> 4854.03 | G15: window clean | I15: no | K15: HouseBill
A16: Percentage | B16: =B14/B13 -> 0.514597 | D16: nor holiday fund in matt | E16: 595 | G16: water | H16: -31.5 | I16: yes | K16: HouseBill
G17: hp | H17: -1.5 | I17: yes | K17: Subscription
A18: Mortgage | D18: holiday | G18: DISHWASHER | H18: -5 | I18: yes | K18: Insurance
A19: Main | B19: 153458.32 | G19: fran money for card | H19: -800 | I19: yes | J19: f1 | K19: Francesca
A20: Extra | B20: 81199.44 | G20: tesco mobiles | H20: -28 | I20: yes | J20: f2 | K20: Mobile
A21: Total Due | B21: =SUM(B19:B20) -> 234657.76 | G21: credit card | H21: -245 | I21: yes | J21: f1 | K21: Francesca
A22: H2B paybak | B22: =B23*0.2 -> 90000 | D22: JL092865B | G22: food petrol | H22: -900 | I22: yes | J22: f1 | K22: Food
A23: Sold Price | B23: 450000 | G23: phone | H23: -11 | I23: yes | K23: Mobile
A24: Equity | B24: =B23-SUM(B21:B22) -> 125342.24 | G24: greenbelt | H24: -7.6 | I24: yes | K24: HouseBill
G25: next | I25: no | J25: s | K25: Savings
G26: car insurance lv | H26: -31 | I26: yes | K26: Insurance
G27: child benefit shit | H27: -80 | I27: yes | J27: f1 | K27: Francesca
G28: zoom | H28: -18 | I28: yes | K28: HouseBill
G29: gym | H29: -33 | I29: yes | J29: f2 | K29: Francesca
A30: NW | G30: boiler | H30: -12 | I30: yes | K30: HouseBill
A31: 1104841580 | G31: service | H31: -33 | I31: yes | K31: Savings
G32: matt | H32: -100 | I32: yes | K32: Spending
G33: pocket money | H33: -20 | I33: yes | K33: Medical
G34: help to by | H34: -127 | I34: yes | K34: House
G35: lunch | H35: -20 | I35: yes | K35: Savings
G36: sky sports | H36: -27 | I36: yes | K36: Francesca
G37: dental | H37: -20 | I37: yes | K37: Francesca
G38: matt credit card | H38: -35.9 | I38: yes
G39: beth | H39: -40 | I39: yes
G40: PAINT | H40: -140 | I40: yes
G41: NORWAY | H41: -150 | I41: yes
G42: WILLOW bday | H42: -150 | I42: yes
G43: phone | H43: -8 | I43: yes
G44: D AND G | H44: -5 | I44: yes
I45: no
I46: no
I47: no

Sheet minium 25
A1: Money | D1: Savings Account | G1: Name | H1: Value | I1: Paid? | J1: Who | K1: fixed
A2: Paid | B2: 5225 | D2: Rainy Day 🌧️ | E2: 80 | G2: Mortgage | H2: -1117 | I2: no | K2: yes
A3: Taken Already | B3: =SUMIF(I2:I47,"Yes*",H2:H47) -> 0 | G3: stock and share | H3: -140 | I3: no | J3: s
A4: Balance | B4: 5225 | D4: Dental 🪥 | E4: 110 | G4: LifeInsurance/aviva | H4: -39 | I4: no | K4: yes
A5: To Be Taken | B5: =SUMIF(I2:I47,"No",H2:H47) -> -4627.67 | D5: Vet Fund 😺 | E5: 560 | G5: HouseInsurance - Tesco | H5: -39 | I5: no | K5: yes
A6: Total | B6: =B5+B4 -> 597.33 | G6: TvLicence | H6: -17 | I6: no | K6: yes
A7: Francesca pt 1 | B7: =SUMIF(J2:J47,"f1",H2:H47) -> -2032.99 | D7: furnitiure | G7: Gas/Electric | H7: -200 | I7: no | K7: yes
A8: Francesca pt 2 | B8: =SUMIF(J2:J47,"f2",H2:H47) -> -181 | D8: Savings | G8: pet insur | H8: -40 | I8: no | J8: s | K8: yes
A9: Matt | B9: =SUMIF(J2:J47,"",H2:H47) -> -2233.68 | G9: spotoify | H9: -20 | I9: no
A10: Savings | B10: =SUMIF(J2:J47,"s",H2:H47) -> -180 | D10: TAX | G10: rumpus food | H10: -55 | I10: no
D11: Saving Total | E11: =SUM(E2:E10) -> 750 | G11: rumpus arun vet | H11: -7.99 | I11: no | J11: f1 | K11: yes
G12: amazon | H12: -8.99 | I12: no
A13: Emergency Target | B13: 10000 | D13: francesca Isa | E13: 4324 | G13: council tax | H13: -239 | I13: no | K13: y
A14: Emergency Fund | B14: 4324 | D14: FRANNYS MONEY | G14: water | H14: -26 | I14: no | K14: y
A15: Emergency Left | G15: window clean | H15: -10 | I15: no
A16: Percentage | B16: =B14/B13 -> 0.4324 | G16: water | H16: -58 | I16: no | K16: y
G17: hp | H17: -1.5 | I17: no
A18: Mortgage | D18: holiday | G18: DISHWASHER | H18: -5 | I18: no
A19: Main | B19: 151455.79 | G19: fran money for card | H19: -800 | I19: no | J19: f1 | K19: y
A20: Extra | B20: 80139.8 | G20: tesco mobiles | H20: -28 | I20: no | J20: f2 | K20: y
A21: Total Due | B21: =SUM(B19:B20) -> 231595.59 | G21: green belt | H21: -14.99 | I21: no | K21: y
A22: H2B paybak | B22: =B23*0.2 -> 92000 | D22: JL092865B | G22: food petrol | H22: -930 | I22: no | J22: f1 | K22: y
A23: Sold Price | B23: 460000 | G23: willow bday | I23: no
A24: Equity | B24: =B23-SUM(B21:B22) -> 136404.41 | G24: botox | H24: -70 | I24: no | J24: f1
G25: dental | H25: -20 | I25: no
G26: car insurance lv | H26: -27.7 | I26: no | K26: y
G27: child benefit shit | H27: -90 | I27: no | J27: f1
G28: zoom | H28: -18 | I28: no
G29: 5 week month | H29: -133 | I29: no | J29: f2
A30: NW | G30: boiler | H30: -14.5 | I30: no
A31: 1104841580 | G31: service | H31: -35 | I31: no | J31: f1
G32: matt | H32: -60 | I32: no
G33: pocket money | H33: -25 | I33: no
G34: help to by | H34: -130 | I34: no
G35: lunch | H35: -20 | I35: no | J35: f2
G36: nails | H36: -100 | I36: no | J36: f1
G37: christma | H37: -50 | I37: no
G38: green waste | H38: -8 | I38: no
I39: no
G40: gym | H40: -30 | I40: no
I41: no
I42: no
I43: no
I44: no
I45: no
I46: no
I47: no

Sheet dec24
A1: Money | D1: Savings Account | G1: Name | H1: Value | I1: Paid? | J1: Who | K1: Category
A2: Paid | B2: 5176.06 | G2: Mortgage | H2: -1268.67 | I2: yes | K2: House
A3: Taken Already | B3: =SUMIF(I2:I47,"Yes*",H2:H47) -> -5152.25 | D3: Rainy Day 🌧️ | E3: 50 | G3: botox | H3: -210 | I3: yes | J3: s | K3: Savings
A4: Balance | B4: 19.45 | D4: health insure | E4: 100 | G4: LifeInsurance/aviva | H4: -37 | I4: yes | K4: Insurance
A5: To Be Taken | B5: =SUMIF(I2:I47,"No",H2:H47) -> -16 | D5: Dental 🪥 | E5: 100 | G5: HouseInsurance - Tesco | H5: -39 | I5: yes | K5: Insurance
A6: Total | B6: =B5+B4 -> 3.45 | D6: Vet Fund 😺 | E6: 580 | G6: TvLicence | H6: -15 | I6: yes | K6: HouseBill
A7: Francesca pt 1 | B7: =SUMIF(J2:J47,"f1",H2:H47) -> -2400 | D7: face | E7: 370 | G7: Gas/Electric | H7: -155 | I7: yes | K7: HouseBill
A8: Francesca pt 2 | B8: =SUMIF(J2:J47,"f2",H2:H47) -> -171 | D8: phone | G8: pet insur | H8: -50 | I8: yes | J8: s | K8: Insurance
A9: Matt | B9: =SUMIF(J2:J47,"",H2:H47) -> -2287.25 | D9: Christmas 🎄 | G9: spotoify | H9: -20 | I9: yes | K9: Subscription
A10: Savings | B10: =SUMIF(J2:J47,"s",H2:H47) -> -310 | D10: xmas trip | G10: rumpus food | H10: -30 | I10: yes | J10: f2 | K10: Savings
D11: Saving Total | E11: =SUM(E2:E10) -> 1200 | G11: netflix | H11: -4.99 | I11: yes | K11: Subscription
D12: Emergency Fund | G12: breakdown | H12: -38 | I12: yes | K12: Subscription
A13: Emergency Target | B13: 12000 | D13: francesca Isa | E13: 5135.7 | G13: council tax | H13: -225 | I13: yes | K13: HouseBill
A14: Emergency Fund | B14: =E12+E13 -> 5135.7 | D14: LV handbag fund | E14: 1453 | G14: water | H14: -13 | I14: yes | K14: HouseBill
A15: Emergency Left | B15: =B13-B14 -> 6864.3 | D15: car fix fund | G15: window clean | I15: no | K15: HouseBill
A16: Percentage | B16: =B14/B13 -> 0.427975 | D16: nor holiday fund in matt | E16: 445 | G16: water | H16: -31.5 | I16: yes | K16: HouseBill
G17: hp | H17: -1.5 | I17: yes | K17: Subscription
A18: Mortgage | D18: holiday | G18: DISHWASHER | H18: -5 | I18: no | K18: Insurance
A19: Main | B19: 152053.12 | G19: fran money for card | H19: -1000 | I19: yes | J19: f1 | K19: Francesca
A20: Extra | B20: 80455.88 | G20: tesco mobiles | H20: -28 | I20: yes | J20: f2 | K20: Mobile
A21: Total Due | B21: =SUM(B19:B20) -> 232509 | G21: credit card | H21: -40 | I21: yes | J21: f1 | K21: Francesca
A22: H2B paybak | B22: =B23*0.2 -> 90000 | D22: JL092865B | G22: food petrol | H22: -1100 | I22: yes | J22: f1 | K22: Food
A23: Sold Price | B23: 450000 | G23: phone | H23: -11 | I23: no | K23: Mobile
A24: Equity | B24: =B23-SUM(B21:B22) -> 127491 | G24: greenbelt | H24: -7.6 | I24: yes | K24: HouseBill
G25: cat food | H25: -30 | I25: yes | J25: s | K25: Savings
G26: car insurance lv | H26: -31 | I26: yes | K26: Insurance
G27: child benefit shit | H27: -80 | I27: yes | J27: f1 | K27: Francesca
G28: zoom | H28: -18 | I28: yes | K28: HouseBill
G29: gym | H29: -33 | I29: yes | J29: f2 | K29: Francesca
A30: NW | G30: boiler | H30: -12 | I30: yes | K30: HouseBill
A31: 1104841580 | G31: service | H31: -33 | I31: yes | K31: Savings
G32: matt | H32: -50 | I32: yes | K32: Spending
G33: pocket money | H33: -20 | I33: yes | J33: s | K33: Medical
G34: help to by | H34: -127 | I34: yes | K34: House
G35: christmas hols | H35: -180 | I35: yes | J35: f1 | K35: Savings
G36: sky sports | H36: -27 | I36: yes | K36: Francesca
G37: new year | H37: -80 | I37: yes | J37: f2 | K37: Francesca
G38: bartley | H38: -108 | I38: yes
G39: amazon | H39: -8.99 | I39: yes
I40: no
I41: no
I42: no
I43: no
I44: no
I45: no
I46: no
I47: no

Sheet nov24
A1: Money | D1: Savings Account | G1: Name | H1: Value | I1: Paid? | J1: Who | K1: Category
A2: Paid | B2: 5237.78 | G2: Mortgage | H2: -1268.67 | I2: yes | K2: House
A3: Taken Already | B3: =SUMIF(I2:I47,"Yes*",H2:H47) -> -5301.39 | D3: Rainy Day 🌧️ | E3: 100 | G3: plummer | H3: -250 | I3: yes | J3: s | K3: Savings
A4: Balance | B4: 38.48 | D4: health insure | E4: 100 | G4: LifeInsurance/aviva | H4: -37 | I4: yes | K4: Insurance
A5: To Be Taken | B5: =SUMIF(I2:I47,"No",H2:H47) -> -31 | D5: Dental 🪥 | E5: 100 | G5: HouseInsurance - Tesco | H5: -35 | I5: yes | K5: Insurance
A6: Total | B6: =B5+B4 -> 7.48 | D6: Vet Fund 😺 | E6: 550 | G6: TvLicence | H6: -15 | I6: yes | K6: HouseBill
A7: Francesca pt 1 | B7: =SUMIF(J2:J47,"f1",H2:H47) -> -1966 | D7: face money | E7: 160 | G7: Gas/Electric | H7: -155 | I7: yes | K7: HouseBill
A8: Francesca pt 2 | B8: =SUMIF(J2:J47,"f2",H2:H47) -> -61 | D8: phone | G8: pet insur | H8: -80 | I8: yes | J8: s | K8: Insurance
A9: Matt | B9: =SUMIF(J2:J47,"",H2:H47) -> -2855.39 | D9: Christmas 🎄 | G9: spotoify | H9: -20 | I9: yes | K9: Subscription
A10: Savings | B10: =SUMIF(J2:J47,"s",H2:H47) -> -450 | D10: xmas trip | G10: health insurance | H10: -100 | I10: yes | J10: s | K10: Savings
D11: Saving Total | E11: =SUM(E2:E10) -> 1010 | G11: netflix | H11: -4.99 | I11: yes | K11: Subscription
D12: Emergency Fund | G12: zoom | H12: -18 | I12: yes | K12: Subscription
A13: Emergency Target | B13: 12000 | D13: francesca Isa | E13: 5111.07 | G13: council tax | H13: -225 | I13: yes | K13: HouseBill
A14: Emergency Fund | B14: =E12+E13 -> 5111.07 | D14: LV handbag fund | E14: 1345.57 | G14: water | H14: -13 | I14: yes | K14: HouseBill
A15: Emergency Left | B15: =B13-B14 -> 6888.93 | D15: car fix fund | E15: 1370 | G15: window clean | H15: -10 | I15: yes | K15: HouseBill
A16: Percentage | B16: =B14/B13 -> 0.4259225 | G16: water | H16: -31.5 | I16: yes | K16: HouseBill
G17: hp | H17: -1.5 | I17: yes | K17: Subscription
A18: Mortgage | G18: DISHWASHER | H18: -5 | I18: yes | K18: Insurance
A19: Main | B19: 152415.81 | G19: fran money for card | H19: -800 | I19: yes | J19: f1 | K19: Francesca
A20: Extra | B20: 80647.8 | G20: tesco mobiles | H20: -28 | I20: yes | J20: f2 | K20: Mobile
A21: Total Due | B21: =SUM(B19:B20) -> 233063.61 | G21: credit card | H21: -186 | I21: yes | J21: f1 | K21: Francesca
A22: H2B paybak | B22: =B23*0.2 -> 90000 | G22: food petrol | H22: -900 | I22: yes | J22: f1 | K22: Food
A23: Sold Price | B23: 450000 | G23: phone | H23: -11 | I23: yes | K23: Mobile
A24: Equity | B24: =B23-SUM(B21:B22) -> 126936.39 | G24: greenbelt | H24: -7.6 | I24: yes | K24: HouseBill
G25: next | I25: no | J25: s | K25: Savings
A26: JL092865B | G26: car insurance lv | H26: -31 | I26: yes | K26: Insurance
G27: child benefit shit | H27: -80 | I27: yes | J27: f1 | K27: Francesca
G28: zoom | H28: -18 | I28: no | K28: HouseBill
G29: gym | H29: -33 | I29: yes | J29: f2 | K29: Francesca
A30: NW | G30: boiler | H30: -12 | I30: yes | K30: HouseBill
A31: 1104841580 | G31: service | H31: -33 | I31: yes | K31: Savings
G32: matt | H32: -100 | I32: yes | K32: Spending
G33: dental | H33: -20 | I33: yes | J33: s | K33: Medical
G34: help to by | H34: -127 | I34: yes | K34: House
G35: christmas frank | I35: no | K35: Savings
G36: sky sports | H36: -27 | I36: yes | K36: Francesca
G37: christmas | H37: -100 | I37: yes | K37: Francesca
G38: christmas food | H38: -150 | I38: yes
G39: matt credit | H39: -236.13 | I39: yes
G40: matt christmas | H40: -150 | I40: yes
G41: ebay | H41: -13 | I41: no
I42: no
I43: no
I44: no
I45: no
I46: no
I47: no

Sheet oct24
A1: Money | D1: Savings Account | G1: Name | H1: Value | I1: Paid? | J1: Who | K1: Category
A2: Paid | B2: 5147.97 | G2: Mortgage | H2: -1268.67 | I2: yes | K2: House
A3: Taken Already | B3: =SUMIF(I2:I47,"Yes*",H2:H47) -> -5776.4 | D3: Rainy Day 🌧️ | E3: 100 | G3: botox | H3: -230 | I3: yes | K3: Savings
A4: Balance | B4: 56.22 | D4: HEALTH INSURANCE | E4: 100 | G4: LifeInsurance/aviva | H4: -37 | I4: yes | K4: Insurance
A5: To Be Taken | B5: =SUMIF(I2:I47,"No",H2:H47) -> 0 | D5: Dental 🪥 | E5: 80 | G5: HouseInsurance - Tesco | H5: -39 | I5: yes | K5: Insurance
A6: Total | B6: =B5+B4 -> 56.22 | D6: Vet Fund 😺 | E6: 570 | G6: TvLicence | H6: -15 | I6: yes | K6: HouseBill
A7: Francesca pt 1 | B7: =SUMIF(J2:J47,"f1",H2:H47) -> -1700 | D7: next month | G7: Gas/Electric | H7: -155 | I7: yes | K7: HouseBill
A8: Francesca pt 2 | B8: =SUMIF(J2:J47,"f2",H2:H47) -> -28 | D8: phone | G8: pet insur | H8: -50 | I8: yes | J8: s | K8: Insurance
A9: Matt | B9: =SUMIF(J2:J47,"",H2:H47) -> -3978.4 | D9: Christmas francesca🎄 | E9: 73 | G9: spotoify | H9: -20 | I9: yes | K9: Subscription
A10: Savings | B10: =SUMIF(J2:J47,"s",H2:H47) -> -70 | G10: zoom | H10: -18 | I10: yes | K10: Savings
D11: Saving Total | E11: =SUM(E2:E10) -> 923 | G11: netflix | H11: -4.99 | I11: yes | K11: Subscription
D12: Emergency Fund | G12: franny phone | H12: -80 | I12: yes | K12: Subscription
A13: Emergency Target | B13: 12000 | D13: francesca Isa | E13: 5095.24 | G13: council tax | H13: -225 | I13: yes | K13: HouseBill
A14: Emergency Fund | B14: =E12+E13 -> 5095.24 | D14: bag | E14: 1341.51 | G14: water | H14: -13 | I14: yes | K14: HouseBill
A15: Emergency Left | B15: =B13-B14 -> 6904.76 | D15: car fix fund | E15: 1270 | G15: window clean | H15: -10 | I15: yes | K15: HouseBill
A16: Percentage | B16: =B14/B13 -> 0.42460333 | G16: water | H16: -31.5 | I16: yes | K16: HouseBill
G17: hp | H17: -1.5 | I17: yes | K17: Subscription
A18: Mortgage | D18: holiday | G18: DISHWASHER | H18: -5 | I18: yes | K18: Insurance
A19: Main | B19: 153458.32 | G19: fran money for card | H19: -185 | I19: yes | J19: f1 | K19: Francesca
A20: Extra | B20: 81199.44 | G20: tesco mobiles | H20: -28 | I20: yes | J20: f2 | K20: Mobile
A21: Total Due | B21: =SUM(B19:B20) -> 234657.76 | G21: credit card | H21: -85 | I21: yes | J21: f1 | K21: Francesca
A22: H2B paybak | B22: =B23*0.2 -> 90000 | D22: JL092865B | G22: food petrol | H22: -1100 | I22: yes | J22: f1 | K22: Food
A23: Sold Price | B23: 450000 | G23: phone | H23: -11 | I23: yes | K23: Mobile
A24: Equity | B24: =B23-SUM(B21:B22) -> 125342.24 | G24: greenbelt | H24: -7.6 | I24: yes | K24: HouseBill
G25: next | H25: -30 | I25: yes | K25: Savings
G26: car insurance lv | H26: -31 | I26: yes | K26: Insurance
G27: child benefit shit | H27: -80 | I27: yes | J27: f1 | K27: Francesca
G28: zoom | H28: -18 | I28: yes | K28: HouseBill
G29: credit card | H29: -657.22 | I29: yes | K29: Francesca
A30: NW | G30: boiler | H30: -12 | I30: yes | K30: HouseBill
A31: 1104841580 | G31: service | H31: -33 | I31: yes | K31: Savings
G32: matt | H32: -100 | I32: yes | K32: Spending
G33: dental | H33: -20 | I33: yes | J33: s | K33: Medical
G34: help to by | H34: -127 | I34: yes | K34: House
G35: half term | H35: -150 | I35: yes | K35: Savings
G36: sky sports | H36: -27 | I36: yes | K36: Francesca
G37: klana | H37: -620.92 | I37: yes | K37: Francesca
G38: isa | H38: -250 | I38: yes | J38: f1
I39: no
I40: no
I41: no
I42: no
I43: no
I44: no
I45: no
I46: no
I47: no

Sheet may24
A1: Money | D1: Savings Account | G1: Name | H1: Value | I1: Paid? | J1: Who
A2: Paid | B2: 4954.81 | D2: holday fund | E2: 335 | G2: Mortgage | H2: -1268.67 | I2: yes
A3: Taken Already | B3: =SUMIF(I2:I28,"Yes*",H2:H28) -> -4331.95 | D3: rainy day fund | E3: 111 | G3: Car | H3: -244.8 | I3: yes | J3: f2
A4: Balance | B4: 53.12 | D4: service fund | E4: 250 | G4: LifeInsurance/aviva | H4: -33 | I4: yes
A5: To Be Taken | B5: =SUMIF(I2:I37,"No",H2:H37) -> -10 | D5: dental | E5: 95 | G5: HouseInsurance - Tesco | H5: -39 | I5: yes
A6: Total | B6: =B5+B4 -> 43.12 | D6: rumpus vet fund | E6: 355 | G6: TvLicence | H6: -13.2 | I6: yes
A7: Francesca pt 1 | B7: =SUMIF(J2:J32,"f1",H2:H32) -> -1805 | D7: coffee machine | E7: 275 | G7: Gas/Electric | H7: -155 | I7: yes
A8: Francesca pt 2 | B8: =SUMIF(J2:J32,"f2",H2:H32) -> -304.8 | D8: cat sitter AP+AUG | E8: 90 | G8: pet insur | H8: -40 | I8: yes
A9: Matt | B9: =SUMIF(J2:J32,"",H2:H32) -> -2627.15 | G9: spotoify | H9: -20 | I9: yes
D10: Saving Total | E10: =SUM(E2:E9) -> 1511 | G10: rainy day | H10: -60 | I10: yes
D11: Emergency Fund | E11: 1006.73 | G11: netflix | H11: -4.99 | I11: yes
D12: Car Fund | E12: 1100.58 | G12: gym | H12: -27 | I12: yes
G13: council tax | H13: -225 | I13: yes
B14: 806.34 | G14: water | H14: -13 | I14: yes
B15: 891.38 | D15: 4674 | G15: window clean | H15: -10 | I15: no
B16: =B15+B14 -> 1697.72 | G16: water | H16: -29.2 | I16: yes
D17: check come in at 235 | G17: hp | H17: -4.49 | I17: yes
A18: Mortgage | D18: 100 to willow | G18: DISHWASHER | H18: -5 | I18: yes
A19: Main | B19: 154131.53 | D19: 165 TO FRAn | G19: fran money for card | H19: -800 | I19: yes | J19: f1
A20: Extra | B20: 81555.67 | D20: WV6KZMV | G20: tesco mobiles | H20: -27 | I20: yes | J20: f2
A21: Total Due | B21: =SUM(B19:B20) -> 235687.2 | D21: Silverboots69! | G21: credit card hsbc | H21: -5 | I21: yes | J21: f1
A22: H2B paybak | B22: =B23*0.2 -> 90000 | D22: JL092865B | G22: food petrol | H22: -850 | I22: yes | J22: f1
A23: Sold Price | B23: 450000 | G23: phone | H23: -11 | I23: yes
A24: Equity | B24: =B23-SUM(B21:B22) -> 124312.8 | D24: 264 on credit card to be made into cash | G24: greenbelt | H24: -7.6 | I24: yes
D25: 75 +190 | G25: holiday | H25: -250 | I25: yes
G26: car insurance lv | H26: -31 | I26: yes
G27: child benefit shit | H27: -150 | I27: yes | J27: f1
G28: zoom | H28: -18 | I28: yes
G29: gym | H29: -33 | I29: yes | J29: f2
G30: boiler | H30: -12 | I30: yes
G31: service | H31: -60 | I31: yes
G32: matt | H32: -290 | I32: yes
G33: dental | H33: -20 | I33: yes
G34: help to by | H34: -127 | I34: yes
G35: dishwasher | H35: -5 | I35: yes
G36: uniform | H36: -50 | I36: yes
G37: Savings | H37: -1100 | I37: yes

Sheet sept24
A1: Money | D1: Savings Account | G1: Name | H1: Value | I1: Paid? | J1: Who | K1: Category
A2: Paid | B2: 5205.3 | G2: Mortgage | H2: -1268.67 | I2: yes | K2: House
A3: Taken Already | B3: =SUMIF(I2:I47,"Yes*",H2:H47) -> -6163.26 | D3: Rainy Day 🌧️ | E3: 100 | G3: isa payment | I3: no | J3: s | K3: Savings
A4: Balance | B4: 518.36 | D4: Service Fund 🚗 | E4: 100 | G4: LifeInsurance/aviva | H4: -37 | I4: yes | K4: Insurance
A5: To Be Taken | B5: =SUMIF(I2:I47,"No",H2:H47) -> -466.87 | D5: Dental 🪥 | E5: 60 | G5: HouseInsurance - Tesco | H5: -39 | I5: yes | K5: Insurance
A6: Total | B6: =B5+B4 -> 51.49 | D6: Vet Fund 😺 | E6: 520 | G6: TvLicence | H6: -15 | I6: yes | K6: HouseBill
A7: Francesca pt 1 | B7: =SUMIF(J2:J47,"f1",H2:H47) -> -1845 | D7: next month | E7: 200 | G7: Gas/Electric | H7: -155 | I7: yes | K7: HouseBill
A8: Francesca pt 2 | B8: =SUMIF(J2:J47,"f2",H2:H47) -> -27 | D8: Hair 💇‍♀️ | E8: 0 | G8: pet insur | H8: -50 | I8: yes | J8: s | K8: Insurance
A9: Matt | B9: =SUMIF(J2:J47,"",H2:H47) -> -4208.13 | D9: Christmas 🎄 | E9: 515 | G9: spotoify | H9: -20 | I9: yes | K9: Subscription
A10: Savings | B10: =SUMIF(J2:J47,"s",H2:H47) -> -550 | D10: xmas trip | E10: 30 | G10: car tax | H10: -190 | I10: yes | K10: Savings
D11: Saving Total | E11: =SUM(E2:E10) -> 1525 | G11: netflix | H11: -4.99 | I11: yes | K11: Subscription
G12: gym | H12: -27 | I12: yes | K12: Subscription
A13: Emergency Target | B13: 12000 | D13: francesca Isa | E13: 4828.1 | G13: council tax | H13: -225 | I13: yes | K13: HouseBill
A14: Emergency Fund | B14: =E12+E13 -> 4828.1 | D14: holiday fund isa | E14: 1104.26 | G14: water | H14: -13 | I14: yes | K14: HouseBill
A15: Emergency Left | B15: =B13-B14 -> 7171.9 | D15: car fix fund | E15: 1000 | G15: window clean | H15: -10 | I15: yes | K15: HouseBill
A16: Percentage | B16: =B14/B13 -> 0.40234167 | G16: water | H16: -31.5 | I16: yes | K16: HouseBill
G17: hp | H17: -1.5 | I17: yes | K17: Subscription
A18: Mortgage | G18: DISHWASHER | H18: -5 | I18: yes | K18: Insurance
A19: Main | B19: 153239.09 | G19: fran money for card | H19: -800 | I19: yes | J19: f1 | K19: Francesca
A20: Extra | B20: 81083.43 | G20: tesco mobiles | H20: -27 | I20: yes | J20: f2 | K20: Mobile
A21: Total Due | B21: =SUM(B19:B20) -> 234322.52 | G21: credit card hsbc | H21: -65 | I21: yes | J21: f1 | K21: Francesca
A22: H2B paybak | B22: =B23*0.2 -> 90000 | D22: JL092865B | G22: food petrol | H22: -900 | I22: yes | J22: f1 | K22: Food
A23: Sold Price | B23: 450000 | G23: phone | H23: -11 | I23: yes | K23: Mobile
A24: Equity | B24: =B23-SUM(B21:B22) -> 125677.48 | G24: greenbelt | H24: -7.6 | I24: yes | K24: HouseBill
G25: christmas | H25: -280 | I25: yes | J25: s | K25: Savings
G26: car insurance lv | H26: -31 | I26: yes | K26: Insurance
G27: child benefit shit | H27: -80 | I27: yes | J27: f1 | K27: Francesca
G28: zoom | H28: -18 | I28: no | K28: HouseBill
I29: no | J29: f2 | K29: Francesca
A30: NW | G30: boiler | H30: -12 | I30: yes | K30: HouseBill
A31: 1104841580 | G31: service | H31: -33 | I31: yes | K31: Savings
G32: matt | H32: -100 | I32: yes | K32: Spending
G33: dental | H33: -20 | I33: yes | J33: s | K33: Medical
G34: help to by | H34: -127 | I34: yes | K34: House
G35: mum birthday | H35: -60 | I35: yes | K35: Savings
G36: sky sports | H36: -27 | I36: yes | K36: Francesca
G37: next month | H37: -200 | I37: yes | J37: s
G38: next | H38: -1290 | I38: yes
I39: no
G40: credit card ma | H40: -448.87 | I40: no
I41: no
I42: no
I43: no
I44: no
I45: no
I46: no
I47: no

Sheet aug 24
A1: Money | D1: Savings Account | G1: Name | H1: Value | I1: Paid? | J1: Who | K1: Category
A2: Paid | B2: 5203.53 | D2: Holiday Fund ☀️ | E2: 45 | G2: Mortgage | H2: -1268.67 | I2: yes | K2: House
A3: Taken Already | B3: =SUMIF(I2:I47,"Yes*",H2:H47) -> -5189.12 | D3: Rainy Day 🌧️ | E3: 100 | G3: Car | H3: -244.8 | I3: yes | J3: s | K3: Savings
A4: Balance | B4: 35.57 | D4: Service Fund 🚗 | E4: 269 | G4: LifeInsurance/aviva | H4: -36.07 | I4: yes | K4: Insurance
A5: To Be Taken | B5: =SUMIF(I2:I47,"No",H2:H47) -> 0 | D5: Dental 🪥 | E5: 40 | G5: HouseInsurance - Tesco | H5: -39 | I5: yes | K5: Insurance
A6: Total | B6: =B5+B4 -> 35.57 | D6: Vet Fund 😺 | E6: 470 | G6: TvLicence | H6: -15 | I6: yes | K6: HouseBill
A7: Francesca pt 1 | B7: =SUMIF(J2:J47,"f1",H2:H47) -> -1825 | D7: Summer Holiday ⛱️ | G7: Gas/Electric | H7: -155 | I7: yes | K7: HouseBill
A8: Francesca pt 2 | B8: =SUMIF(J2:J47,"f2",H2:H47) -> -127 | D8: Hair 💇‍♀️ | E8: 0 | G8: pet insur | H8: -60 | I8: yes | J8: s | K8: Insurance
A9: Matt | B9: =SUMIF(J2:J47,"",H2:H47) -> -2547.32 | D9: Christmas 🎄 | E9: 250 | G9: spotoify | H9: -20 | I9: yes | K9: Subscription
A10: Savings | B10: =SUMIF(J2:J47,"s",H2:H47) -> -689.8 | G10: rainy day | H10: -65 | I10: yes | J10: s | K10: Savings
D11: Saving Total | E11: =SUM(E2:E9) -> 1174 | G11: netflix | H11: -4.99 | I11: yes | K11: Subscription
D12: Emergency Fund | E12: 1317.13 | G12: gym | H12: -27 | I12: yes | K12: Subscription
A13: Emergency Target | B13: 12000 | D13: francesca Isa | E13: 4800 | G13: council tax | H13: -225 | I13: yes | K13: HouseBill
A14: Emergency Fund | B14: =E12+E13 -> 6117.13 | G14: water | H14: -13 | I14: yes | K14: HouseBill
A15: Emergency Left | B15: =B13-B14 -> 5882.87 | D15: 4674 | G15: window clean | H15: -10 | I15: yes | K15: HouseBill
A16: Percentage | B16: =B14/B13 -> 0.50976083 | G16: water | H16: -31.5 | I16: yes | K16: HouseBill
G17: hp | H17: -4.49 | I17: yes | K17: Subscription
A18: Mortgage | G18: DISHWASHER | H18: -5 | I18: yes | K18: Insurance
A19: Main | B19: 153458.32 | G19: fran money for card | H19: -800 | I19: yes | J19: f1 | K19: Francesca
A20: Extra | B20: 81199.44 | G20: tesco mobiles | H20: -27 | I20: yes | J20: f2 | K20: Mobile
A21: Total Due | B21: =SUM(B19:B20) -> 234657.76 | G21: credit card hsbc | H21: -45 | I21: yes | J21: f1 | K21: Francesca
A22: H2B paybak | B22: =B23*0.2 -> 90000 | D22: JL092865B | G22: food petrol | H22: -900 | I22: yes | J22: f1 | K22: Food
A23: Sold Price | B23: 450000 | G23: phone | H23: -11 | I23: yes | K23: Mobile
A24: Equity | B24: =B23-SUM(B21:B22) -> 125342.24 | G24: greenbelt | H24: -7.6 | I24: yes | K24: HouseBill
G25: christmas | H25: -150 | I25: yes | J25: s | K25: Savings
G26: car insurance lv | H26: -31 | I26: yes | K26: Insurance
G27: child benefit shit | H27: -80 | I27: yes | J27: f1 | K27: Francesca
G28: zoom | H28: -18 | I28: yes | K28: HouseBill
G29: hair | H29: -100 | I29: yes | J29: f2 | K29: Francesca
A30: NW | G30: boiler | H30: -12 | I30: yes | K30: HouseBill
A31: 1104841580 | G31: service | H31: -150 | I31: yes | J31: s | K31: Savings
G32: matt | H32: -126 | I32: yes | K32: Spending
G33: dental | H33: -20 | I33: yes | J33: s | K33: Medical
G34: help to by | H34: -127 | I34: yes | K34: House
G35: emergancy fund | H35: -300 | I35: yes | K35: Savings
G36: anniversary | H36: -40 | I36: yes | K36: Francesca
G37: willow isa | H37: -20 | I37: yes
I38: no
I39: no
I40: no
I41: no
I42: no
I43: no
I44: no
I45: no
I46: no
I47: no

Sheet july
A1: Money | D1: Savings Account | G1: Name | H1: Value | I1: Paid? | J1: Who
A2: Paid | B2: 5114.06 | D2: Holiday Fund ☀️ | E2: 200 | G2: Mortgage | H2: -1268.67 | I2: yes
A3: Taken Already | B3: =SUMIF(I2:I28,"Yes*",H2:H28) -> -4496.05 | D3: Rainy Day 🌧️ | E3: 35 | G3: Car | H3: -244.8 | I3: yes | J3: f2
A4: Balance | B4: 13.84 | D4: Service Fund 🚗 | E4: 450 | G4: LifeInsurance/aviva | H4: -33 | I4: yes
A5: To Be Taken | B5: =SUMIF(I2:I37,"No",H2:H37) -> 0 | D5: Dental 🪥 | E5: 20 | G5: HouseInsurance - Tesco | H5: -39 | I5: yes
A6: Total | B6: =B5+B4 -> 13.84 | D6: Vet Fund 😺 | E6: 440 | G6: TvLicence | H6: -15 | I6: yes
A7: Francesca pt 1 | B7: =SUMIF(J2:J37,"f1",H2:H37) -> -2083 | D7: Summer Holiday ⛱️ | E7: 200 | G7: Gas/Electric | H7: -155 | I7: yes
A8: Francesca pt 2 | B8: =SUMIF(J2:J37,"f2",H2:H37) -> -304.8 | E8: 0 | G8: pet insur | H8: -40 | I8: yes | J8: s
A9: Matt | B9: =SUMIF(J2:J37,"",H2:H37) -> -2288.25 | D9: Christmas 🎄 | E9: 100 | G9: spotoify | H9: -20 | I9: yes
A10: Savings | B10: =SUMIF(J2:J37,"s",H2:H37) -> -592 | G10: rainy day | H10: -82 | I10: yes | J10: s
D11: Saving Total | E11: =SUM(E2:E9) -> 1445 | G11: netflix | H11: -4.99 | I11: yes
D12: Emergency Fund | E12: 1016.58 | G12: gym | H12: -27 | I12: yes
D13: Car Fund | E13: 908.99 | G13: council tax | H13: -225 | I13: yes
B14: 806.34 | D14: Virgin ISA | E14: 5157 | G14: water | H14: -13 | I14: yes
B15: 891.38 | D15: 4674 | G15: window clean | H15: -10 | I15: yes
B16: =B15+B14 -> 1697.72 | G16: water | H16: -31.5 | I16: yes
D17: check come in at 235 | G17: hp | H17: -4.49 | I17: yes
A18: Mortgage | D18: 100 to willow | G18: DISHWASHER | H18: -5 | I18: yes
A19: Main | B19: 153676.79 | D19: 165 TO FRAn | G19: fran money for card | H19: -800 | I19: yes | J19: f1
A20: Extra | B20: 81315.04 | D20: WV6KZMV | G20: tesco mobiles | H20: -27 | I20: yes | J20: f2
A21: Total Due | B21: =SUM(B19:B20) -> 234991.83 | D21: Silverboots69! | G21: credit card hsbc | H21: -303 | I21: yes | J21: f1
A22: H2B paybak | B22: =B23*0.2 -> 90000 | D22: JL092865B | G22: food petrol | H22: -900 | I22: yes | J22: f1
A23: Sold Price | B23: 450000 | G23: phone | H23: -11 | I23: yes
A24: Equity | B24: =B23-SUM(B21:B22) -> 125008.17 | G24: greenbelt | H24: -7.6 | I24: yes
D25: Car Balance | E25: -7024 | G25: christmas | H25: -100 | I25: yes | J25: s
D26: Car Fund Savings | E26: 909 | G26: car insurance lv | H26: -31 | I26: yes
D27: Money From Noetica | E27: 1800 | G27: child benefit shit | H27: -80 | I27: yes | J27: f1
D28: Virgin ISA | E28: 4315 | G28: zoom | H28: -18 | I28: yes
D29: Total Left | E29: =SUM(E25:E28) -> 0 | G29: gym | H29: -33 | I29: yes | J29: f2
A30: NW | G30: boiler | H30: -12 | I30: yes
A31: 1104841580 | G31: service | H31: -150 | I31: yes | J31: s
G32: matt | H32: -25 | I32: yes
G33: dental | H33: -20 | I33: yes | J33: s
G34: help to by | H34: -127 | I34: yes
G35: dishwasher | H35: -5 | I35: yes
G36: car fund | H36: -200 | I36: yes
G37: summer hols | H37: -200 | I37: yes | J37: s
I38: no

Sheet june24
A1: Money | D1: Savings Account | G1: Name | H1: Value | I1: Paid? | J1: Who
A2: Paid | B2: 4991.17 | D2: holday fund | E2: 485 | G2: Mortgage | H2: -1268.67 | I2: yes
A3: Taken Already | B3: =SUMIF(I2:I28,"Yes*",H2:H28) -> -4602.05 | D3: rainy day fund | E3: 8 | G3: Car | H3: -244.8 | I3: yes | J3: f2
A4: Balance | B4: 67.08 | D4: service fund | E4: 300 | G4: LifeInsurance/aviva | H4: -33 | I4: yes
A5: To Be Taken | B5: =SUMIF(I2:I37,"No",H2:H37) -> -64 | D5: dental | G5: HouseInsurance - Tesco | H5: -39 | I5: yes
A6: Total | B6: =B5+B4 -> 3.08 | D6: rumpus vet fund | E6: 400 | G6: TvLicence | H6: -15 | I6: yes
A7: Francesca pt 1 | B7: =SUMIF(J2:J32,"f1",H2:H32) -> -2265 | D7: lego | G7: Gas/Electric | H7: -155 | I7: yes
A8: Francesca pt 2 | B8: =SUMIF(J2:J32,"f2",H2:H32) -> -304.8 | D8: cat sitter AP+AUG | E8: 90 | G8: pet insur | H8: -40 | I8: yes
A9: Matt | B9: =SUMIF(J2:J32,"",H2:H32) -> -2271.25 | D9: school unoform | E9: 65 | G9: spotoify | H9: -20 | I9: yes
D10: Saving Total | E10: =SUM(E2:E9) -> 1348 | G10: rainy day | H10: -20 | I10: yes
D11: Emergency Fund | E11: 1005.08 | G11: netflix | H11: -4.99 | I11: yes
D12: Car Fund | E12: 700 | G12: gym | H12: -27 | I12: yes
G13: council tax | H13: -225 | I13: yes
B14: 806.34 | G14: water | H14: -13 | I14: yes
B15: 891.38 | D15: 4674 | G15: window clean | H15: -10 | I15: yes
B16: =B15+B14 -> 1697.72 | G16: water | H16: -31.5 | I16: yes
D17: check come in at 235 | G17: hp | H17: -4.49 | I17: yes
A18: Mortgage | D18: 100 to willow | G18: DISHWASHER | H18: -5 | I18: no
A19: Main | B19: 153843.9 | D19: 165 TO FRAn | G19: fran money for card | H19: -1000 | I19: yes | J19: f1
A20: Extra | B20: 81408.76 | D20: WV6KZMV | G20: tesco mobiles | H20: -27 | I20: yes | J20: f2
A21: Total Due | B21: =SUM(B19:B20) -> 235252.66 | D21: Silverboots69! | G21: credit card hsbc | H21: -135 | I21: yes | J21: f1
A22: H2B paybak | B22: =B23*0.2 -> 90000 | D22: JL092865B | G22: food petrol | H22: -1050 | I22: yes | J22: f1
A23: Sold Price | B23: 450000 | G23: phone | H23: -11 | I23: no
A24: Equity | B24: =B23-SUM(B21:B22) -> 124747.34 | G24: greenbelt | H24: -7.6 | I24: yes
G25: holiday | H25: -120 | I25: yes
G26: car insurance lv | H26: -31 | I26: yes
B27: 400000 | G27: child benefit shit | H27: -80 | I27: yes | J27: f1
B28: 125000 | G28: zoom | H28: -18 | I28: no
B29: =SUM(B27:B28) -> 525000 | G29: gym | H29: -33 | I29: yes | J29: f2
G30: boiler | H30: -12 | I30: yes
G31: service | H31: -50 | I31: yes
G32: matt | H32: -110 | I32: yes
G33: dental | H33: -20 | I33: yes
G34: help to by | H34: -127 | I34: yes
G35: dishwasher | H35: -5 | I35: no
G36: uniform | H36: -50 | I36: yes
G37: matt | H37: -25 | I37: no

Sheet apr24
A1: Money | D1: Savings Account | G1: Name | H1: Value | I1: Paid? | J1: Who
A2: Paid | B2: 5010.9 | D2: holday fund | E2: 100 | G2: Mortgage | H2: -1268.67 | I2: yes
A3: Taken Already | B3: =SUMIF(I2:I28,"Yes*",H2:H28) -> -4069.94 | D3: rainy day fund | E3: 180 | G3: Car | H3: -244.8 | I3: yes | J3: f
A4: Balance | B4: 42.94 | D4: service fund | E4: 190 | G4: LifeInsurance/aviva | H4: -33 | I4: yes
A5: To Be Taken | B5: =SUMIF(I2:I37,"No",H2:H37) -> -34 | D5: dental | E5: 76 | G5: HouseInsurance - Tesco | H5: -39 | I5: yes
A6: Total | B6: =B5+B4 -> 8.94 | D6: rumpus vet fund | E6: 315 | G6: TvLicence | H6: -13.2 | I6: yes
A7: Francesca | B7: =SUMIF(J2:J32,"f",H2:H32) -> -2013.8 | D7: coffee machine | E7: 54.47 | G7: Gas/Electric | H7: -173 | I7: yes
D8: cat sitter AP+AUG | E8: 90 | G8: pet insur | H8: -40 | I8: yes
D9: holiday in august | E9: 1025 | G9: spotoify | H9: -16.99 | I9: yes
A10: expenses for SWE | D10: Saving Total | E10: =SUM(E2:E9) -> 2030.47 | G10: rainy day | H10: -60 | I10: yes
A11: 140.35 | G11: netflix | H11: -4.99 | I11: yes
D12: garage isa | G12: gym | H12: -27 | I12: yes
G13: council tax | H13: -225 | I13: yes
B14: 806.34 | G14: water | H14: -13 | I14: yes
B15: 891.38 | D15: 4674 | G15: window clean | I15: no
B16: =B15+B14 -> 1697.72 | G16: water | H16: -29.2 | I16: yes
D17: check come in at 235 | G17: hp | H17: -4.49 | I17: yes
A18: Mortgage | D18: 100 to willow | G18: DISHWASHER | H18: -5 | I18: no
A19: Main | B19: 157869 | D19: 165 TO FRAn | G19: fran money for card | H19: -1000 | I19: yes | J19: f
A20: Extra | B20: 82960 | D20: WV6KZMV | G20: tesco mobiles | H20: -26 | I20: yes | J20: f
A21: Total Due | B21: =SUM(B19:B20) -> 240829 | D21: Silverboots69! | G21: credit card hsbc | I21: no | J21: f
A22: H2B paybak | B22: =B23*0.2 -> 80000 | D22: JL092865B | G22: food petrol | H22: -630 | I22: yes | J22: f
A23: Sold Price | B23: 400000 | G23: phone | H23: -11 | I23: no
A24: Equity | B24: =SUM(B21:B22)-B23 -> -79171 | G24: greenbelt | H24: -7.6 | I24: yes
A25: House Price | B25: 450000 | G25: holiday | H25: -100 | I25: yes
A26: Mortgage Amount | B26: =B25+B24 -> 370829 | G26: car insurance lv | H26: -34 | I26: yes
D27: 4674 | G27: child benefit shit | H27: -80 | I27: yes | J27: f
A28: Mortgage H2B Plan | G28: zoom | H28: -18 | I28: no
A29: Main | B29: 158345 | G29: gym | H29: -33 | I29: yes | J29: f
A30: Extra | B30: 83156 | G30: boiler | H30: -12 | I30: yes
A31: Total Due | B31: =SUM(B29:B30) -> 241501 | G31: service | H31: -40 | I31: yes
A32: H2B paybak | B32: =B33*0.2 -> 80000 | C32: - | G32: matt | H32: -262.46 | I32: yes
A33: Valuation | B33: 400000 | D33: 558.2 | G33: dental | H33: -20 | I33: yes
A34: Equity | B34: =SUM(B31:B32)-B33 -> -78499 | D34: 484.16 | G34: help to by | H34: -127 | I34: yes
A35: Mortgage Amount | B35: =B32+B31 -> 321501 | D35: =D34-D33 -> -74.04 | G35: car | H35: -110 | I35: yes | J35: f
G36: insurance | H36: -28 | I36: yes
G37: check | H37: -1260 | I37: yes
I38: no
I39: no

Sheet mar24
A1: Money | D1: Savings Account | G1: Name | H1: Value | I1: Paid? | J1: Who
A2: Paid | B2: 4920.23 | D2: Savings Account | G2: Mortgage | H2: -1268.67 | I2: yes
A3: Taken Already | B3: =SUMIF(I2:I28,"Yes*",H2:H28) -> -4056.94 | D3: rainy day fund | E3: 135 | G3: Car | H3: -244.8 | I3: yes | J3: f
A4: Balance | B4: 4.01 | D4: service fund | E4: 150 | G4: LifeInsurance/aviva | H4: -33 | I4: yes
A5: To Be Taken | B5: =SUMIF(I2:I37,"No",H2:H37) -> 0 | D5: dental | G5: HouseInsurance - Tesco | H5: -39 | I5: yes
A6: Total | B6: =B5+B4 -> 4.01 | D6: rumpus vet fund | E6: 275 | G6: TvLicence | H6: -13.2 | I6: yes
A7: Francesca | B7: =SUMIF(J2:J32,"f",H2:H32) -> -2026.8 | D7: francesca birhday | G7: Gas/Electric | H7: -173 | I7: yes
D8: cat sitter AP+AUG | E8: 90 | G8: pet insur | H8: -40 | I8: yes
D9: holiday in august | E9: 1025 | G9: spotoify | H9: -16.99 | I9: yes
A10: expenses for SWE | D10: Saving Total | E10: =SUM(E2:E9) -> 1675 | G10: rainy day | H10: -90 | I10: yes
A11: 140.35 | G11: netflix | H11: -4.99 | I11: yes
D12: garage isa | G12: gym | H12: -27 | I12: yes
G13: council tax | H13: -225 | I13: yes
B14: 806.34 | G14: water | H14: -13 | I14: yes
B15: 891.38 | D15: 4674 | G15: window clean | H15: -10 | I15: yes
B16: =B15+B14 -> 1697.72 | G16: water | H16: -29.2 | I16: yes
D17: check come in at 235 | G17: hp | H17: -4.49 | I17: yes
A18: Mortgage | D18: 100 to willow | G18: DISHWASHER | H18: -5 | I18: yes
A19: Main | B19: 157869 | D19: 165 TO FRAn | G19: fran money for card | H19: -800 | I19: yes | J19: f
A20: Extra | B20: 82960 | D20: WV6KZMV | G20: tesco mobiles | H20: -26 | I20: yes | J20: f
A21: Total Due | B21: =SUM(B19:B20) -> 240829 | D21: Silverboots69! | G21: credit card hsbc | H21: -23 | I21: yes | J21: f
A22: H2B paybak | B22: =B23*0.2 -> 80000 | D22: JL092865B | G22: food petrol | H22: -850 | I22: yes | J22: f
A23: Sold Price | B23: 400000 | G23: phone | H23: -11 | I23: yes
A24: Equity | B24: =SUM(B21:B22)-B23 -> -79171 | G24: greenbelt | H24: -7.6 | I24: yes
A25: House Price | B25: 450000 | G25: next | I25: no
A26: Mortgage Amount | B26: =B25+B24 -> 370829 | G26: car insurance lv | H26: -34 | I26: yes
D27: 4674 | G27: child benefit shit | H27: -50 | I27: yes | J27: f
A28: Mortgage H2B Plan | G28: zoom | H28: -18 | I28: yes
A29: Main | B29: 158345 | G29: gym | H29: -33 | I29: yes | J29: f
A30: Extra | B30: 83156 | G30: boiler | H30: -12 | I30: yes
A31: Total Due | B31: =SUM(B29:B30) -> 241501 | G31: service | H31: -40 | I31: yes
A32: H2B paybak | B32: =B33*0.2 -> 80000 | C32: - | G32: MATTS crdit card | H32: -422 | I32: yes
A33: Valuation | B33: 400000 | D33: 558.2 | G33: dental | H33: -20 | I33: yes
A34: Equity | B34: =SUM(B31:B32)-B33 -> -78499 | D34: 484.16 | G34: help to by | H34: -114 | I34: yes
A35: Mortgage Amount | B35: =B32+B31 -> 321501 | D35: =D34-D33 -> -74.04 | G35: willow bday | H35: -170 | I35: yes | J35: f
G36: birthday | H36: -435 | I36: yes
G37: holiday | H37: -45 | I37: yes
I38: no
I39: no

Sheet feb24
A1: Money | D1: Savings Account | G1: Name | H1: Value | I1: Paid? | J1: Who
A2: Paid | B2: 4974.35 | D2: Savings Account | G2: Mortgage | H2: -1268.67 | I2: yes
A3: Taken Already | B3: =SUMIF(I2:I28,"Yes*",H2:H28) -> -3561.94 | D3: rainy day fund | E3: 80 | G3: Car | H3: -244.8 | I3: yes | J3: f
A4: Balance | B4: 29.64 | D4: service fund | E4: 110 | G4: LifeInsurance/aviva | H4: -33 | I4: yes
A5: To Be Taken | B5: =SUMIF(I2:I37,"No",H2:H37) -> -29 | D5: dental | E5: 60 | G5: HouseInsurance - Tesco | H5: -39 | I5: yes
A6: Total | B6: =B5+B4 -> 0.64 | D6: rumpus vet fund | E6: 400 | G6: TvLicence | H6: -13.2 | I6: yes
A7: Francesca | B7: =SUMIF(J2:J32,"f",H2:H32) -> -1613.8 | D7: francesca birhday | E7: 244 | G7: Gas/Electric | H7: -173 | I7: yes
D8: cat sitter AP+AUG | E8: 160 | G8: pet insur | I8: no
D9: holiday in august | E9: 1025 | G9: spotoify | H9: -16.99 | I9: yes
D10: Saving Total | E10: =SUM(E2:E9) -> 2079 | G10: rainy day | H10: -40 | I10: yes
G11: netflix | H11: -4.99 | I11: yes
D12: garage isa | G12: gym | H12: -27 | I12: yes
G13: council tax | H13: -214 | I13: yes
B14: 806.34 | G14: water | H14: -13 | I14: yes
B15: 891.38 | G15: window clean | H15: -10 | I15: yes
B16: =B15+B14 -> 1697.72 | G16: water | H16: -29.2 | I16: yes
D17: expensis 224 | G17: hp | H17: -4.49 | I17: yes
A18: Mortgage | G18: DISHWASHER | H18: -5 | I18: yes
A19: Main | B19: 157869 | G19: fran money for card | H19: -800 | I19: yes | J19: f
A20: Extra | B20: 82960 | D20: WV6KZMV | G20: tesco mobiles | H20: -26 | I20: yes | J20: f
A21: Total Due | B21: =SUM(B19:B20) -> 240829 | D21: Silverboots69! | G21: credit card hsbc | H21: -350 | I21: yes | J21: f
A22: H2B paybak | B22: =B23*0.2 -> 80000 | D22: JL092865B | G22: food petrol | H22: -80 | I22: yes | J22: f
A23: Sold Price | B23: 400000 | G23: phone | H23: -11 | I23: no
A24: Equity | B24: =SUM(B21:B22)-B23 -> -79171 | G24: greenbelt | H24: -7.6 | I24: yes
A25: House Price | B25: 450000 | G25: next | H25: -48 | I25: yes
A26: Mortgage Amount | B26: =B25+B24 -> 370829 | G26: car insurance lv | H26: -34 | I26: yes
D27: 4674 | G27: child benefit shit | H27: -80 | I27: yes | J27: f
A28: Mortgage H2B Plan | G28: zoom | H28: -18 | I28: no
A29: Main | B29: 158345 | G29: gym | H29: -33 | I29: yes | J29: f
A30: Extra | B30: 83156 | G30: boiler | H30: -12 | I30: yes
A31: Total Due | B31: =SUM(B29:B30) -> 241501 | G31: service | H31: -40 | I31: yes
A32: H2B paybak | B32: =B33*0.2 -> 80000 | C32: - | G32: MATTS crdit card | H32: -257.71 | I32: yes
A33: Valuation | B33: 400000 | D33: 558.2 | G33: dental | H33: -20 | I33: yes
A34: Equity | B34: =SUM(B31:B32)-B33 -> -78499 | D34: 484.16 | G34: help to by | H34: -114 | I34: yes
A35: Mortgage Amount | B35: =B32+B31 -> 321501 | D35: =D34-D33 -> -74.04 | G35: willow bday | I35: no | J35: f
G36: birthday | H36: -20 | I36: yes
I37: no
I38: no
I39: no

Sheet jan24
A1: Money | D1: Savings Account | G1: Name | H1: Value | I1: Paid? | J1: Who
A2: Paid | B2: 4968.44 | D2: Savings Account | E2: 77 | G2: Mortgage | H2: -1268.67 | I2: yes
A3: Taken Already | B3: =SUMIF(I2:I28,"Yes*",H2:H28) -> -4419.94 | D3: rainy day fund | E3: 40 | G3: Car | H3: -244.8 | I3: yes | J3: f
A4: Balance | B4: 3 | D4: service fund | E4: 70 | G4: LifeInsurance/aviva | H4: -33 | I4: yes
A5: To Be Taken | B5: =SUMIF(I2:I37,"No",H2:H37) -> 0 | D5: dental | E5: 40 | G5: HouseInsurance - Tesco | H5: -39 | I5: yes
A6: Total | B6: =B5+B4 -> 3 | D6: rumpus vet fund | E6: 400 | G6: TvLicence | H6: -13.2 | I6: yes
A7: Francesca | B7: =SUMIF(J2:J32,"f",H2:H32) -> -2296.8 | D7: fran birthday | E7: 50 | G7: Gas/Electric | H7: -173 | I7: yes
D8: ct sitter | E8: 70 | G8: pet insur | H8: -40 | I8: yes
G9: spotoify | H9: -16.99 | I9: yes
D10: Saving Total | E10: =SUM(E2:E9) -> 747 | G10: rainy day | H10: -40 | I10: yes
G11: netflix | H11: -10.99 | I11: yes
D12: garage isa | G12: gym | H12: -27 | I12: yes
G13: council tax | H13: -214 | I13: yes
B14: 806.34 | G14: water | H14: -13 | I14: yes
B15: 891.38 | G15: window clean | H15: -10 | I15: yes
B16: =B15+B14 -> 1697.72 | G16: water | H16: -29.2 | I16: yes
D17: expensis 224 | G17: hp | H17: -4.49 | I17: yes
A18: Mortgage | G18: PLUMMER | H18: -120 | I18: yes
A19: Main | B19: 157869 | G19: fran money for card | H19: -900 | I19: yes | J19: f
A20: Extra | B20: 82960 | D20: WV6KZMV | G20: tesco mobiles | H20: -8 | I20: yes | J20: f
A21: Total Due | B21: =SUM(B19:B20) -> 240829 | D21: Silverboots69! | G21: credit card hsbc | H21: -31 | I21: yes | J21: f
A22: H2B paybak | B22: =B23*0.2 -> 80000 | D22: JL092865B | G22: food petrol | H22: -1000 | I22: yes | J22: f
A23: Sold Price | B23: 400000 | G23: phone | H23: -11 | I23: yes
A24: Equity | B24: =SUM(B21:B22)-B23 -> -79171 | G24: greenbelt | H24: -7.6 | I24: yes
A25: House Price | B25: 450000 | D25: 0205UK11 | G25: next | H25: -33 | I25: yes
A26: Mortgage Amount | B26: =B25+B24 -> 370829 | D26: 0205UK10 | G26: car insurance lv | H26: -34 | I26: yes
G27: child benefit shit | H27: -80 | I27: yes | J27: f
A28: Mortgage H2B Plan | G28: zoom | H28: -18 | I28: yes
A29: Main | B29: 158345 | G29: gym | H29: -33 | I29: yes | J29: f
A30: Extra | B30: 83156 | G30: boiler | H30: -12 | I30: yes
A31: Total Due | B31: =SUM(B29:B30) -> 241501 | G31: service | H31: -40 | I31: yes
A32: H2B paybak | B32: =B33*0.2 -> 80000 | C32: - | G32: MATTS crdit card | H32: -168 | I32: yes
A33: Valuation | B33: 400000 | D33: 558.2 | G33: dental | H33: -20 | I33: yes
A34: Equity | B34: =SUM(B31:B32)-B33 -> -78499 | D34: 484.16 | G34: help to by | H34: -114 | I34: yes
A35: Mortgage Amount | B35: =B32+B31 -> 321501 | D35: =D34-D33 -> -74.04 | G35: savings | H35: -150 | I35: yes | J35: f
G36: birthday | H36: -15 | I36: yes
I37: no
I38: no
I39: no

Sheet dec23
A1: Money | D1: Savings Account | G1: Name | H1: Value | I1: Paid? | J1: Who
A2: Paid | B2: 4974.87 | D2: Savings Account | E2: 146 | G2: Mortgage | H2: -797 | I2: yes
A3: Taken Already | D3: service fund | E3: 30 | G3: Car | H3: -244.8 | I3: yes | J3: f
A4: Balance | B4: 17.36 | D4: rainy day | G4: LifeInsurance/aviva | H4: -33 | I4: yes
A5: To Be Taken | B5: =SUMIF(I2:I37,"No",H2:H37) -> -11 | D5: dental | E5: 20 | G5: HouseInsurance - Tesco | H5: -39 | I5: yes
A6: Total | B6: =B5+B4 -> 6.36 | D6: rumpus vet fund | E6: 460 | G6: TvLicence | H6: -13.2 | I6: yes
A7: Francesca | B7: =SUMIF(J2:J32,"f",H2:H32) -> -2140.8 | G7: Gas/Electric | H7: -173 | I7: yes
D8: christmas | G8: pet insur | H8: -40 | I8: yes
G9: spotoify | H9: -16.99 | I9: yes
D10: Saving Total | E10: =SUM(E2:E9) -> 656 | G10: rescue me car | H10: -24 | I10: yes
G11: netflix | H11: -10.99 | I11: yes
D12: garage isa | G12: gym | H12: -27 | I12: yes
G13: council tax | H13: -214 | I13: yes
B14: 806.34 | G14: water | H14: -13 | I14: yes
B15: 891.38 | G15: medical | H15: -100 | I15: yes
B16: =B15+B14 -> 1697.72 | G16: water | H16: -29.2 | I16: yes
D17: expensis 224 | G17: hp | H17: -4.49 | I17: yes
A18: Mortgage | G18: service fund | I18: no
A19: Main | B19: 155468.76 | G19: fran money for card | H19: -800 | I19: yes | J19: f
A20: Extra | B20: 82260.05 | D20: WV6KZMV | G20: tesco mobiles | H20: -26 | I20: yes | J20: f
A21: Total Due | B21: =SUM(B19:B20) -> 237728.81 | D21: Silverboots69! | G21: credit card hsbc | H21: -132 | I21: yes | J21: f
A22: H2B paybak | B22: =B23*0.2 -> 90000 | D22: JL092865B | G22: food petrol | H22: -825 | I22: yes | J22: f
A23: Sold Price | B23: 450000 | G23: phone | H23: -11 | I23: no
A24: Equity | B24: =SUM(B21:B22)-B23 -> -122271.19 | G24: greenbelt | H24: -7.6 | I24: yes
A25: House Price | B25: 450000 | G25: bartley | H25: -100 | I25: yes
A26: Mortgage Amount | B26: =B25+B24 -> 327728.81 | G26: car insurance lv | H26: -34 | I26: yes
G27: child benefit shit | H27: -80 | I27: yes | J27: f
A28: Mortgage H2B Plan | G28: zoom | H28: -18 | I28: yes
A29: Main | B29: 158345 | G29: gym | H29: -33 | I29: yes | J29: f
A30: Extra | B30: 83156 | G30: boiler | H30: -12 | I30: yes
A31: Total Due | B31: =SUM(B29:B30) -> 241501 | G31: christmas food | H31: -160 | I31: yes
A32: H2B paybak | B32: =B33*0.2 -> 80000 | C32: - | G32: MATTS crdit card | H32: -373 | I32: yes
A33: Valuation | B33: 400000 | D33: 558.2 | I33: no
A34: Equity | B34: =SUM(B31:B32)-B33 -> -78499 | D34: 484.16 | G34: help to by | H34: -114 | I34: yes
A35: Mortgage Amount | B35: =B32+B31 -> 321501 | D35: =D34-D33 -> -74.04 | G35: christmas holiday money | H35: -150 | I35: yes | J35: f
G36: mot and tyres | H36: -60 | I36: yes
G37: birthday | H37: -30 | I37: yes
I38: no
I39: no

Sheet nov23
A1: Money | D1: Savings Account | G1: Name | H1: Value | I1: Paid? | J1: Who
A2: Paid | B2: 4982.07 | D2: Savings Account | E2: 60 | G2: Mortgage | H2: -797 | I2: yes
A3: Taken Already | B3: =SUMIF(I2:I28,"Yes*",H2:H28) -> -4131.27 | D3: corse money | G3: Car | H3: -244.8 | I3: yes | J3: f
A4: Balance | B4: 0.62 | G4: LifeInsurance/aviva | H4: -33 | I4: yes
A5: To Be Taken | B5: =SUMIF(I2:I37,"No",H2:H37) -> 0 | D5: garage fund | G5: HouseInsurance - Tesco | H5: -39 | I5: yes
A6: Total | B6: =B5+B4 -> 0.62 | D6: rumpus vet fund | E6: 426 | G6: TvLicence | H6: -13.2 | I6: yes
A7: Francesca | B7: =SUMIF(J2:J32,"f",H2:H32) -> -2113.8 | D7: Matt Bday | G7: Gas/Electric | H7: -173 | I7: yes
D8: christmas | E8: 20 | G8: pet insur | H8: -40 | I8: yes
D9: garage fund | G9: spotoify | H9: -16.99 | I9: yes
D10: Saving Total | E10: =SUM(E2:E9) -> 506 | G10: savings | H10: -100 | I10: yes
G11: netflix | H11: -10.99 | I11: yes
D12: garage isa | G12: gym | H12: -27 | I12: yes
G13: council tax | H13: -214 | I13: yes
B14: 806.34 | G14: water | H14: -13 | I14: yes
B15: 891.38 | G15: meal | H15: -160 | I15: yes
B16: =B15+B14 -> 1697.72 | G16: water | H16: -29.2 | I16: yes
D17: expensis 224 | G17: hp | H17: -4.49 | I17: yes
A18: Mortgage | G18: course | H18: -159 | I18: yes
A19: Main | B19: 157869 | G19: fran money for card | H19: -800 | I19: yes | J19: f
A20: Extra | B20: 82960 | D20: WV6KZMV | G20: tesco mobiles | H20: -26 | I20: yes | J20: f
A21: Total Due | B21: =SUM(B19:B20) -> 240829 | D21: Silverboots69! | G21: credit card hsbc | H21: -105 | I21: yes | J21: f
A22: H2B paybak | B22: =B23*0.2 -> 80000 | D22: JL092865B | G22: food petrol | H22: -825 | I22: yes | J22: f
A23: Sold Price | B23: 400000 | G23: phone | H23: -11 | I23: yes
A24: Equity | B24: =SUM(B21:B22)-B23 -> -79171 | G24: greenbelt | H24: -7.6 | I24: yes
A25: House Price | B25: 450000 | G25: london | H25: -150 | I25: yes
A26: Mortgage Amount | B26: =B25+B24 -> 370829 | G26: car insurance lv | H26: -34 | I26: yes
G27: child benefit shit | H27: -80 | I27: yes | J27: f
A28: Mortgage H2B Plan | G28: zoom | H28: -18 | I28: yes
A29: Main | B29: 158345 | G29: gym | H29: -33 | I29: yes | J29: f
A30: Extra | B30: 83156 | G30: boiler | H30: -12 | I30: yes
A31: Total Due | B31: =SUM(B29:B30) -> 241501 | G31: christmas | H31: -500 | I31: yes
A32: H2B paybak | B32: =B33*0.2 -> 80000 | C32: - | G32: MATTS crdit card | H32: -313 | I32: yes
A33: Valuation | B33: 400000 | D33: 558.2 | G33: hoiliday | H33: -30 | I33: yes
A34: Equity | B34: =SUM(B31:B32)-B33 -> -78499 | D34: 484.16 | G34: help to by | H34: -114 | I34: yes
A35: Mortgage Amount | B35: =B32+B31 -> 321501 | D35: =D34-D33 -> -74.04 | G35: health insurance | H35: -50 | I35: yes | J35: f
G36: birthday | H36: -20 | I36: yes
I37: no

Sheet oct23
A1: Money | D1: Savings Account | G1: Name | H1: Value | I1: Paid? | J1: Who
A2: Paid | B2: 4954 | D2: Savings Account | E2: 60 | G2: Mortgage | H2: -897 | I2: yes
A3: Taken Already | B3: =SUMIF(I2:I28,"Yes*",H2:H28) -> -4077.27 | D3: corse money | G3: Car | H3: -244.8 | I3: yes | J3: f
A4: Balance | B4: 32.55 | G4: LifeInsurance/aviva | H4: -33 | I4: yes
A5: To Be Taken | B5: =SUMIF(I2:I37,"No",H2:H37) -> 0 | D5: garage fund | G5: HouseInsurance - Tesco | H5: -39 | I5: yes
A6: Total | B6: =B5+B4 -> 32.55 | D6: rumpus vet fund | E6: 415 | G6: TvLicence | H6: -13.2 | I6: yes
A7: Francesca | B7: =SUMIF(J2:J32,"f",H2:H32) -> -2343.8 | D7: Matt Bday | G7: Gas/Electric | H7: -173 | I7: yes
D8: christmas | E8: 320 | G8: pet insur | H8: -40 | I8: yes
D9: garage fund | G9: spotoify | H9: -16.99 | I9: yes
D10: Saving Total | E10: =SUM(E2:E9) -> 795 | G10: isa savings | H10: -180 | I10: yes
G11: netflix | H11: -10.99 | I11: yes
D12: garage isa | G12: gym | H12: -27 | I12: yes
G13: council tax | H13: -214 | I13: yes
B14: 806.34 | G14: water | H14: -13 | I14: yes
B15: 891.38 | G15: savings | I15: no
B16: =B15+B14 -> 1697.72 | G16: water | H16: -29.2 | I16: yes
D17: expensis 224 | G17: hp | H17: -4.49 | I17: yes
A18: Mortgage | G18: car tax | I18: no
A19: Main | B19: 157869 | G19: fran money for card | H19: -900 | I19: yes | J19: f
A20: Extra | B20: 82960 | D20: WV6KZMV | G20: tesco mobiles | H20: -26 | I20: yes | J20: f
A21: Total Due | B21: =SUM(B19:B20) -> 240829 | D21: Silverboots69! | G21: credit card hsbc | H21: -60 | I21: yes | J21: f
A22: H2B paybak | B22: =B23*0.2 -> 80000 | D22: JL092865B | G22: food petrol | H22: -1000 | I22: yes | J22: f
A23: Sold Price | B23: 400000 | G23: phone | H23: -11 | I23: yes
A24: Equity | B24: =SUM(B21:B22)-B23 -> -79171 | G24: greenbelt | H24: -7.6 | I24: yes
A25: House Price | B25: 450000 | G25: window cleanewr | H25: -5 | I25: yes
A26: Mortgage Amount | B26: =B25+B24 -> 370829 | G26: car insurance lv | H26: -34 | I26: yes
G27: child benefit shit | H27: -80 | I27: yes | J27: f
A28: Mortgage H2B Plan | G28: zoom | H28: -18 | I28: yes
A29: Main | B29: 158345 | G29: gym | H29: -33 | I29: yes | J29: f
A30: Extra | B30: 83156 | G30: boiler | H30: -12 | I30: yes
A31: Total Due | B31: =SUM(B29:B30) -> 241501 | G31: christmas | H31: -500 | I31: yes
A32: H2B paybak | B32: =B33*0.2 -> 80000 | C32: - | G32: MATTS crdit card | H32: -160 | I32: yes
A33: Valuation | B33: 400000 | D33: 558.2 | G33: hoiliday | I33: no
A34: Equity | B34: =SUM(B31:B32)-B33 -> -78499 | D34: 484.16 | G34: help to by | H34: -114 | I34: yes
A35: Mortgage Amount | B35: =B32+B31 -> 321501 | D35: =D34-D33 -> -74.04 | G35: health insurance | H35: -50 | I35: yes | J35: f
G36: dentisyt | I36: no
I37: no

Sheet sept23
A1: Money | D1: Savings Account | G1: Name | H1: Value | I1: Paid? | J1: Who
A2: Paid | B2: 4911.86 | D2: Savings Account | E2: 100 | G2: Mortgage | H2: -897 | I2: yes
A3: Taken Already | B3: =SUMIF(I2:I28,"Yes*",H2:H28) -> -4033.26 | D3: corse money | G3: Car | H3: -244.8 | I3: yes | J3: f
A4: Balance | B4: 43.18 | G4: LifeInsurance/aviva | H4: -33 | I4: yes
A5: To Be Taken | B5: =SUMIF(I2:I37,"No",H2:H37) -> -41 | D5: garage fund | E5: 25 | G5: HouseInsurance - Tesco | H5: -39 | I5: yes
A6: Total | B6: =B5+B4 -> 2.18 | D6: rumpus vet fund | E6: 400 | G6: TvLicence | H6: -13.2 | I6: yes
A7: Francesca | B7: =SUMIF(J2:J32,"f",H2:H32) -> -1983.8 | D7: holiday money | G7: Gas/Electric | H7: -118 | I7: yes
D8: christmas | E8: 90 | G8: pet insur | H8: -40 | I8: yes
D9: garage fund | G9: spotoify | H9: -17.99 | I9: yes
D10: Saving Total | E10: =SUM(E2:E9) -> 615 | G10: isa savings | H10: -285 | I10: yes
G11: netflix | H11: -10.99 | I11: yes
D12: garage isa | G12: gym | H12: -26.99 | I12: yes
G13: council tax | H13: -214 | I13: yes
B14: 806.34 | G14: water | H14: -14 | I14: yes
B15: 891.38 | G15: savings | H15: -100 | I15: yes
B16: =B15+B14 -> 1697.72 | G16: water | H16: -29.2 | I16: yes
D17: expensis 224 | G17: hp | H17: -4.49 | I17: yes
A18: Mortgage | G18: car tax | H18: -180 | I18: yes
A19: Main | B19: 157869 | G19: fran money for card | H19: -800 | I19: yes | J19: f
A20: Extra | B20: 82960 | D20: WV6KZMV | G20: tesco mobiles | H20: -26 | I20: yes | J20: f
A21: Total Due | B21: =SUM(B19:B20) -> 240829 | D21: Silverboots69! | G21: credit card hsbc | I21: no | J21: f
A22: H2B paybak | B22: =B23*0.2 -> 80000 | D22: JL092865B | G22: food petrol | H22: -800 | I22: yes | J22: f
A23: Sold Price | B23: 400000 | G23: phone | H23: -11 | I23: no
A24: Equity | B24: =SUM(B21:B22)-B23 -> -79171 | G24: greenbelt | H24: -7.6 | I24: yes
A25: House Price | B25: 450000 | G25: window cleanewr | I25: no
A26: Mortgage Amount | B26: =B25+B24 -> 370829 | G26: car insurance lv | H26: -34 | I26: yes
G27: child benefit shit | H27: -80 | I27: yes | J27: f
A28: Mortgage H2B Plan | G28: zoom | H28: -18 | I28: yes
A29: Main | B29: 158345 | G29: gym | H29: -33 | I29: yes | J29: f
A30: Extra | B30: 83156 | G30: boiler | H30: -12 | I30: yes
A31: Total Due | B31: =SUM(B29:B30) -> 241501 | G31: christmas | H31: -195 | I31: yes
A32: H2B paybak | B32: =B33*0.2 -> 80000 | C32: - | G32: MATTS crdit card | H32: -296 | I32: yes
A33: Valuation | B33: 400000 | D33: 558.2 | G33: Francesca Money | H33: -935 | I33: yes
A34: Equity | B34: =SUM(B31:B32)-B33 -> -78499 | D34: 484.16 | G34: help to by | H34: -114 | I34: yes
A35: Mortgage Amount | B35: =B32+B31 -> 321501 | D35: =D34-D33 -> -74.04 | G35: health insurance | H35: -50 | I35: yes | J35: f
G36: Garage | H36: -30 | I36: no
I37: no

Sheet aug24
A1: Money | D1: Savings Account | G1: Name | H1: Value | I1: Paid? | J1: Who
A2: Paid | B2: 5038.84 | D2: Savings Account | E2: 14 | G2: Mortgage | H2: -897 | I2: yes
A3: Taken Already | B3: =SUMIF(I2:I28,"Yes*",H2:H28) -> -4823.27 | D3: corse money | G3: Car | H3: -244.8 | I3: yes | J3: f
A4: Balance | B4: 33.36 | G4: LifeInsurance/aviva | H4: -33 | I4: yes
A5: To Be Taken | B5: =SUMIF(I2:I37,"No",H2:H37) -> -29 | D5: garage fund | E5: 531.76 | G5: HouseInsurance - Tesco | H5: -39 | I5: yes
A6: Total | B6: =B5+B4 -> 4.36 | D6: rumpus vet fund | E6: 390 | G6: TvLicence | H6: -13.2 | I6: yes
A7: Francesca | B7: =SUMIF(J2:J32,"f",H2:H32) -> -2223.8 | D7: holiday money | G7: Gas/Electric | H7: -118 | I7: yes
D8: cat money | G8: pet insur | H8: -10 | I8: yes
D9: garage fund | G9: spotoify | H9: -16.99 | I9: yes
D10: Saving Total | E10: =SUM(E2:E9) -> 935.76 | G10: isa savings | H10: -650 | I10: yes
G11: netflix | H11: -10.99 | I11: yes
D12: garage isa | G12: plus net | H12: -7 | I12: yes
G13: council tax | H13: -214 | I13: yes
B14: 806.34 | G14: water | H14: -13 | I14: yes
B15: 891.38 | G15: PIXEL 7 | H15: -225 | I15: yes
B16: =B15+B14 -> 1697.72 | G16: water | H16: -29.2 | I16: yes
D17: expensis 224 | G17: hp | H17: -4.49 | I17: yes
A18: Mortgage | G18: service | H18: -300 | I18: yes
A19: Main | B19: 157869 | G19: fran money for card | H19: -900 | I19: yes | J19: f
A20: Extra | B20: 82960 | D20: WV6KZMV | G20: tesco | H20: -26 | I20: yes | J20: f
A21: Total Due | B21: =SUM(B19:B20) -> 240829 | D21: Silverboots69! | G21: hsbc Credit Card | H21: -100 | I21: yes | J21: f
A22: H2B paybak | B22: =B23*0.2 -> 80000 | D22: JL092865B | G22: food petrol | H22: -800 | I22: yes | J22: f
A23: Sold Price | B23: 400000 | G23: phone | H23: -11 | I23: no
A24: Equity | B24: =SUM(B21:B22)-B23 -> -79171 | G24: greenbelt | H24: -7.6 | I24: yes
A25: House Price | B25: 450000 | G25: window cleanewr | H25: -10 | I25: yes
A26: Mortgage Amount | B26: =B25+B24 -> 370829 | G26: car insurance lv | H26: -34 | I26: yes
G27: child benefit shit | H27: -120 | I27: yes | J27: f
A28: Mortgage H2B Plan | G28: zoom | H28: -18 | I28: no
A29: Main | B29: 158345 | G29: gym | H29: -33 | I29: yes | J29: f
A30: Extra | B30: 83156 | G30: boiler | H30: -12 | I30: yes
A31: Total Due | B31: =SUM(B29:B30) -> 241501 | G31: savings | I31: no
A32: H2B paybak | B32: =B33*0.2 -> 80000 | C32: - | G32: MATTS crdit card | H32: -211.5 | I32: yes
A33: Valuation | B33: 400000 | D33: 558.2 | G33: hoiliday | I33: no
A34: Equity | B34: =SUM(B31:B32)-B33 -> -78499 | D34: 484.16 | G34: help to by | H34: -114 | I34: yes
A35: Mortgage Amount | B35: =B32+B31 -> 321501 | D35: =D34-D33 -> -74.04 | G35: health insurance | H35: -50 | I35: yes | J35: f
G36: dentisyt | H36: -65 | I36: yes
I37: no

Sheet July23
A1: Money | D1: Savings Account | G1: Name | H1: Value | I1: Paid? | J1: Who
A2: Paid | B2: 5196.61 | D2: Savings Account | E2: 110 | G2: Mortgage | H2: -897 | I2: yes
A3: Taken Already | B3: =SUMIF(I2:I28,"Yes*",H2:H28) -> -4616.97 | D3: botox | G3: Car | H3: -244.8 | I3: yes | J3: f
A4: Balance | B4: 96.44 | G4: LifeInsurance/aviva | H4: -33 | I4: yes
A5: To Be Taken | B5: =SUMIF(I2:I37,"No",H2:H37) -> -94 | G5: HouseInsurance - Tesco | H5: -39 | I5: yes
A6: Total | B6: =B5+B4 -> 2.44 | D6: rumpus vet fund | E6: 380 | G6: TvLicence | H6: -13.2 | I6: yes
A7: Francesca | B7: =SUMIF(J2:J32,"f",H2:H32) -> -2211.25 | D7: holiday money | G7: Gas/Electric | H7: -118 | I7: yes
D8: cat money | G8: pet insur | H8: -40 | I8: yes
D9: garage fund | G9: spotoify | H9: -16.99 | I9: yes
D10: Saving Total | E10: =SUM(E2:E9) -> 490 | G10: isa savings | I10: no
G11: netflix | H11: -10.99 | I11: yes
D12: hyper jar | E12: 1348.47 | G12: plus net | I12: no
G13: council tax | H13: -214 | I13: yes
B14: 806.34 | G14: water | H14: -13 | I14: yes
B15: 891.38 | I15: no
B16: =B15+B14 -> 1697.72 | G16: water | H16: -29.2 | I16: yes
D17: expensis 224 | G17: hp | H17: -4.49 | I17: yes
A18: Mortgage | G18: HSBC CC | H18: -754 | I18: yes | J18: f
A19: Main | B19: 157869 | G19: fran money for card | H19: -800 | I19: yes | J19: f
A20: Extra | B20: 82960 | D20: WV6KZMV | G20: tesco | H20: -17.7 | I20: yes | J20: f
A21: Total Due | B21: =SUM(B19:B20) -> 240829 | D21: Silverboots69! | G21: summer holiday | H21: -200 | I21: yes
A22: H2B paybak | B22: =B23*0.2 -> 80000 | D22: JL092865B | G22: food petrol | H22: -1000 | I22: yes
A23: Sold Price | B23: 400000 | G23: phone | H23: -11 | I23: no | J23: f
A24: Equity | B24: =SUM(B21:B22)-B23 -> -79171 | G24: greenbelt | H24: -7.6 | I24: yes
A25: House Price | B25: 450000 | G25: window cleanewr | H25: -50 | I25: yes
A26: Mortgage Amount | B26: =B25+B24 -> 370829 | G26: car insurance lv | H26: -34 | I26: yes
G27: child benefit shit | H27: -80 | I27: yes | J27: f
A28: Mortgage H2B Plan | G28: zoom | H28: -18 | I28: no
A29: Main | B29: 158345 | G29: gym | H29: -33 | I29: yes | J29: f
A30: Extra | B30: 83156 | G30: boiler | H30: -12 | I30: yes
A31: Total Due | B31: =SUM(B29:B30) -> 241501 | G31: savings | I31: no
A32: H2B paybak | B32: =B33*0.2 -> 80000 | C32: - | G32: MATTS crdit card | H32: -270.75 | I32: yes | J32: f
A33: Valuation | B33: 400000 | D33: 558.2 | G33: willow phone | H33: -6.86 | I33: yes
A34: Equity | B34: =SUM(B31:B32)-B33 -> -78499 | D34: 484.16 | G34: help to by | H34: -114 | I34: yes
A35: Mortgage Amount | B35: =B32+B31 -> 321501 | D35: =D34-D33 -> -74.04 | G35: health insurance | H35: -50 | I35: yes | J35: f
G36: dentisyt | H36: -65 | I36: no
I37: no

Sheet june23
A1: Money | D1: Savings Account | G1: Name | H1: Value | I1: Paid?
A2: Paid | B2: 4850.83 | D2: Savings Account | E2: 135 | G2: Mortgage | H2: -897 | I2: yes
A3: Taken Already | B3: =SUMIF(I2:I28,"Yes*",H2:H28) -> -4202.02 | D3: botox | E3: 264.77 | G3: Car | H3: -244.8 | I3: yes
A4: Balance | B4: 21.46 | G4: LifeInsurance/aviva | H4: -33 | I4: yes
A5: To Be Taken | B5: =SUMIF(I2:I37,"No",H2:H37) -> 0 | G5: HouseInsurance - Tesco | H5: -39 | I5: yes
A6: Total | B6: =B5+B4 -> 21.46 | D6: rumpus vet fund | E6: 340 | G6: TvLicence | H6: -13.25 | I6: yes
D7: holiday money | G7: Gas/Electric | H7: -118 | I7: yes
D8: cat money | G8: pet insur | H8: -40 | I8: yes
B9: 4867.22 | G9: spotoify | H9: -16.99 | I9: yes
B10: 4745.42 | D10: Saving Total | E10: =SUM(E2:E9) -> 739.77 | G10: isa savings | H10: -500 | I10: yes
B11: =B10-B9 -> -121.8 | G11: netflix | H11: -10.99 | I11: yes
G12: plus net | H12: -60 | I12: yes
G13: council tax | H13: -214 | I13: yes
B14: 806.34 | G14: water | H14: -14 | I14: yes
B15: 891.38 | I15: no
B16: =B15+B14 -> 1697.72 | G16: water | H16: -29.2 | I16: yes
D17: expensis 224 | G17: hp | H17: -4.49 | I17: yes
A18: Mortgage | G18: HSBC CC | H18: -950 | I18: yes
A19: Main | B19: 157869 | G19: oven | H19: -50 | I19: yes
A20: Extra | B20: 82960 | D20: WV6KZMV | G20: Tesco Mobile | H20: -17.7 | I20: yes
A21: Total Due | B21: =SUM(B19:B20) -> 240829 | D21: Silverboots69! | G21: holiday | I21: no
A22: H2B paybak | B22: =B23*0.2 -> 80000 | D22: JL092865B | G22: food petrol | H22: -800 | I22: yes
A23: Sold Price | B23: 400000 | G23: NEXT | I23: no
A24: Equity | B24: =SUM(B21:B22)-B23 -> -79171 | G24: greenbelt | H24: -7.6 | I24: yes
A25: House Price | B25: 450000 | G25: window cleanewr | H25: -10 | I25: yes
A26: Mortgage Amount | B26: =B25+B24 -> 370829 | G26: car insurance lv | H26: -34 | I26: yes
G27: child benefit shit | H27: -80 | I27: yes
A28: Mortgage H2B Plan | G28: zoom | H28: -18 | I28: yes
A29: Main | B29: 158345 | G29: gym | H29: -33 | I29: yes
A30: Extra | B30: 83156 | G30: boiler | H30: -12 | I30: yes
A31: Total Due | B31: =SUM(B29:B30) -> 241501 | G31: savings | H31: -100 | I31: yes
A32: H2B paybak | B32: =B33*0.2 -> 80000 | C32: - | G32: MATTS crdit card | H32: -78 | I32: yes
A33: Valuation | B33: 400000 | D33: 558.2 | G33: willow phone | H33: -6.86 | I33: yes
A34: Equity | B34: =SUM(B31:B32)-B33 -> -78499 | D34: 484.16 | G34: help to by | H34: -114 | I34: yes
A35: Mortgage Amount | B35: =B32+B31 -> 321501 | D35: =D34-D33 -> -74.04 | G35: health insurance | H35: -50 | I35: yes
G36: dad bday | H36: -45 | I36: yes
G37: house | H37: -280 | I37: yes

Sheet may23
A1: Money | D1: Savings Account | G1: Name | H1: Value | I1: Paid? | J1: Who
A2: Paid | B2: 4868.23 | D2: Savings Account | E2: 140 | G2: Mortgage | H2: -897 | I2: yes
A3: Taken Already | B3: =SUMIF(I2:I28,"Yes*",H2:H28) -> -4533.31 | G3: Car | H3: -244.8 | I3: yes | J3: f
A4: Balance | B4: 32.91 | G4: LifeInsurance/aviva | H4: -33 | I4: yes
A5: To Be Taken | B5: =SUMIF(I2:I37,"No",H2:H37) -> -16 | G5: HouseInsurance - Tesco | I5: no
A6: Total | B6: =B5+B4 -> 16.91 | D6: rumpus vet fund | E6: 300 | G6: TvLicence | H6: -13.2 | I6: yes
A7: Francesca | B7: =SUMIF(J2:J32,"f",H2:H32) -> -1757.3 | D7: holiday money | G7: Gas/Electric | H7: -118 | I7: yes
G8: pet insur | I8: no
G9: spotoify | H9: -16.99 | I9: yes
D10: Saving Total | E10: =SUM(E2:E9) -> 440 | G10: isa savings | I10: no
G11: netflix | H11: -10.99 | I11: yes
G12: plus net | H12: -37.53 | I12: yes
G13: council tax | H13: -214 | I13: yes
B14: 806.34 | G14: water | H14: -13 | I14: yes
B15: 891.38 | G15: dentist | H15: -60 | I15: yes
B16: =B15+B14 -> 1697.72 | G16: water | H16: -29.2 | I16: yes
D17: expensis 224 | G17: hp | H17: -4.5 | I17: yes
A18: Mortgage | G18: HSBC CC | H18: -832 | I18: yes | J18: f
A19: Main | B19: 158345 | G19: tesco bank | H19: -500 | I19: yes | J19: f
A20: Extra | B20: 83156 | G20: Tesco Mobile | H20: -17.5 | I20: yes | J20: f
A21: Total Due | B21: =SUM(B19:B20) -> 241501 | G21: holiday | H21: -260 | I21: yes
A22: H2B paybak | B22: =B23*0.2 -> 90000 | D22: JL092865B | G22: food petrol | H22: -950 | I22: yes
A23: Sold Price | B23: 450000 | G23: NEXT | I23: no | J23: f
A24: Equity | B24: =SUM(B21:B22)-B23 -> -118499 | G24: greenbelt | H24: -7.6 | I24: yes
A25: House Price | B25: 450000 | G25: window cleanewr | H25: -10 | I25: yes
A26: Mortgage Amount | B26: =B25+B24 -> 331501 | G26: car insurance lv | H26: -34 | I26: yes
G27: child benefit shit | H27: -130 | I27: yes | J27: f
A28: Mortgage H2B Plan | G28: petrol | H28: -100 | I28: yes
A29: Main | B29: 158345 | G29: gym | H29: -33 | I29: yes | J29: f
A30: Extra | B30: 83156 | G30: boiler | H30: -12 | I30: yes
A31: Total Due | B31: =SUM(B29:B30) -> 241501 | G31: MATTS crdit card | H31: -359 | I31: yes
A32: H2B paybak | B32: =B33*0.2 -> 80000 | C32: - | G32: ebay | H32: -16 | I32: no
A33: Valuation | B33: 400000 | G33: willow phone | H33: -6.86 | I33: yes
A34: Equity | B34: =SUM(B31:B32)-B33 -> -78499 | G34: help to by | H34: -114 | I34: yes
A35: Mortgage Amount | B35: =B32+B31 -> 321501 | G35: health insurance | H35: -50 | I35: yes | J35: f
G36: father day | H36: -10 | I36: yes
G37: Fiber | H37: -18 | I37: yes

Sheet aprl23
A1: Money | D1: Savings Account | G1: Name | H1: Value | I1: Paid? | J1: Who
A2: Paid | B2: 4706.24 | D2: Savings Account | E2: 140 | G2: Mortgage | H2: -897 | I2: yes
A3: Taken Already | B3: =SUMIF(I2:I28,"Yes*",H2:H28) -> -4309.81 | G3: Car | H3: -244.8 | I3: yes | J3: f
A4: Balance | B4: 42.02 | G4: LifeInsurance/aviva | H4: -33 | I4: yes
A5: To Be Taken | B5: =SUMIF(I2:I38,"No",H2:H38) -> -35 | G5: HouseInsurance - Tesco | H5: -35 | I5: no
A6: Total | B6: =B5+B4 -> 7.02 | D6: rumpus vet fund | E6: 300 | G6: TvLicence | H6: -13.2 | I6: yes
A7: Francesca | B7: =SUMIF(J2:J32,"f",H2:H32) -> -1914.3 | D7: holiday money | E7: 180 | G7: Gas/Electric | H7: -118 | I7: yes
D8: cat money | E8: 50 | G8: pet insur | H8: -40 | I8: yes
G9: spotoify | H9: -16.99 | I9: yes
D10: Saving Total | E10: =SUM(E2:E9) -> 670 | I10: no
G11: netflix | H11: -10.99 | I11: yes
G12: plus net | H12: -37.53 | I12: yes
G13: council tax | H13: -214 | I13: yes
B14: 806.34 | G14: water | H14: -13 | I14: yes
B15: 891.38
B16: =B15+B14 -> 1697.72 | G16: water | H16: -29.2 | I16: yes
D17: expensis 224 | G17: hp | H17: -3 | I17: yes
A18: Mortgage | G18: HSBC CC | H18: -667 | I18: yes | J18: f
A19: Main | B19: 159289 | G19: tesco bank | H19: -835 | I19: yes | J19: f
A20: Extra | B20: 83545 | G20: Tesco Mobile | H20: -17.5 | I20: yes | J20: f
A21: Total Due | B21: =SUM(B19:B20) -> 242834 | G21: hotel | H21: -109 | I21: yes
A22: H2B paybak | B22: =B23*0.2 -> 90000 | D22: JL092865B | G22: food petrol | H22: -800 | I22: yes
A23: Sold Price | B23: 450000 | G23: NEXT | H23: -29 | I23: yes | J23: f
A24: Equity | B24: =SUM(B21:B22)-B23 -> -117166 | G24: greenbelt | H24: -7.6 | I24: yes
A25: House Price | B25: 450000 | G25: window cleanewr | H25: -10 | I25: yes
A26: Mortgage Amount | B26: =B25+B24 -> 332834 | G26: car insurance lv | H26: -34 | I26: yes
G27: child benefit shit | H27: -80 | I27: yes | J27: f
G28: cat | H28: -50 | I28: yes
G29: gym | H29: -33 | I29: yes | J29: f
G30: boiler | H30: -12 | I30: yes
G31: MATTS crdit card | H31: -104.46 | I31: yes
C32: - | G32: amazon | H32: -8 | I32: yes | J32: f
G33: willow phone | H33: -6.86 | I33: yes
G34: help to by | H34: -114 | I34: yes
G35: holiday | H35: -100 | I35: yes
G36: health insurance | H36: -50 | I36: yes | J36: f
I37: no
I38: no
I39: no

Sheet mar23
A1: Money | D1: Savings Account | G1: Name | H1: Value | I1: Paid? | J1: Who
A2: Paid | B2: 4665.77 | D2: Savings Account | E2: 140 | G2: Mortgage | H2: -897 | I2: yes
A3: Taken Already | B3: =SUMIF(I2:I28,"Yes*",H2:H28) -> -4431.72 | G3: Car | H3: -244.8 | I3: yes | J3: f
A4: Balance | B4: 27.45 | G4: LifeInsurance/aviva | H4: -33 | I4: yes
A5: To Be Taken | B5: =SUMIF(I2:I38,"No",H2:H38) -> 0 | G5: HouseInsurance - Tesco | H5: -35 | I5: yes
A6: Total | B6: =B5+B4 -> 27.45 | D6: rumpus vet fund | E6: 260 | G6: TvLicence | H6: -13.2 | I6: yes
A7: Francesca | B7: =SUMIF(J2:J32,"f",H2:H32) -> -1801.3 | D7: francesc london | G7: Gas/Electric | H7: -217 | I7: yes
G8: pet insur | H8: -40 | I8: yes
G9: spotoify | H9: -16.99 | I9: yes
D10: Saving Total | E10: =SUM(E2:E9) -> 400 | G10: willow guitar | H10: -62 | I10: yes
G11: netflix | H11: -10.99 | I11: yes
G12: plus net | H12: -31.67 | I12: yes
G13: council tax | H13: -214 | I13: yes
G14: water | H14: -13 | I14: yes
G15: GARDEN | H15: -6.25 | I15: yes
G16: water | H16: -28 | I16: yes
D17: expensis 224 | G17: hp | H17: -3 | I17: yes
A18: Mortgage | G18: HSBC CC | H18: -880 | I18: yes | J18: f
A19: Main | B19: 159289 | G19: tesco bank | H19: -530 | I19: yes | J19: f
A20: Extra | B20: 83545 | G20: Tesco Mobile | H20: -17.5 | I20: yes | J20: f
A21: Total Due | B21: =SUM(B19:B20) -> 242834 | G21: birthday | H21: -200 | I21: yes
A22: H2B paybak | B22: =B23*0.2 -> 90000 | D22: JL092865B | G22: food petrol | H22: -800 | I22: yes
A23: Sold Price | B23: 450000 | G23: NEXT | H23: -8 | I23: yes | J23: f
A24: Equity | B24: =SUM(B21:B22)-B23 -> -117166 | G24: greenbelt | H24: -7.4 | I24: yes
A25: House Price | B25: 375000 | G25: window cleanewr | H25: -10 | I25: yes
A26: Mortgage Amount | B26: =B25+B24 -> 257834 | G26: car insurance lv | H26: -32.92 | I26: yes
G27: child benefit shit | H27: -80 | I27: yes | J27: f
G28: train tickest | I28: no
G29: gym | H29: -33 | I29: yes | J29: f
G30: boiler | H30: -12 | I30: yes
G31: MATTS crdit card | H31: -31.76 | I31: yes
C32: - | G32: amazon | H32: -8 | I32: yes | J32: f
G33: willow phone | H33: -6 | I33: yes
G34: help to by | I34: no
I35: no
G36: health insurance | H36: -50 | I36: yes | J36: f
I37: no
I38: no
I39: no

Sheet feb23
C2: Money | F2: Savings Account | I2: Name | J2: Value | K2: Paid? | L2: Who
C3: Paid | D3: 4714.24 | F3: Savings Account | G3: 155 | I3: Mortgage | J3: -897 | K3: yes
C4: Taken Already | D4: =SUMIF(K3:K29,"Yes*",J3:J29) -> -4467.2 | I4: Car | J4: -244.8 | K4: yes | L4: f
C5: Balance | D5: 13.22 | I5: LifeInsurance/aviva | J5: -28.4 | K5: yes
C6: To Be Taken | D6: =SUMIF(K3:K39,"No",J3:J39) -> -11.7 | F6: camp | G6: 207 | I6: HouseInsurance - Tesco | J6: -35 | K6: yes
C7: Total | D7: =D6+D5 -> 1.52 | F7: rumpus vet fund | G7: 220 | I7: TvLicence | J7: -13.2 | K7: yes
C8: Francesca | D8: =SUMIF(L3:L33,"f",J3:J33) -> -1883.3 | F8: willow bday | G8: 218 | I8: Gas/Electric | J8: -217 | K8: yes
I9: pet insur | J9: -40 | K9: yes
I10: spotoify | J10: -16.99 | K10: yes
F11: Saving Total | G11: =SUM(G3:G10) -> 800 | I11: plusnet mobile | J11: -10 | K11: yes
I12: netflix | J12: -10.99 | K12: yes
I13: plus net | J13: -31.67 | K13: yes
I14: council tax | J14: -204 | K14: yes
I15: water | J15: -13 | K15: yes
I16: GARDEN | J16: -6.25 | K16: yes
I17: water | J17: -28 | K17: yes
F18: expensis 224 | I18: hp | J18: -3 | K18: yes
C19: Mortgage | I19: HSBC CC | J19: -765 | K19: yes | L19: f
C20: Main | D20: 159289 | I20: tesco bank | J20: -740 | K20: yes | L20: f
C21: Extra | D21: 83545 | I21: Tesco Mobile | J21: -12.5 | K21: yes | L21: f
C22: Total Due | D22: =SUM(D20:D21) -> 242834 | I22: bug | J22: -70 | K22: yes
C23: H2B paybak | D23: =D24*0.2 -> 90000 | F23: JL092865B | I23: food petrol | J23: -800 | K23: yes
C24: Sold Price | D24: 450000 | I24: NEXT | K24: no | L24: f
C25: Equity | D25: =D24-SUM(D22:D23) -> 117166 | I25: greenbelt | J25: -7.4 | K25: yes
C26: New House | D26: 450000 | I26: window cleanewr | J26: -10 | K26: yes
C27: Mortgage Required | D27: =D26-D25 -> 332834 | I27: car insurance lv | J27: -33 | K27: yes
I28: child benefit shit | J28: -80 | K28: yes | L28: f
I29: willow bday | J29: -150 | K29: yes
I30: gym | J30: -33 | K30: yes | L30: f
I31: boiler | J31: -11.7 | K31: no
I32: MATTS crdit card | J32: -132.37 | K32: yes
E33: - | I33: amazon | J33: -8 | K33: yes | L33: f
I34: willow phone | J34: -6 | K34: yes
I35: mothers day | J35: -20 | K35: yes
I36: beths noirday | J36: -25 | K36: yes
I37: health insurance | J37: -50 | K37: yes | L37: f
I38: bike | J38: -160 | K38: yes
K39: no
K40: no

Sheet Jan23
C2: Money | F2: Savings Account | I2: Name | J2: Value | K2: Paid? | L2: Who
C3: Paid | D3: 4830.24 | F3: Savings Account | G3: 160 | I3: Mortgage | J3: -897 | K3: yes
C4: Taken Already | D4: =SUMIF(K3:K29,"Yes*",J3:J29) -> -4627.7 | I4: Car | J4: -244.8 | K4: yes | L4: f
C5: Balance | D5: 8 | I5: LifeInsurance/aviva | J5: -28.4 | K5: yes
C6: To Be Taken | D6: =SUMIF(K3:K39,"No",J3:J39) -> 0 | F6: camo | G6: 207 | I6: HouseInsurance - Tesco | J6: -35 | K6: yes
C7: Total | D7: =D6+D5 -> 8 | F7: rumpus vet fund | G7: 230 | I7: TvLicence | J7: -13.2 | K7: yes
C8: Francesca | D8: =SUMIF(L3:L33,"f",J3:J33) -> -1949.3 | F8: willow bday | G8: 211 | I8: Gas/Electric | J8: -217 | K8: yes
F9: elec buffer | G9: 20 | I9: pet insur | J9: -80 | K9: yes
I10: spotoify | J10: -16.99 | K10: yes
F11: Saving Total | G11: =SUM(G3:G10) -> 828 | I11: plusnet mobile | J11: -10.5 | K11: yes
I12: netflix | J12: -10.99 | K12: yes
I13: plus net | J13: -31.67 | K13: yes
I14: council tax | J14: -204 | K14: yes
I15: water | J15: -13 | K15: yes
I16: GARDEN | J16: -6.25 | K16: yes
I17: water | J17: -28 | K17: yes
F18: expensis 224 | I18: hp | J18: -3 | K18: yes
C19: Mortgage | I19: HSBC CC | J19: -650 | K19: yes | L19: f
C20: Main | D20: 167660.11 | I20: tesco bank | J20: -860 | K20: yes | L20: f
C21: Extra | D21: 87559.93 | I21: Tesco Mobile | J21: -12.5 | K21: yes | L21: f
C22: Total Due | D22: =SUM(D20:D21) -> 255220.04 | I22: wbday | J22: -100 | K22: yes
C23: H2B paybak | D23: =D24*0.2 -> 89000 | F23: JL092865B | I23: food petrol | J23: -950 | K23: yes
C24: Sold Price | D24: 445000 | I24: NEXT | J24: -69 | K24: yes | L24: f
C25: Equity | D25: =SUM(D22:D23)-D24 -> -100779.96 | I25: greenbelt | J25: -7.4 | K25: yes
I26: window cleanewr | K26: no
I27: car insurance lv | J27: -33 | K27: yes
I28: child benefit shit | J28: -80 | K28: yes | L28: f
I29: matt | J29: -26 | K29: yes
I30: gym | J30: -25 | K30: yes | L30: f
I31: boiler | J31: -11.7 | K31: yes
I32: MATTS crdit card | J32: -43.36 | K32: yes
E33: - | I33: amazon | J33: -8 | K33: yes | L33: f
I34: willow phone | J34: -6 | K34: yes
I35: willow bday | J35: -20 | K35: yes
I36: birthdays | J36: -20 | K36: yes
I37: health insurance | J37: -50 | K37: yes | L37: f
I38: barcley | K38: no
I39: Matt | J39: -50 | K39: yes

Sheet dec
C2: Money | F2: Savings Account | I2: Name | J2: Value | K2: Paid? | L2: Who
C3: Paid | D3: 4791.7 | F3: Savings Account | G3: 180 | I3: Mortgage | J3: -897 | K3: yes
C4: Taken Already | D4: =SUMIF(K3:K29,"Yes*",J3:J29) -> -4752.2 | F4: london | I4: Car | J4: -244.8 | K4: yes | L4: f
C5: Balance | D5: 3.59 | I5: LifeInsurance/aviva | J5: -28.4 | K5: yes
C6: To Be Taken | D6: =SUMIF(K3:K39,"No",J3:J39) -> 0 | F6: francesca | I6: HouseInsurance - Tesco | J6: -35 | K6: yes
C7: Total | D7: =D6+D5 -> 3.59 | F7: rumpus vet fund | G7: 170 | I7: TvLicence | J7: -13.2 | K7: yes
C8: Francesca | D8: =SUMIF(L3:L33,"f",J3:J33) -> -2088.3 | F8: willow birthday | G8: 67 | I8: Gas/Electric | J8: -217 | K8: yes
F9: elec buffer | G9: 243 | I9: pet insur | J9: -40 | K9: yes
F10: matt ebay money | G10: 72 | I10: spotoify | J10: -16.99 | K10: yes
F11: Saving Total | G11: =SUM(G3:G10) -> 732 | I11: plusnet mobile | J11: -10 | K11: yes
I12: netflix | J12: -10.99 | K12: yes
I13: plus net | J13: -31.67 | K13: yes
I14: council tax | J14: -204 | K14: yes
I15: water | J15: -13 | K15: yes
I16: GARDEN | J16: -6.25 | K16: yes
I17: water | J17: -28 | K17: yes
F18: expensis 224 | I18: hp | J18: -6 | K18: yes
C19: Mortgage | I19: HSBC CC | J19: -938 | K19: yes | L19: f
C20: Main | D20: 167660.11 | I20: tesco bank | J20: -750 | K20: yes | L20: f
C21: Extra | D21: 87559.93 | I21: Tesco Mobile | J21: -12.5 | K21: yes | L21: f
C22: Total Due | D22: =SUM(D20:D21) -> 255220.04 | I22: nye | J22: -65 | K22: yes
C23: H2B paybak | D23: =D24*0.2 -> 89000 | F23: JL092865B | I23: food petrol | J23: -800 | K23: yes
C24: Sold Price | D24: 445000 | I24: NEXT | J24: -30 | K24: yes | L24: f
C25: Equity | D25: =SUM(D22:D23)-D24 -> -100779.96 | I25: greenbelt | J25: -7.4 | K25: yes
I26: window cleanewr | J26: -10 | K26: yes
I27: car insurance lv | J27: -33 | K27: yes
I28: child benefit shit | J28: -80 | K28: yes | L28: f
I29: food for christmas | J29: -224 | K29: yes
I30: gym | J30: -25 | K30: yes | L30: f
I31: boiler | J31: -11.7 | K31: yes
I32: MATTS crdit card | J32: -6 | K32: yes
E33: - | I33: amazon | J33: -8 | K33: yes | L33: f
I34: willow phone | J34: -6 | K34: yes
I35: francesca | J35: -190 | K35: yes
I36: birthdays | J36: -15 | K36: yes
I37: health insurance | J37: -50 | K37: yes
I38: barcley | J38: -18.69 | K38: yes
I39: mattxmas | J39: -72 | K39: yes

Sheet nov22
C2: Money | F2: Savings Account | I2: Name | J2: Value | K2: Paid? | L2: Who
C3: Paid | D3: 4830 | F3: Savings Account | G3: 180 | I3: Mortgage | J3: -897 | K3: yes
C4: Taken Already | D4: =SUMIF(K3:K29,"Yes*",J3:J29) -> -4400.2 | F4: london | I4: Car | J4: -244.8 | K4: yes | L4: f
C5: Balance | D5: 9.68 | I5: LifeInsurance/aviva | J5: -28.4 | K5: yes
C6: To Be Taken | D6: =SUMIF(K3:K39,"No",J3:J39) -> -9 | F6: CHRISTMAS | G6: 104 | I6: HouseInsurance - Tesco | J6: -35 | K6: yes
C7: Total | D7: =D6+D5 -> 0.68 | F7: rumpus vet fund | G7: 430 | I7: TvLicence | J7: -13.2 | K7: yes
C8: Francesca | D8: =SUMIF(L3:L33,"f",J3:J33) -> -1751.3 | F8: willow | I8: Gas/Electric | J8: -217 | K8: yes
F9: elec buffer | G9: 242 | I9: pet insur | J9: -40 | K9: yes
F10: wage | I10: spotoify | J10: -16.99 | K10: yes
F11: Saving Total | G11: =SUM(G3:G10) -> 956 | I11: plusnet mobile | J11: -10 | K11: yes
I12: netflix | J12: -10.99 | K12: yes
I13: plus net | J13: -31.67 | K13: yes
I14: council tax | J14: -204 | K14: yes
I15: water | J15: -13 | K15: yes
I16: GARDEN | J16: -6.25 | K16: yes
I17: water | J17: -28 | K17: yes
F18: expensis 224 | I18: hp | J18: -3 | K18: no
C19: Mortgage | I19: HSBC CC | J19: -520 | K19: yes | L19: f
C20: Main | D20: 167660.11 | I20: tesco bank | J20: -835 | K20: yes | L20: f
C21: Extra | D21: 87559.93 | I21: Tesco Mobile | J21: -12.5 | K21: yes | L21: f
C22: Total Due | D22: =SUM(D20:D21) -> 255220.04 | I22: dentist | J22: -60 | K22: yes
C23: H2B paybak | D23: =D24*0.2 -> 94000 | F23: JL092865B | I23: food petrol | J23: -800 | K23: yes
C24: Sold Price | D24: 470000 | I24: NEXT | J24: -26 | K24: yes | L24: f
C25: Equity | D25: =SUM(D22:D23)-D24 -> -120779.96 | I25: greenbelt | J25: -7.4 | K25: yes
I26: window cleanewr | J26: -10 | K26: yes
I27: car insurance lv | J27: -33 | K27: yes
I28: child benefit shit | J28: -80 | K28: yes | L28: f
I29: christmas | J29: -220 | K29: yes
I30: gym | J30: -25 | K30: yes | L30: f
I31: boier | J31: -11.7 | K31: yes
I32: MATTS crdit card | J32: -297 | K32: yes
E33: - | I33: amazon | J33: -8 | K33: yes | L33: f
I34: willow phone | J34: -6 | K34: no
I35: fran | J35: -25 | K35: yes
I36: rumpus | J36: -100 | K36: yes
K37: no
K38: no
K39: no

Sheet oct2
C2: Money | F2: Savings Account | I2: Name | J2: Value | K2: Paid? | L2: Who
C3: Paid | D3: 4475.69 | F3: Savings Account | G3: 180 | I3: Mortgage | J3: -897 | K3: yes
C4: Taken Already | D4: =SUMIF(K3:K29,"Yes*",J3:J29) -> -4339.2 | I4: Car | J4: -244.8 | K4: yes | L4: f
C5: Balance | D5: 145 | I5: LifeInsurance/aviva | J5: -28.4 | K5: yes
C6: To Be Taken | D6: =SUMIF(K3:K39,"No",J3:J39) -> -120 | F6: CHRISTMAS | G6: 240 | I6: HouseInsurance - Tesco | J6: -35 | K6: yes
C7: Total | D7: =D6+D5 -> 25 | F7: rumpus vet fund | G7: 390 | I7: TvLicence | J7: -13.2 | K7: yes
C8: Francesca | D8: =SUMIF(L3:L33,"f",J3:J33) -> -1917.3 | F8: willow | I8: Gas/Electric | J8: -217 | K8: yes
F9: elec buffer | G9: 235 | I9: pet insur | J9: -35 | K9: yes
F10: wage | I10: spotoify | J10: -16.99 | K10: yes
F11: Saving Total | G11: =SUM(G3:G10) -> 1045 | I11: plusnet mobile | J11: -10 | K11: yes
I12: netflix | J12: -10.99 | K12: yes
I13: plus net | J13: -31.67 | K13: yes
I14: council tax | J14: -204 | K14: yes
I15: water | J15: -13 | K15: yes
I16: GARDEN | J16: -6.25 | K16: yes
I17: water | J17: -27.8 | K17: yes
F18: 224.2 | I18: hp | J18: -3 | K18: yes
C19: Mortgage | I19: HSBC CC | J19: -790 | K19: yes | L19: f
C20: Main | D20: 167660.11 | I20: tesco bank | J20: -730 | K20: yes | L20: f
C21: Extra | D21: 87559.93 | I21: Tesco Mobile | J21: -12.5 | K21: yes | L21: f
C22: Total Due | D22: =SUM(D20:D21) -> 255220.04 | I22: petrol | J22: -25 | K22: yes
C23: H2B paybak | D23: =D24*0.2 -> 94000 | F23: JL092865B | I23: food petrol | J23: -530 | K23: yes
C24: Sold Price | D24: 470000 | I24: NEXT | J24: -22 | K24: yes | L24: f
C25: Equity | D25: =SUM(D22:D23)-D24 -> -120779.96 | I25: greenbelt | J25: -7.6 | K25: yes
I26: window cleanewr | J26: -10 | K26: yes
I27: car insurance lv | J27: -33 | K27: yes
I28: child benefit shit | J28: -85 | K28: yes | L28: f
I29: christmas | J29: -300 | K29: yes
I30: gym | J30: -25 | K30: yes | L30: f
I31: boier | J31: -11.7 | K31: yes
I32: MATTS | J32: -35 | K32: yes
E33: - | I33: amazon | J33: -8 | K33: yes | L33: f
I34: the ivy | J34: -120 | K34: no
I35: hayley | J35: -20 | K35: yes
I36: matts birthday | J36: -10 | K36: yes
I37: LONDON | J37: -60 | K37: yes
K38: no
K39: no

Sheet oct22
B2: Money | E2: Savings Account | H2: Name | I2: Value | J2: Paid? | K2: Who
B3: Paid | C3: 6080 | E3: Savings Account | F3: 180 | H3: Mortgage | I3: -797 | J3: no
B4: Taken Already | C4: =SUMIF(J3:J29,"Yes*",I3:I29) -> -3409.94 | E4: london | F4: 100 | H4: Car | I4: -244.8 | J4: yes | K4: f
B5: Balance | C5: 88.99 | E5: matt birthday | F5: 100 | H5: LifeInsurance/aviva | I5: -28.4 | J5: yes
B6: To Be Taken | C6: =SUMIF(J3:J39,"No",I3:I39) -> -882.06 | E6: CHRISTMAS | F6: 665 | H6: HouseInsurance - Tesco | I6: -35 | J6: no
B7: Total | C7: =C6+C5 -> -793.07 | E7: rumpus vet fund | F7: 356 | H7: TvLicence | I7: -13.2 | J7: yes
B8: Francesca | C8: =SUMIF(K3:K33,"f",I3:I33) -> -2407.1 | E8: willow | H8: Gas/Electric | I8: -217 | J8: yes
E9: elec buffer | F9: 263 | H9: pet insur | I9: -35 | J9: yes
C10: 4042 | E10: wage | F10: 4475.69 | H10: spotoify | I10: -16.99 | J10: yes
C11: =C5-C10 -> -3953.01 | E11: Saving Total | F11: =SUM(F3:F10) -> 6139.69 | H11: loan | I11: -395 | J11: yes
H12: netflix | I12: -10.99 | J12: no
B13: on cal | C13: 4172.91 | H13: plus net | I13: -31.67 | J13: no
B14: off call | C14: 3945 | H14: council tax | I14: -204 | J14: yes
H15: water | I15: -16 | J15: yes
E16: should have paid | F16: 4201.28 | H16: GARDEN | I16: -6.25 | J16: yes
E17: got paid after expence | F17: 168 owed hmrc | H17: water | I17: -35 | J17: yes
E18: 4369 | H18: hp | I18: -3 | J18: yes
B19: Mortgage | H19: HSBC CC | I19: -700 | J19: yes | K19: f
B20: Main | C20: 167660.11 | H20: tesco bank | I20: -254.8 | J20: yes | K20: f
B21: Extra | C21: 87559.93 | H21: Tesco Mobile | I21: -12.5 | J21: yes | K21: f
B22: Total Due | C22: =SUM(C20:C21) -> 255220.04 | H22: driving licence | I22: -15 | J22: yes
B23: H2B paybak | C23: =C24*0.2 -> 94000 | E23: JL092865B | H23: food petrol | I23: -950 | J23: yes | K23: f
B24: Sold Price | C24: 470000 | H24: NEXT | I24: -135 | J24: yes | K24: f
B25: Equity | C25: =SUM(C22:C23)-C24 -> -120779.96 | H25: greenbelt | I25: -7.4 | J25: no
H26: window cleanewr | I26: -10 | J26: yes
H27: car insurance lv | I27: -33 | J27: yes
H28: child benefit shit | I28: -85 | J28: yes | K28: f
B29: Loan Settlement (11/03/22) | C29: 11819 | H29: matts b | J29: no
B30: 45538 | C30: =C29/32 -> 369.34375 | H30: gym | I30: -25 | J30: yes | K30: f
C31: =C30*24 -> 8864.25 | H31: boier | I31: -11.7 | J31: yes
C32: =C31-C29 -> -2954.75 | F32: 720 | H32: MATTS | I32: -42.23 | J32: yes
E33: fuel | F33: 225 | H33: plusnet Mobile | I33: -10 | J33: yes
H34: tax | I34: -873.2 | J34: yes
H35: SAVONGS | I35: -100 | J35: yes
H36: Loan | I36: -8624.41 | J36: yes
J37: no
J38: no
J39: no
E43: 19th april
E44: 24yh

Sheet sept
C2: Money | F2: Savings Account | I2: Name | J2: Value | K2: Paid? | L2: Who
C3: Paid | D3: 4203.03 | F3: Savings Account | G3: 90 | I3: Mortgage | J3: -797 | K3: yes
C4: Taken Already | D4: =SUMIF(K3:K29,"Yes*",J3:J29) -> -3763.13 | I4: Car | J4: -244.8 | K4: yes | L4: f
C5: Balance | D5: 39 | F5: wage kitty loan | G5: 3396 | I5: LifeInsurance/aviva | J5: -28.4 | K5: yes
C6: To Be Taken | D6: =SUMIF(K3:K39,"No",J3:J39) -> -39.07 | F6: wage kitty | G6: 500 | I6: HouseInsurance - Tesco | J6: -35 | K6: yes
C7: Total | D7: =D6+D5 -> -0.07 | F7: rumpus vet fund | G7: 322 | I7: TvLicence | J7: -13.2 | K7: yes
C8: Francesca | D8: =SUMIF(L3:L33,"f",J3:J33) -> -1895.3 | I8: Gas/Electric | J8: -217 | K8: yes
I9: pet insur | J9: -35 | K9: yes
D10: 4042 | F10: francesca cashback | I10: spotoify | J10: -16.99 | K10: yes
D11: =D5-D10 -> -4003 | F11: Saving Total | G11: =SUM(G3:G10) -> 4308 | I11: loan | J11: -395 | K11: yes
I12: netflix | J12: -10.99 | K12: yes
C13: on cal | D13: 4172.91 | I13: plus net | J13: -31.67 | K13: no
C14: off call | D14: 3945 | I14: council tax | J14: -204 | K14: yes
I15: water | J15: -16 | K15: yes
F16: should have paid | G16: 4201.28 | I16: GARDEN | J16: -6.25 | K16: yes
F17: got paid after expence | G17: 168 owed hmrc | I17: water | J17: -35 | K17: yes
F18: 4369 | I18: hp | J18: -3 | K18: yes
C19: Mortgage | I19: HSBC CC | J19: -718 | K19: yes | L19: f
C20: Main | D20: 167660.11 | I20: tesco bank | J20: -15 | K20: yes | L20: f
C21: Extra | D21: 87559.93 | I21: Tesco Mobile | J21: -12.5 | K21: yes | L21: f
C22: Total Due | D22: =SUM(D20:D21) -> 255220.04 | I22: matt | J22: -17 | K22: yes
C23: H2B paybak | D23: =D24*0.2 -> 94000 | F23: JL092865B | I23: food petrol | J23: -800 | K23: yes | L23: f
C24: Sold Price | D24: 470000 | I24: NEXT | K24: yes | L24: f
C25: Equity | D25: =SUM(D22:D23)-D24 -> -120779.96 | I25: greenbelt | J25: -7.4 | K25: no
I26: window cleanewr | J26: -10 | K26: yes
I27: car insurance lv | J27: -33 | K27: yes
I28: child benefit shit | J28: -80 | K28: yes | L28: f
C29: Loan Settlement (11/03/22) | D29: 11819 | I29: train | J29: -20 | K29: yes
C30: 45538 | D30: =D29/32 -> 369.34375 | I30: gym | J30: -25 | K30: yes | L30: f
D31: =D30*24 -> 8864.25 | I31: service | J31: -215 | K31: yes
D32: =D31-D29 -> -2954.75 | G32: 720 | I32: car tax | J32: -160 | K32: yes
F33: fuel | G33: 225 | I33: plusnet Mobile | J33: -10 | K33: yes
I34: boiler | J34: -11.7 | K34: yes
I35: matt | J35: -50 | K35: yes

Sheet aug22
C2: Money | F2: Savings Account | I2: Name | J2: Value | K2: Paid? | L2: Who
C3: Paid | D3: 4120.77 | F3: Savings Account | G3: 190 | I3: Mortgage | J3: -797 | K3: yes
C4: Taken Already | D4: =SUMIF(K3:K29,"Yes*",J3:J29) -> -4018.96 | I4: Car | J4: -244.8 | K4: yes | L4: f
C5: Balance | D5: 9.43 | F5: wage kitty loan | G5: 1900 | I5: LifeInsurance/aviva | J5: -25.56 | K5: yes
C6: To Be Taken | D6: =SUMIF(K3:K39,"No",J3:J39) -> -7.4 | F6: wage kitty | G6: 1500 | I6: HouseInsurance - Tesco | J6: -35 | K6: yes
C7: Total | D7: =D6+D5 -> 2.03 | F7: rumpus vet fund | G7: 300 | I7: TvLicence | J7: -13.2 | K7: yes
C8: Francesca | D8: =SUMIF(L3:L33,"f",J3:J33) -> -1979.3 | I8: Gas/Electric | J8: -217 | K8: yes
I9: pet insur | J9: -35 | K9: yes
D10: 4042 | F10: francesca cashback | I10: spotoify | J10: -16.99 | K10: yes
D11: =D5-D10 -> -4032.57 | F11: Saving Total | G11: =SUM(G3:G10) -> 3890 | I11: loan | J11: -395 | K11: yes
I12: netflix | J12: -10.99 | K12: yes
C13: on cal | D13: 4172.91 | I13: plus net | J13: -31.67 | K13: yes
C14: off call | D14: 3945 | I14: council tax | J14: -204 | K14: yes
I15: water | J15: -16 | K15: yes
F16: should have paid | G16: 4201.28 | I16: GARDEN | J16: -6.25 | K16: yes
F17: got paid after expence | G17: 168 owed hmrc | I17: water | J17: -35 | K17: yes
F18: 4369 | I18: hp | J18: -3 | K18: yes
C19: Mortgage | I19: HSBC CC | J19: -725 | K19: yes | L19: f
C20: Main | D20: 167660.11 | I20: holiday | J20: -160 | K20: yes
C21: Extra | D21: 87559.93 | I21: Tesco Mobile | J21: -12.5 | K21: yes | L21: f
C22: Total Due | D22: =SUM(D20:D21) -> 255220.04 | I22: unit | K22: no
C23: H2B paybak | D23: =D24*0.2 -> 94000 | I23: food petrol | J23: -850 | K23: yes | L23: f
C24: Sold Price | D24: 470000 | I24: NEXT | J24: -42 | K24: yes | L24: f
C25: Equity | D25: =SUM(D22:D23)-D24 -> -120779.96 | I25: greenbelt | J25: -7.4 | K25: no
I26: window cleanewr | J26: -10 | K26: yes
I27: car insurance lv | J27: -33 | K27: yes
I28: child benefit shit | J28: -80 | K28: yes | L28: f
C29: Loan Settlement (11/03/22) | D29: 11819 | I29: train | J29: -20 | K29: yes
C30: 45538 | D30: =D29/32 -> 369.34375 | I30: gym | J30: -25 | K30: yes | L30: f
D31: =D30*24 -> 8864.25 | I31: savings | J31: -30 | K31: yes
D32: =D31-D29 -> -2954.75 | G32: 720 | I32: mholiday | J32: -70 | K32: yes
F33: fuel | G33: 225 | I33: fuel | J33: -60 | K33: yes
I34: dinner | J34: -500 | K34: yes
K35: no

Sheet july22
C2: Money | F2: Savings Account | I2: Name | J2: Value | K2: Paid? | L2: Who
C3: Paid | D3: 4608.2 | F3: Savings Account | G3: 208 | I3: Mortgage | J3: -797 | K3: yes
C4: Taken Already | D4: =SUMIF(K3:K29,"Yes*",J3:J29) -> -3964.36 | I4: Car | J4: -244.8 | K4: yes | L4: f
C5: Balance | D5: 73.29 | I5: LifeInsurance/aviva | J5: -25.56 | K5: yes
C6: To Be Taken | D6: =SUMIF(K3:K39,"No",J3:J39) -> -65 | F6: wage kitty | G6: 1500 | I6: HouseInsurance - Tesco | J6: -35 | K6: yes
C7: Total | D7: =D6+D5 -> 8.29 | F7: rumpus vet fund | G7: 260 | I7: TvLicence | J7: -13.2 | K7: yes
C8: Francesca | D8: =SUMIF(L3:L33,"f",J3:J33) -> -1960.3 | F8: holiday | G8: 560 | I8: Gas/Electric | J8: -217 | K8: yes
I9: pet insur | J9: -35 | K9: yes
D10: 4042 | F10: francesca cashback | I10: spotoify | J10: -16.99 | K10: yes
D11: =D5-D10 -> -3968.71 | F11: Saving Total | G11: =SUM(G3:G10) -> 2528 | I11: loan | J11: -395 | K11: yes
I12: netflix | J12: -10.99 | K12: yes
C13: on cal | D13: 4172.91 | I13: plus net | J13: -31.67 | K13: yes
C14: off call | D14: 3945 | I14: council tax | J14: -204 | K14: yes
C15: Mortgage | I15: water | J15: -16 | K15: yes
C16: Main | D16: 167660.11 | F16: should have paid | G16: 4201.28 | I16: GARDEN | J16: -6.25 | K16: yes
C17: Extra | D17: 87559.93 | F17: got paid after expence | G17: 168 owed hmrc | I17: water | J17: -35 | K17: yes
C18: Total Due | D18: =SUM(D16:D17) -> 255220.04 | F18: 4369 | I18: hp | J18: -3 | K18: yes
C19: H2B paybak | D19: =D20*0.2 -> 84000 | I19: HSBC CC | J19: -648 | K19: yes | L19: f
C20: Sold Price | D20: 420000 | I20: holiday | J20: -130 | K20: yes
C21: Equity | D21: =SUM(D18:D19)-D20 -> -80779.96 | I21: Tesco Mobile | J21: -12.5 | K21: yes | L21: f
I22: matts | J22: -7 | K22: yes
I23: food petrol | J23: -950 | K23: yes | L23: f
I24: NEXT | K24: no | L24: f
C25: Loan Settlement (11/03/22) | D25: 11819 | I25: greenbelt | J25: -7.4 | K25: yes
C26: 45538 | D26: =D25/32 -> 369.34375 | I26: window cleanewr | J26: -10 | K26: yes
D27: =D26*24 -> 8864.25 | I27: car insurance lv | J27: -33 | K27: yes
D28: =D27-D25 -> -2954.75 | I28: child benefit shit | J28: -80 | K28: yes | L28: f
I29: train | K29: no
I30: gym | J30: -25 | K30: yes | L30: f
I31: savings | J31: -380 | K31: yes
I32: CHAMPNEYS | J32: -100 | K32: yes
I33: toms bday | J33: -20 | K33: yes
I34: unit | J34: -65 | K34: no
K35: no

Sheet june
C2: Money | F2: Savings Account | I2: Name | J2: Value | K2: Paid? | L2: Who
C3: Paid | D3: 4459 | F3: Savings Account | G3: 305 | I3: Mortgage | J3: -797 | K3: yes
C4: Taken Already | D4: =SUMIF(K3:K29,"Yes*",J3:J29) -> -4108.36 | I4: Car | J4: -244.8 | K4: yes | L4: f
C5: Balance | D5: 38.57 | F5: train | G5: 80 | I5: LifeInsurance/aviva | J5: -25.56 | K5: yes
C6: To Be Taken | D6: =SUMIF(K3:K39,"No",J3:J39) -> -38 | I6: HouseInsurance - Tesco | J6: -35 | K6: yes
C7: Total | D7: =D6+D5 -> 0.57 | F7: rumpus vet fund | G7: 260 | I7: TvLicence | J7: -13.2 | K7: yes
C8: Francesca | D8: =SUMIF(L3:L33,"f",J3:J33) -> -1995.3 | F8: holiday | G8: 430 | I8: Gas/Electric | J8: -217 | K8: yes
I9: pet insur | J9: -35 | K9: yes
D10: 4042 | F10: francesca cashback | I10: spotoify | J10: -16.99 | K10: yes
D11: =D5-D10 -> -4003.43 | F11: Saving Total | G11: =SUM(G3:G10) -> 1075 | I11: loan | J11: -395 | K11: yes
I12: netflix | J12: -10.99 | K12: yes
C13: on cal | D13: 4172.91 | I13: plus net | J13: -31.67 | K13: yes
C14: off call | D14: 3945 | I14: council tax | J14: -204 | K14: yes
C15: Mortgage | I15: water | J15: -16 | K15: yes
C16: Main | D16: 167660.11 | F16: should have paid | G16: 4201.28 | I16: GARDEN | J16: -6.25 | K16: yes
C17: Extra | D17: 87559.93 | F17: got paid after expence | G17: 168 owed hmrc | I17: water | J17: -35 | K17: yes
C18: Total Due | D18: =SUM(D16:D17) -> 255220.04 | F18: 4369 | I18: hp | J18: -3 | K18: yes
C19: H2B paybak | D19: =D20*0.2 -> 84000 | I19: HSBC CC | J19: -748 | K19: yes | L19: f
C20: Sold Price | D20: 420000 | I20: holiday | J20: -150 | K20: yes
C21: Equity | D21: =SUM(D18:D19)-D20 -> -80779.96 | I21: Tesco Mobile | J21: -12.5 | K21: yes | L21: f
I22: matts | J22: -96 | K22: yes
I23: food petrol | J23: -800 | K23: yes | L23: f
I24: NEXT | J24: -85 | K24: yes | L24: f
C25: Loan Settlement (11/03/22) | D25: 11819 | I25: greenbelt | J25: -7.4 | K25: yes
C26: 45538 | D26: =D25/32 -> 369.34375 | I26: window cleanewr | J26: -10 | K26: yes
D27: =D26*24 -> 8864.25 | I27: car insurance lv | J27: -33 | K27: yes
D28: =D27-D25 -> -2954.75 | I28: child benefit shit | J28: -80 | K28: yes | L28: f
I29: train | J29: -38 | K29: no
I30: gym | J30: -25 | K30: yes | L30: f
I31: savings | J31: -110 | K31: yes
I32: dentist | J32: -60 | K32: yes
I33: fathers day | J33: -20 | K33: yes
I34: dinner | J34: -57 | K34: yes

Sheet may22
C2: Money | F2: Savings Account | I2: Name | J2: Value | K2: Paid? | L2: Who
C3: Paid | D3: 4221.73 | F3: Savings Account | G3: 310 | I3: Mortgage | J3: -797 | K3: yes
C4: Taken Already | D4: =SUMIF(K3:K29,"Yes*",J3:J29) -> -4070.51 | I4: Car | J4: -244.8 | K4: yes | L4: f
C5: Balance | D5: 8.33 | F5: train | G5: 90 | I5: LifeInsurance/aviva | J5: -25.56 | K5: yes
C6: To Be Taken | D6: =SUMIF(K3:K39,"No",J3:J39) -> -7.4 | I6: HouseInsurance - Tesco | K6: no
C7: Total | D7: =D6+D5 -> 0.93 | F7: rumpus vet fund | G7: 222 | I7: TvLicence | J7: -13.2 | K7: yes
C8: Francesca | D8: =SUMIF(L3:L33,"f",J3:J33) -> -1939.3 | F8: holiday | G8: 280 | I8: Gas/Electric | J8: -217 | K8: yes
I9: pet insur | J9: -35 | K9: yes
D10: 4042 | F10: francesca cashback | I10: spotoify | J10: -16.99 | K10: yes
D11: =D5-D10 -> -4033.67 | F11: Saving Total | G11: =SUM(G3:G10) -> 902 | I11: loan | J11: -395 | K11: yes
I12: netflix | J12: -10.99 | K12: yes
C13: EXPENSES | D13: 89.03 | I13: plus net | J13: -28.22 | K13: yes
I14: council tax | J14: -204 | K14: yes
C15: Mortgage | I15: water | J15: -16 | K15: Yes
C16: Main | D16: 167660.11 | I16: GARDEN | J16: -6.25 | K16: yes
C17: Extra | D17: 87559.93 | I17: water | J17: -35 | K17: yes
C18: Total Due | D18: =SUM(D16:D17) -> 255220.04 | F18: eric easter | G18: -6.99 | I18: hp | J18: -3 | K18: yes
C19: H2B paybak | D19: =D20*0.2 -> 84000 | F19: mum easter | G19: -6.99 | I19: HSBC CC | J19: -735 | K19: yes | L19: f
C20: Sold Price | D20: 420000 | I20: holiday | J20: -75 | K20: yes
C21: Equity | D21: =SUM(D18:D19)-D20 -> -80779.96 | F21: matts mum lego | G21: -30.48 | I21: Tesco Mobile | J21: -12.5 | K21: yes | L21: f
I22: matts | J22: -155 | K22: yes
G23: 200.05 | I23: food petrol | J23: -800 | K23: yes | L23: f
I24: NEXT | J24: -37 | K24: yes | L24: f
C25: Loan Settlement (11/03/22) | D25: 11819 | I25: greenbelt | J25: -7.4 | K25: no
C26: 45538 | D26: =D25/32 -> 369.34375 | I26: window cleanewr | K26: no
D27: =D26*24 -> 8864.25 | I27: car insurance lv | J27: -33 | K27: yes
D28: =D27-D25 -> -2954.75 | I28: child benefit shit | J28: -85 | K28: yes | L28: f
I29: train | J29: -90 | K29: yes
I30: gym | J30: -25 | K30: yes | L30: f
I31: savings | J31: -100 | K31: yes
K32: no
K33: no
K34: no

Sheet april22
C2: Money | F2: Savings Account | I2: Name | J2: Value | K2: Paid? | L2: Who
C3: Paid | D3: 4015.11 | F3: Savings Account | G3: 265 | I3: Mortgage | J3: -797 | K3: yes
C4: Taken Already | D4: =SUMIF(K3:K29,"Yes*",J3:J29) -> -3643.22 | I4: Car | J4: -244.8 | K4: yes | L4: f
C5: Balance | D5: 117.35 | F5: train | I5: LifeInsurance/aviva | J5: -25.56 | K5: yes
C6: To Be Taken | D6: =SUMIF(K3:K39,"No",J3:J39) -> -69.82 | F6: francesca meal | I6: HouseInsurance - Tesco | J6: -24.82 | K6: no
C7: Total | D7: =D6+D5 -> 47.53 | F7: rumpus vet fund | G7: 187 | I7: TvLicence | J7: -13.2 | K7: yes
C8: Francesca | D8: =SUMIF(L3:L33,"f",J3:J33) -> -1729.3 | F8: holiday | G8: 115 | I8: Gas/Electric | J8: -217 | K8: yes
I9: pet insur | J9: -35 | K9: yes
D10: 4042 | F10: francesca cashback | I10: spotoify | J10: -16.99 | K10: yes
D11: =D5-D10 -> -3924.65 | F11: Saving Total | G11: =SUM(G3:G10) -> 567 | I11: loan | J11: -395 | K11: yes
I12: netflix | J12: -10 | K12: yes
I13: plus net | J13: -28.22 | K13: yes
I14: council tax | J14: -204 | K14: yes
C15: Mortgage | I15: water | J15: -16 | K15: yes
C16: Main | D16: 167660.11 | I16: GARDEN | J16: -6.25 | K16: yes
C17: Extra | D17: 87559.93 | I17: water | J17: -35.3 | K17: yes
C18: Total Due | D18: =SUM(D16:D17) -> 255220.04 | F18: eric easter | G18: -6.99 | I18: hp | J18: -3 | K18: yes
C19: H2B paybak | D19: =D20*0.2 -> 84000 | F19: mum easter | G19: -6.99 | I19: HSBC CC | J19: -600 | K19: yes | L19: f
C20: Sold Price | D20: 420000 | I20: swim | J20: -24 | K20: yes
C21: Equity | D21: =SUM(D18:D19)-D20 -> -80779.96 | F21: matts mum lego | G21: -30.48 | I21: Tesco Mobile | J21: -12.5 | K21: yes | L21: f
I22: matts | J22: -60 | K22: yes
G23: 200.05 | I23: food petrol | J23: -750 | K23: yes | L23: f
I24: NEXT | J24: -12 | K24: yes | L24: f
C25: Loan Settlement (11/03/22) | D25: 11819 | I25: greenbelt | J25: -7.4 | K25: yes
C26: 45538 | D26: =D25/32 -> 369.34375 | I26: window cleanewr | J26: -10 | K26: yes
D27: =D26*24 -> 8864.25 | I27: car insurance lv | J27: -35 | K27: yes
D28: =D27-D25 -> -2954.75 | I28: child benefit shit | J28: -85 | K28: yes | L28: f
I29: train | J29: -45 | K29: no
I30: gym | J30: -25 | K30: yes | L30: f
I31: fran bday | J31: -220 | K31: yes
I32: wagamama | J32: -50 | K32: yes
K33: no
K34: no

Sheet march22
C2: Money | F2: Savings Account | I2: Name | J2: Value | K2: Paid? | L2: Who
C3: Paid | D3: 4246.71 | F3: Savings Account | G3: 355 | I3: Mortgage | J3: -797 | K3: yes
C4: Taken Already | D4: =SUMIF(K3:K29,"Yes*",J3:J29) -> -3883.34 | I4: Car | J4: -244.8 | K4: yes | L4: f
C5: Balance | D5: 8.17 | F5: train | I5: LifeInsurance/aviva | J5: -25.56 | K5: yes
C6: To Be Taken | D6: =SUMIF(K3:K39,"No",J3:J39) -> -7.4 | F6: francesca christmas | I6: HouseInsurance - Tesco | J6: -24.82 | K6: yes
C7: Total | D7: =D6+D5 -> 0.77 | F7: rumpus vet fund | G7: 152 | I7: TvLicence | J7: -13.2 | K7: yes
C8: Francesca | D8: =SUMIF(L3:L33,"f",J3:J33) -> -1805.3 | F8: EDF BUFFER | G8: 75 | I8: Gas/Electric | J8: -127 | K8: yes
I9: pet insur | J9: -35 | K9: yes
D10: 4042 | F10: francesca cashback | I10: spotoify | J10: -16.99 | K10: yes
D11: =D5-D10 -> -4033.83 | F11: Saving Total | G11: =SUM(G3:G10) -> 582 | I11: loan | J11: -395 | K11: yes
I12: netflix | J12: -10 | K12: yes
I13: plus net | J13: -28.22 | K13: yes
I14: council tax | J14: -198 | K14: yes
C15: Mortgage | I15: water | J15: -16 | K15: yes
C16: Main | D16: 167660.11 | I16: GARDEN | J16: -6.25 | K16: yes
C17: Extra | D17: 87559.93 | I17: water | J17: -35 | K17: yes
C18: Total Due | D18: =SUM(D16:D17) -> 255220.04 | F18: eric easter | G18: -6.99 | I18: hp | J18: -3 | K18: yes
C19: H2B paybak | D19: =D20*0.2 -> 84000 | F19: mum easter | G19: -6.99 | I19: HSBC CC | J19: -692 | K19: yes | L19: f
C20: Sold Price | D20: 420000 | I20: Swimming | J20: -24 | K20: yes
C21: Equity | D21: =SUM(D18:D19)-D20 -> -80779.96 | F21: matts mum lego | I21: Tesco Mobile | J21: -12.5 | K21: yes | L21: f
I22: matts | J22: -238 | K22: yes
G23: 200.05 | I23: food petrol | J23: -750 | K23: yes | L23: f
I24: francesca train | J24: -38 | K24: yes
I25: greenbelt | J25: -7.4 | K25: no
I26: next | J26: -11 | K26: yes | L26: f
I27: car insurance lv | J27: -35 | K27: yes
I28: child benefit shit | J28: -70 | K28: yes | L28: f
I29: train | J29: -37 | K29: yes
I30: gym | J30: -25 | K30: yes | L30: f
I31: willows birthday | J31: -155 | K31: yes
I32: mothers day | K32: no
I33: Savings | J33: -125 | K33: yes

Sheet Feb22
C2: Money | F2: Savings Account | I2: Name | J2: Value | K2: Paid? | L2: Who
C3: Paid | D3: 4354.71 | F3: Savings Account | G3: 290 | I3: Mortgage | J3: -797 | K3: yes
C4: Taken Already | D4: =SUMIF(K3:K29,"Yes*",J3:J29) -> -3794.83 | F4: holiday | I4: Car | J4: -244.8 | K4: yes | L4: f
C5: Balance | D5: 10.71 | F5: train | I5: LifeInsurance/aviva | J5: -25.56 | K5: yes
C6: To Be Taken | D6: =SUMIF(K3:K33,"No",J3:J33) -> -7.4 | F6: francesca christmas | I6: HouseInsurance - Tesco | J6: -24.82 | K6: yes
C7: Total | D7: =D6+D5 -> 3.31 | F7: rumpus vet fund | G7: 151 | I7: TvLicence | J7: -13.2 | K7: yes
C8: Francesca | D8: =SUMIF(L3:L33,"f",J3:J33) -> -1984.8 | F8: EDF BUFFER | G8: 35 | I8: Gas/Electric | J8: -127 | K8: yes
I9: pet insur | J9: -35 | K9: yes
D10: 4042 | F10: francesca cashback | I10: spotoify | J10: -16.99 | K10: yes
D11: =D5-D10 -> -4031.29 | F11: Saving Total | G11: =SUM(G3:G10) -> 476 | I11: loan | J11: -395 | K11: yes
I12: netflix | J12: -13.99 | K12: yes
F13: Botox | G13: 290 | I13: plus net | J13: -28.22 | K13: yes
I14: council tax | J14: -198 | K14: yes
C15: Mortgage | I15: water | J15: -16 | K15: yes
C16: Main | D16: 167660.11 | I16: GARDEN | J16: -6.25 | K16: yes
C17: Extra | D17: 87559.93 | I17: water | J17: -35 | K17: yes
C18: Total Due | D18: =SUM(D16:D17) -> 255220.04 | I18: hp | J18: -3 | K18: yes
C19: H2B paybak | D19: =D20*0.2 -> 84000 | F19: loan is 2600.00 | G19: 1082 | I19: HSBC CC | J19: -616 | K19: yes | L19: f
C20: Sold Price | D20: 420000 | F20: Paid 1 | G20: 160 | I20: swimming | J20: -24 | K20: yes
C21: Equity | D21: =SUM(D18:D19)-D20 -> -80779.96 | F21: Paid 1 | I21: Tesco Mobile | J21: -12.5 | K21: yes | L21: f
F22: Paid 1 | I22: tesco card | J22: -180 | K22: yes | L22: f
F23: Paid 1 | I23: food petrol | J23: -750 | K23: yes | L23: f
G24: =SUM(G20:G23)-G19 -> -922 | I24: window cleaner | J24: -10 | K24: yes
C25: christmas | I25: greenbelt | J25: -7.4 | K25: no
C26: mum and dad | D26: 60 | I26: next | J26: -66.5 | K26: yes | L26: f
C27: nana and eric | I27: car insurance lv | J27: -35 | K27: yes
C28: ben and lou | I28: child benefit shit | J28: -85 | K28: yes | L28: f
C29: food | I29: train | J29: -36 | K29: yes
C30: beth | I30: gym | J30: -30 | K30: yes | L30: f
C31: willows friend | I31: matts credit | J31: -259 | K31: yes
C32: teacher | I32: edf buffer | J32: -35 | K32: yes
D33: =SUM(D26:D32) -> 60 | I33: savings | J33: -275 | K33: yes

Sheet jAN22
C2: Money | F2: Savings Account | I2: Name | J2: Value | K2: Paid? | L2: Who
C3: Paid | D3: 4197.12 | F3: Savings Account | G3: 145 | I3: Mortgage | J3: -852.98 | K3: yes
C4: Taken Already | D4: =SUMIF(K3:K29,"Yes*",J3:J29) -> -3790.81 | I4: Car | J4: -244.8 | K4: yes | L4: f
C5: Balance | D5: 14.04 | F5: train | I5: LifeInsurance/aviva | J5: -25.56 | K5: yes
C6: To Be Taken | D6: =SUMIF(K3:K33,"No",J3:J33) -> -7.4 | F6: francesca christmas | I6: HouseInsurance - Tesco | J6: -24.82 | K6: yes
C7: Total | D7: =D6+D5 -> 6.64 | F7: rumpus vet fund | G7: 116 | I7: TvLicence | J7: -13.2 | K7: yes
C8: Francesca | D8: =SUMIF(L3:L33,"f",J3:J33) -> -1901.8 | F8: EDF BUFFER | I8: Gas/Electric | J8: -127 | K8: yes
I9: pet insur | J9: -35 | K9: yes
D10: 4042 | F10: francesca cashback | I10: spotoify | J10: -16.99 | K10: yes
D11: =D5-D10 -> -4027.96 | F11: Saving Total | G11: =SUM(G3:G10) -> 261 | I11: loan | J11: -395 | K11: yes
I12: netflix | J12: -13.99 | K12: yes
F13: Botox | G13: 290 | I13: plus net | J13: -28.22 | K13: yes
I14: council tax | J14: -198 | K14: yes
C15: Mortgage | I15: water | J15: -16 | K15: yes
C16: Main | D16: 167660.11 | I16: GARDEN | J16: -6.25 | K16: yes
C17: Extra | D17: 87559.93 | I17: water | J17: -35 | K17: yes
C18: Total Due | D18: =SUM(D16:D17) -> 255220.04 | I18: hp | J18: -2 | K18: yes
C19: H2B paybak | D19: =D20*0.2 -> 84000 | F19: loan is 2600.00 | G19: 1082 | I19: HSBC CC | J19: -650 | K19: yes | L19: f
C20: Sold Price | D20: 420000 | F20: Paid 1 | G20: 160 | I20: swimming | J20: -24 | K20: yes
C21: Equity | D21: =SUM(D18:D19)-D20 -> -80779.96 | F21: Paid 1 | I21: Tesco Mobile | J21: -12.5 | K21: yes | L21: f
F22: Paid 1 | I22: tesco card | J22: -100 | K22: yes | L22: f
F23: Paid 1 | I23: food petrol | J23: -846 | K23: yes | L23: f
G24: =SUM(G20:G23)-G19 -> -922 | I24: window cleaner | J24: -10 | K24: yes
C25: christmas | I25: greenbelt | J25: -7.4 | K25: no
C26: mum and dad | D26: 60 | I26: next | J26: -38.5 | K26: yes | L26: f
C27: nana and eric | I27: car insurance lv | J27: -35 | K27: yes
C28: ben and lou | I28: savings | K28: no
C29: food | I29: Birthday | J29: -40 | K29: yes
C30: beth | I30: gym | J30: -10 | K30: yes | L30: f
C31: willows friend | I31: matts credit | J31: -8 | K31: yes
C32: teacher | I32: berclay | J32: -37 | K32: yes
D33: =SUM(D26:D32) -> 60 | I33: savings | J33: -150 | K33: yes
K34: no

Sheet FebEstimate
A1: Money | D1: Savings Account | G1: Name | H1: Value | I1: Paid? | J1: Who
A2: Paid | B2: 4650 | D2: Savings Account | E2: 140 | G2: Mortgage | H2: -1295.21 | I2: no
A3: Taken Already | B3: =SUMIF(I2:I28,"Yes*",H2:H28) -> 0 | G3: Car | H3: -244.8 | I3: no | J3: f
A4: Balance | B4: 4650 | G4: LifeInsurance/aviva | H4: -33 | I4: no
A5: To Be Taken | B5: =SUMIF(I2:I37,"No",H2:H37) -> -4153.99 | G5: HouseInsurance - Tesco | H5: -38 | I5: no
A6: Total | B6: =B5+B4 -> 496.01 | D6: rumpus vet fund | E6: 300 | G6: TvLicence | H6: -13.2 | I6: no
A7: Francesca | B7: =SUMIF(J2:J32,"f",H2:H32) -> -1209.3 | D7: holiday money | E7: 180 | G7: Gas/Electric | H7: -170 | I7: no
D8: cat money | E8: 50 | G8: pet insur | H8: -40 | I8: no
G9: spotoify | H9: -16.99 | I9: no
D10: Saving Total | E10: =SUM(E2:E9) -> 670 | G10: phone | H10: -10 | I10: no
G11: netflix | H11: -10.99 | I11: no
G12: zoom | H12: -18 | I12: no
G13: council tax | H13: -214 | I13: no
G14: water | H14: -13 | I14: no
G15: GARDEN | I15: no
G16: water | H16: -29.2 | I16: no
G17: hp | H17: -4.5 | I17: no
G18: HSBC CC | H18: -800 | I18: no | J18: f
G19: tesco bank | I19: no | J19: f
G20: Tesco Mobile | H20: -26.5 | I20: no | J20: f
G21: holiday | I21: no
G22: food petrol | H22: -800 | I22: no
G23: NEXT | I23: no | J23: f
G24: greenbelt | H24: -7.6 | I24: no
G25: window cleanewr | H25: -10 | I25: no
G26: car insurance lv | H26: -34 | I26: no
G27: child benefit shit | H27: -80 | I27: no | J27: f
G28: cat | I28: no
G29: gym | H29: -58 | I29: no | J29: f
G30: boiler | H30: -12 | I30: no
G31: MATTS crdit card | I31: no
I32: no | J32: f
G33: willow phone | I33: no
G34: help top buy | H34: -125 | I34: no
G35: health insurance | H35: -50 | I35: no | J35: f
I36: no
I37: no
I38: no

Sheet Minimum
C2: Money | I2: Name | J2: Value | K2: Paid? | L2: Who
C3: Paid | D3: 5250 | I3: Mortgage | J3: -1267 | K3: no
C4: Taken Already | D4: =SUMIF(K3:K29,"Yes*",J3:J29) -> 0 | I4: food petrol | J4: -900 | K4: no | L4: f
C5: Balance | D5: 5250 | I5: fran money | J5: -800 | K5: no
C6: To Be Taken | D6: =SUMIF(K3:K39,"No",J3:J39) -> -3947.69 | I6: rumpus | J6: -60 | K6: no | L6: f
C7: Total | D7: =D6+D5 -> 1302.31 | I7: council tax | J7: -225 | K7: no
C8: Francesca | D8: =SUMIF(L3:L33,"f",J3:J33) -> -1240 | I8: Gas/Electric | J8: -155 | K8: no
I9: help to by | J9: -140 | K9: no | L9: f
I10: child benefit shit | J10: -80 | K10: no | L10: f
I11: HouseInsurance - Tesco | J11: -35 | K11: no
I12: pet insur | J12: -35 | K12: no
I13: car insurance lv | J13: -33 | K13: no
I14: gym | J14: -33 | K14: no | L14: f
I15: LifeInsurance/aviva | J15: -28.4 | K15: no
I16: water | J16: -28 | K16: no
I17: Tesco Mobile | J17: -27 | K17: no | L17: f
I18: internet | J18: -18 | K18: no
I19: spotoify | J19: -20 | K19: no
I20: TvLicence | J20: -13.2 | K20: no
I21: water | J21: -13 | K21: no
I22: boier | J22: -11.7 | K22: no
I23: window cleanewr | J23: -10 | K23: no
I24: netflix | J24: -7.99 | K24: no
I25: greenbelt | J25: -7.4 | K25: no
K26: no
K27: no
K28: no
K29: no
K30: no
K31: no
K32: no | L32: f
K33: no
K34: no
K35: no
K36: no

Sheet eBay (2)
A1: Date | B1: Item | C1: Money In | D1: Fee | E1: Postage | F1: Payout | G1: Total | H1: Link | I1: Postage Quoted | J1: Postage Profit | K1: Postage Paid | L1: Payed Out | M1: Column1
A2: 45423 | B2: google speakers | C2: 65 | D2: 8.6 | E2: 4.79 | F2: =Table13[[#This Row],[Money In]]-Table13[[#This Row],[Fee]] -> 56.4 | G2: =C2-E2-Table13[[#This Row],[Fee]] -> 51.61 | I2: 5 | J2: =Table13[[#This Row],[Postage Quoted]]-Table13[[#This Row],[Postage]] -> 0.21 | K2: Y | L2: Y
A3: 45428 | B3: Headphones | C3: 35.45 | D3: 4.68 | E3: 4.79 | F3: =Table13[[#This Row],[Money In]]-Table13[[#This Row],[Fee]] -> 30.77 | G3: =C3-E3-Table13[[#This Row],[Fee]] -> 25.98 | I3: 5 | J3: =Table13[[#This Row],[Postage Quoted]]-Table13[[#This Row],[Postage]] -> 0.21 | K3: N | L3: Y
A4: 45428 | B4: Nespresso | C4: 40.5 | D4: 5.35 | E4: 3.84 | F4: =Table13[[#This Row],[Money In]]-Table13[[#This Row],[Fee]] -> 35.15 | G4: =C4-E4-Table13[[#This Row],[Fee]] -> 31.31 | I4: 7.5 | J4: =Table13[[#This Row],[Postage Quoted]]-Table13[[#This Row],[Postage]] -> 3.66 | K4: N | L4: Y
A5: 45428 | B5: Google Nest | C5: 15.5 | D5: 2.04 | E5: 4.79 | F5: =Table13[[#This Row],[Money In]]-Table13[[#This Row],[Fee]] -> 13.46 | G5: =Table13[[#This Row],[Money In]]-Table13[[#This Row],[Postage]]-Table13[[#This Row],[Fee]] -> 8.67 | I5: 5 | J5: =Table13[[#This Row],[Postage Quoted]]-Table13[[#This Row],[Postage]] -> 0.21 | K5: N | L5: Y
A6: 45428 | B6: Powerline | C6: 15.5 | D6: 2.04 | E6: 4.79 | F6: =Table13[[#This Row],[Money In]]-Table13[[#This Row],[Fee]] -> 13.46 | G6: =Table13[[#This Row],[Money In]]-Table13[[#This Row],[Postage]]-Table13[[#This Row],[Fee]] -> 8.67 | I6: 5 | J6: =Table13[[#This Row],[Postage Quoted]]-Table13[[#This Row],[Postage]] -> 0.21 | K6: N | L6: Y
A7: 45430 | B7: Smeg Coffee | C7: 100 | D7: 13.22 | E7: 7.99 | F7: =Table13[[#This Row],[Money In]]-Table13[[#This Row],[Fee]] -> 86.78 | G7: =Table13[[#This Row],[Money In]]-Table13[[#This Row],[Postage]]-Table13[[#This Row],[Fee]] -> 78.79 | I7: 10 | J7: =Table13[[#This Row],[Postage Quoted]]-Table13[[#This Row],[Postage]] -> 2.01 | K7: N | L7: Y
A8: 45431 | B8: Oneplus Charger | C8: 10 | D8: 1.33 | E8: 3.39 | F8: =Table13[[#This Row],[Money In]]-Table13[[#This Row],[Fee]] -> 8.67 | G8: =Table13[[#This Row],[Money In]]-Table13[[#This Row],[Postage]]-Table13[[#This Row],[Fee]] -> 5.28 | I8: 5 | J8: =Table13[[#This Row],[Postage Quoted]]-Table13[[#This Row],[Postage]] -> 1.61 | K8: N | L8: Y
F9: =Table13[[#This Row],[Money In]]-Table13[[#This Row],[Fee]] -> 0 | G9: =Table13[[#This Row],[Money In]]-Table13[[#This Row],[Postage]]-Table13[[#This Row],[Fee]] -> 0 | J9: =Table13[[#This Row],[Postage Quoted]]-Table13[[#This Row],[Postage]] -> 0
F10: =Table13[[#This Row],[Money In]]-Table13[[#This Row],[Fee]] -> 0 | G10: =Table13[[#This Row],[Money In]]-Table13[[#This Row],[Postage]]-Table13[[#This Row],[Fee]] -> 0 | J10: =Table13[[#This Row],[Postage Quoted]]-Table13[[#This Row],[Postage]] -> 0
F11: =Table13[[#This Row],[Money In]]-Table13[[#This Row],[Fee]] -> 0 | G11: =Table13[[#This Row],[Money In]]-Table13[[#This Row],[Postage]]-Table13[[#This Row],[Fee]] -> 0 | J11: =Table13[[#This Row],[Postage Quoted]]-Table13[[#This Row],[Postage]] -> 0
F12: =Table13[[#This Row],[Money In]]-Table13[[#This Row],[Fee]] -> 0 | G12: =Table13[[#This Row],[Money In]]-Table13[[#This Row],[Postage]]-Table13[[#This Row],[Fee]] -> 0 | J12: =Table13[[#This Row],[Postage Quoted]]-Table13[[#This Row],[Postage]] -> 0
F13: =Table13[[#This Row],[Money In]]-Table13[[#This Row],[Fee]] -> 0 | G13: =Table13[[#This Row],[Money In]]-Table13[[#This Row],[Postage]]-Table13[[#This Row],[Fee]] -> 0 | J13: =Table13[[#This Row],[Postage Quoted]]-Table13[[#This Row],[Postage]] -> 0
F14: =Table13[[#This Row],[Money In]]-Table13[[#This Row],[Fee]] -> 0 | G14: =Table13[[#This Row],[Money In]]-Table13[[#This Row],[Postage]]-Table13[[#This Row],[Fee]] -> 0 | J14: =Table13[[#This Row],[Postage Quoted]]-Table13[[#This Row],[Postage]] -> 0
F15: =Table13[[#This Row],[Money In]]-Table13[[#This Row],[Fee]] -> 0 | G15: =Table13[[#This Row],[Money In]]-Table13[[#This Row],[Postage]]-Table13[[#This Row],[Fee]] -> 0 | J15: =Table13[[#This Row],[Postage Quoted]]-Table13[[#This Row],[Postage]] -> 0
F16: =Table13[[#This Row],[Money In]]-Table13[[#This Row],[Fee]] -> 0 | G16: =Table13[[#This Row],[Money In]]-Table13[[#This Row],[Postage]]-Table13[[#This Row],[Fee]] -> 0 | J16: =Table13[[#This Row],[Postage Quoted]]-Table13[[#This Row],[Postage]] -> 0
F17: =Table13[[#This Row],[Money In]]-Table13[[#This Row],[Fee]] -> 0 | G17: =Table13[[#This Row],[Money In]]-Table13[[#This Row],[Postage]]-Table13[[#This Row],[Fee]] -> 0 | J17: =Table13[[#This Row],[Postage Quoted]]-Table13[[#This Row],[Postage]] -> 0
F18: =Table13[[#This Row],[Money In]]-Table13[[#This Row],[Fee]] -> 0 | G18: =Table13[[#This Row],[Money In]]-Table13[[#This Row],[Postage]]-Table13[[#This Row],[Fee]] -> 0 | J18: =Table13[[#This Row],[Postage Quoted]]-Table13[[#This Row],[Postage]] -> 0
F19: =Table13[[#This Row],[Money In]]-Table13[[#This Row],[Fee]] -> 0 | G19: =Table13[[#This Row],[Money In]]-Table13[[#This Row],[Postage]]-Table13[[#This Row],[Fee]] -> 0 | J19: =Table13[[#This Row],[Postage Quoted]]-Table13[[#This Row],[Postage]] -> 0
F20: =Table13[[#This Row],[Money In]]-Table13[[#This Row],[Fee]] -> 0 | G20: =Table13[[#This Row],[Money In]]-Table13[[#This Row],[Postage]]-Table13[[#This Row],[Fee]] -> 0 | J20: =Table13[[#This Row],[Postage Quoted]]-Table13[[#This Row],[Postage]] -> 0
... F25: =Table13[[#This Row],[Money In]]-Table13[[#This Row],[Fee]] -> 0 | G25: =Table13[[#This Row],[Money In]]-Table13[[#This Row],[Postage]]-Table13[[#This Row],[Fee]] -> 0 | J25: =Table13[[#This Row],[Postage Quoted]]-Table13[[#This Row],[Postage]] -> 0
B27: TOTAL | C27: =SUM(C2:C25) -> 281.95 | D27: =SUM(D2:D25) -> 37.26 | E27: =SUM(E2:E25) -> 34.38 | F27: =SUM(F2:F25) -> 244.69 | G27: =SUM(G2:G25) -> 210.31 | I27: =SUM(I2:I25) -> 42.5 | J27: =SUM(J2:J25) -> 8.12 | K27: =SUMIF(K2:K25,"N",E2:E25) -> 29.59 | L27: =SUMIF(L2:L25,"N",F2:F25) -> 0

Sheet eBay
A1: Date | B1: Item | C1: Money In | D1: Fee | E1: Postage | F1: Payout | G1: Total | H1: Link | I1: Postage Quoted | J1: Postage Profit | K1: Postage Paid | L1: Payed Out | M1: Column1 | O1: Item | P1: Price
A2: 45123 | B2: Hobbs Coat | C2: 25.99 | D2: 0.97 | E2: 4.65 | F2: =Table1[[#This Row],[Money In]]-Table1[[#This Row],[Fee]] -> 25.02 | G2: =C2-E2-Table1[[#This Row],[Fee]] -> 20.37 | H2: Order details (ebay.co.uk) | I2: 5.99 | J2: =Table1[[#This Row],[Postage Quoted]]-Table1[[#This Row],[Postage]] -> 1.34 | K2: Y | L2: Y | O2: Durham Mug | P2: 30
A3: 45125 | B3: Webcam | C3: 21.95 | D3: 0.86 | E3: 2.7 | F3: =Table1[[#This Row],[Money In]]-Table1[[#This Row],[Fee]] -> 21.09 | G3: =C3-E3-Table1[[#This Row],[Fee]] -> 18.39 | H3: Order details (ebay.co.uk) | I3: 3.95 | J3: =Table1[[#This Row],[Postage Quoted]]-Table1[[#This Row],[Postage]] -> 1.25 | K3: Y | L3: Y | O3: Tiny Tea Cup | P3: 15
A4: 45126 | B4: Football Shirt | C4: 38.95 | D4: 1.3 | E4: 3.45 | F4: =Table1[[#This Row],[Money In]]-Table1[[#This Row],[Fee]] -> 37.65 | G4: =C4-E4-Table1[[#This Row],[Fee]] -> 34.2 | H4: Order details (ebay.co.uk) | I4: 3.95 | J4: =Table1[[#This Row],[Postage Quoted]]-Table1[[#This Row],[Postage]] -> 0.5 | K4: Y | L4: Y | O4: cats on rug | P4: 16
A5: 45126 | B5: Polka Dot Dress | C5: 20 | D5: 0.81 | E5: 3.45 | F5: =Table1[[#This Row],[Money In]]-Table1[[#This Row],[Fee]] -> 19.19 | G5: =Table1[[#This Row],[Money In]]-Table1[[#This Row],[Postage]]-Table1[[#This Row],[Fee]] -> 15.74 | H5: Order details (ebay.co.uk) | I5: 4 | J5: =Table1[[#This Row],[Postage Quoted]]-Table1[[#This Row],[Postage]] -> 0.55 | K5: Y | L5: Y | O5: Trophy | P5: 75
A6: 45128 | B6: Highchar | C6: 40 | D6: 1.32 | E6: 8 | F6: =Table1[[#This Row],[Money In]]-Table1[[#This Row],[Fee]] -> 38.68 | G6: =Table1[[#This Row],[Money In]]-Table1[[#This Row],[Postage]]-Table1[[#This Row],[Fee]] -> 30.68 | H6: Order details (ebay.co.uk) | I6: 8 | J6: =Table1[[#This Row],[Postage Quoted]]-Table1[[#This Row],[Postage]] -> 0 | K6: Y | L6: Y | O6: Rose Bee Mug | P6: 15
A7: 45128 | B7: Bose headphones | C7: 35 | D7: 4.78 | E7: 2.7 | F7: =Table1[[#This Row],[Money In]]-Table1[[#This Row],[Fee]] -> 30.22 | G7: =Table1[[#This Row],[Money In]]-Table1[[#This Row],[Postage]]-Table1[[#This Row],[Fee]] -> 27.52 | H7: Order details (ebay.co.uk) | I7: 3 | J7: =Table1[[#This Row],[Postage Quoted]]-Table1[[#This Row],[Postage]] -> 0.3 | K7: Y | L7: Y | O7: Sampler Jug | P7: 20
A8: 45128 | B8: MK Coat | C8: 15.95 | D8: 0.71 | E8: 4.15 | F8: =Table1[[#This Row],[Money In]]-Table1[[#This Row],[Fee]] -> 15.24 | G8: =Table1[[#This Row],[Money In]]-Table1[[#This Row],[Postage]]-Table1[[#This Row],[Fee]] -> 11.09 | H8: Order details (ebay.co.uk) | I8: 5.95 | J8: =Table1[[#This Row],[Postage Quoted]]-Table1[[#This Row],[Postage]] -> 1.8 | K8: Y | L8: Y | O8: Love all over mug | P8: 20
A9: 45129 | B9: JC Changing Bag | C9: 29.5 | D9: 1.06 | E9: 5.45 | F9: =Table1[[#This Row],[Money In]]-Table1[[#This Row],[Fee]] -> 28.44 | G9: =Table1[[#This Row],[Money In]]-Table1[[#This Row],[Postage]]-Table1[[#This Row],[Fee]] -> 22.99 | H9: Order details (ebay.co.uk) | I9: 7 | J9: =Table1[[#This Row],[Postage Quoted]]-Table1[[#This Row],[Postage]] -> 1.55 | K9: Y | L9: Y | O9: sampler mug | P9: 20
A10: 45130 | B10: HB Sailor | C10: 17 | D10: 0.74 | E10: 3.45 | F10: =Table1[[#This Row],[Money In]]-Table1[[#This Row],[Fee]] -> 16.26 | G10: =Table1[[#This Row],[Money In]]-Table1[[#This Row],[Postage]]-Table1[[#This Row],[Fee]] -> 12.81 | H10: Order details (ebay.co.uk) | I10: 4 | J10: =Table1[[#This Row],[Postage Quoted]]-Table1[[#This Row],[Postage]] -> 0.55 | K10: Y | L10: Y | O10: Sampler Jug | P10: 20
A11: 45130 | B11: Dory Cuddlies | C11: 14.5 | D11: 0.67 | E11: 3.45 | F11: =Table1[[#This Row],[Money In]]-Table1[[#This Row],[Fee]] -> 13.83 | G11: =Table1[[#This Row],[Money In]]-Table1[[#This Row],[Postage]]-Table1[[#This Row],[Fee]] -> 10.38 | H11: Order details (ebay.co.uk) | I11: 4 | J11: =Table1[[#This Row],[Postage Quoted]]-Table1[[#This Row],[Postage]] -> 0.55 | K11: Y | L11: Y | O11: hellabore | P11: 20
A12: 45130 | B12: HB Top | C12: 11.45 | D12: 0.59 | E12: 3.45 | F12: =Table1[[#This Row],[Money In]]-Table1[[#This Row],[Fee]] -> 10.86 | G12: =Table1[[#This Row],[Money In]]-Table1[[#This Row],[Postage]]-Table1[[#This Row],[Fee]] -> 7.41 | H12: Order details (ebay.co.uk) | I12: 3.95 | J12: =Table1[[#This Row],[Postage Quoted]]-Table1[[#This Row],[Postage]] -> 0.5 | K12: Y | L12: Y | O12: bicester dot | P12: 10
A13: 45130 | B13: Armani Exchange top | C13: 8.95 | D13: 0.53 | E13: 3.45 | F13: =Table1[[#This Row],[Money In]]-Table1[[#This Row],[Fee]] -> 8.42 | G13: =Table1[[#This Row],[Money In]]-Table1[[#This Row],[Postage]]-Table1[[#This Row],[Fee]] -> 4.97 | H13: Order details (ebay.co.uk) | I13: 3.95 | J13: =Table1[[#This Row],[Postage Quoted]]-Table1[[#This Row],[Postage]] -> 0.5 | K13: Y | L13: Y | O13: Rose Bee Porter | P13: 75
A14: 45131 | B14: MotoG | C14: 23.83 | D14: 0.91 | E14: 2.7 | F14: =Table1[[#This Row],[Money In]]-Table1[[#This Row],[Fee]] -> 22.92 | G14: =Table1[[#This Row],[Money In]]-Table1[[#This Row],[Postage]]-Table1[[#This Row],[Fee]] -> 20.22 | H14: Order details (ebay.co.uk) | I14: 3.95 | J14: =Table1[[#This Row],[Postage Quoted]]-Table1[[#This Row],[Postage]] -> 1.25 | K14: Y | L14: Y | O14: Rose Bee Mustard | P14: 12
A15: 45131 | B15: Watch | C15: 20.95 | D15: 0.84 | E15: 3.45 | F15: =Table1[[#This Row],[Money In]]-Table1[[#This Row],[Fee]] -> 20.11 | G15: =Table1[[#This Row],[Money In]]-Table1[[#This Row],[Postage]]-Table1[[#This Row],[Fee]] -> 16.66 | H15: Order details (ebay.co.uk) | I15: 3.95 | J15: =Table1[[#This Row],[Postage Quoted]]-Table1[[#This Row],[Postage]] -> 0.5 | K15: Y | L15: Y | O15: Rose Bee Ginger Beer | P15: 25
A16: 45131 | B16: PC | C16: 18.95 | D16: 2.73 | E16: 3.45 | F16: =Table1[[#This Row],[Money In]]-Table1[[#This Row],[Fee]] -> 16.22 | G16: =Table1[[#This Row],[Money In]]-Table1[[#This Row],[Postage]]-Table1[[#This Row],[Fee]] -> 12.77 | H16: Order details (ebay.co.uk) | I16: 3.95 | J16: =Table1[[#This Row],[Postage Quoted]]-Table1[[#This Row],[Postage]] -> 0.5 | K16: Y | L16: Y | O16: Rose Bee Ink | P16: 15
... A21: 45131 | B21: Grobags | C21: 7.97 | D21: 0.51 | E21: 3.45 | F21: =Table1[[#This Row],[Money In]]-Table1[[#This Row],[Fee]] -> 7.46 | G21: =Table1[[#This Row],[Money In]]-Table1[[#This Row],[Postage]]-Table1[[#This Row],[Fee]] -> 4.01 | H21: Order details (ebay.co.uk) | I21: 5 | J21: =Table1[[#This Row],[Postage Quoted]]-Table1[[#This Row],[Postage]] -> 1.55 | K21: Y | L21: Y | O21: Big Jug Words | P21: 300
A22: 45131 | B22: Grobag | C22: 7.65 | D22: 0.5 | E22: 3.45 | F22: =Table1[[#This Row],[Money In]]-Table1[[#This Row],[Fee]] -> 7.15 | G22: =Table1[[#This Row],[Money In]]-Table1[[#This Row],[Postage]]-Table1[[#This Row],[Fee]] -> 3.7 | H22: Order details (ebay.co.uk) | I22: 3.45 | J22: =Table1[[#This Row],[Postage Quoted]]-Table1[[#This Row],[Postage]] -> 0 | K22: Y | L22: Y
A23: 45131 | B23: google | C23: 5.15 | D23: 0.43 | E23: 3.45 | F23: =Table1[[#This Row],[Money In]]-Table1[[#This Row],[Fee]] -> 4.72 | G23: =Table1[[#This Row],[Money In]]-Table1[[#This Row],[Postage]]-Table1[[#This Row],[Fee]] -> 1.27 | H23: Order details (ebay.co.uk) | I23: 3.95 | J23: =Table1[[#This Row],[Postage Quoted]]-Table1[[#This Row],[Postage]] -> 0.5 | K23: Y | L23: Y
A24: 45133 | B24: R and B | C24: 33.95 | D24: 4.65 | E24: 4.15 | F24: =Table1[[#This Row],[Money In]]-Table1[[#This Row],[Fee]] -> 29.3 | G24: =Table1[[#This Row],[Money In]]-Table1[[#This Row],[Postage]]-Table1[[#This Row],[Fee]] -> 25.15 | H24: Order details (ebay.co.uk) | I24: 3.95 | J24: =Table1[[#This Row],[Postage Quoted]]-Table1[[#This Row],[Postage]] -> -0.2 | K24: Y | L24: Y
A25: 45134 | B25: dvd | C25: 17.95 | D25: 2.6 | E25: 3.45 | F25: =Table1[[#This Row],[Money In]]-Table1[[#This Row],[Fee]] -> 15.35 | G25: =Table1[[#This Row],[Money In]]-Table1[[#This Row],[Postage]]-Table1[[#This Row],[Fee]] -> 11.9 | H25: Order details (ebay.co.uk) | I25: 3.45 | J25: =Table1[[#This Row],[Postage Quoted]]-Table1[[#This Row],[Postage]] -> 0 | K25: Y | L25: Y
A26: 45134 | B26: Tablet | C26: 14.45 | D26: 2.15 | E26: 3.45 | F26: =Table1[[#This Row],[Money In]]-Table1[[#This Row],[Fee]] -> 12.3 | G26: =Table1[[#This Row],[Money In]]-Table1[[#This Row],[Postage]]-Table1[[#This Row],[Fee]] -> 8.85 | H26: Order details (ebay.co.uk) | I26: 3.95 | J26: =Table1[[#This Row],[Postage Quoted]]-Table1[[#This Row],[Postage]] -> 0.5 | K26: Y | L26: Y
A27: 45134 | B27: arsenal | C27: 11.95 | D27: 1.83 | E27: 2.7 | F27: =Table1[[#This Row],[Money In]]-Table1[[#This Row],[Fee]] -> 10.12 | G27: =Table1[[#This Row],[Money In]]-Table1[[#This Row],[Postage]]-Table1[[#This Row],[Fee]] -> 7.42 | H27: Order details (ebay.co.uk) | I27: 3.95 | J27: =Table1[[#This Row],[Postage Quoted]]-Table1[[#This Row],[Postage]] -> 1.25 | K27: Y | L27: Y | O27: Total | P27: =SUM(P2:P26) -> 1025
A28: 45134 | B28: bose wave | C28: 9.45 | D28: 1.51 | E28: 3.45 | F28: =Table1[[#This Row],[Money In]]-Table1[[#This Row],[Fee]] -> 7.94 | G28: =Table1[[#This Row],[Money In]]-Table1[[#This Row],[Postage]]-Table1[[#This Row],[Fee]] -> 4.49 | H28: Order details (ebay.co.uk) | I28: 3.95 | J28: =Table1[[#This Row],[Postage Quoted]]-Table1[[#This Row],[Postage]] -> 0.5 | K28: Y | L28: Y
A29: 45134 | B29: bberry | C29: 7.15 | D29: 1.22 | E29: 3.45 | F29: =Table1[[#This Row],[Money In]]-Table1[[#This Row],[Fee]] -> 5.93 | G29: =Table1[[#This Row],[Money In]]-Table1[[#This Row],[Postage]]-Table1[[#This Row],[Fee]] -> 2.48 | H29: Order details (ebay.co.uk) | I29: 3.95 | J29: =Table1[[#This Row],[Postage Quoted]]-Table1[[#This Row],[Postage]] -> 0.5 | K29: Y | L29: Y
A30: 45134 | B30: Grobag | C30: 4.99 | D30: 0.43 | E30: 3.45 | F30: =Table1[[#This Row],[Money In]]-Table1[[#This Row],[Fee]] -> 4.56 | G30: =Table1[[#This Row],[Money In]]-Table1[[#This Row],[Postage]]-Table1[[#This Row],[Fee]] -> 1.11 | H30: Order details (ebay.co.uk) | I30: 4 | J30: =Table1[[#This Row],[Postage Quoted]]-Table1[[#This Row],[Postage]] -> 0.55 | K30: Y | L30: Y
A31: 45134 | B31: Grobag | C31: 4.44 | D31: 0.41 | E31: 3.45 | F31: =Table1[[#This Row],[Money In]]-Table1[[#This Row],[Fee]] -> 4.03 | G31: =Table1[[#This Row],[Money In]]-Table1[[#This Row],[Postage]]-Table1[[#This Row],[Fee]] -> 0.58 | H31: Order details (ebay.co.uk) | I31: 3.45 | J31: =Table1[[#This Row],[Postage Quoted]]-Table1[[#This Row],[Postage]] -> 0 | K31: Y | L31: Y
A32: 45134 | B32: bberry | C32: 4.44 | D32: 0.87 | E32: 3.45 | F32: =Table1[[#This Row],[Money In]]-Table1[[#This Row],[Fee]] -> 3.57 | G32: =Table1[[#This Row],[Money In]]-Table1[[#This Row],[Postage]]-Table1[[#This Row],[Fee]] -> 0.12 | H32: Order details (ebay.co.uk) | I32: 3.45 | J32: =Table1[[#This Row],[Postage Quoted]]-Table1[[#This Row],[Postage]] -> 0 | K32: Y | L32: Y
A33: 45135 | B33: Surface | C33: 72 | D33: 9.52 | E33: 4.65 | F33: =Table1[[#This Row],[Money In]]-Table1[[#This Row],[Fee]] -> 62.48 | G33: =Table1[[#This Row],[Money In]]-Table1[[#This Row],[Postage]]-Table1[[#This Row],[Fee]] -> 57.83 | H33: Order details (ebay.co.uk) | I33: 5 | J33: =Table1[[#This Row],[Postage Quoted]]-Table1[[#This Row],[Postage]] -> 0.35 | K33: Y | L33: Y
A34: 45135 | B34: Bose headphones | C34: 25 | D34: 0.35 | E34: 2.7 | F34: =Table1[[#This Row],[Money In]]-Table1[[#This Row],[Fee]] -> 24.65 | G34: =Table1[[#This Row],[Money In]]-Table1[[#This Row],[Postage]]-Table1[[#This Row],[Fee]] -> 21.95 | H34: Order details (ebay.co.uk) | I34: 3 | J34: =Table1[[#This Row],[Postage Quoted]]-Table1[[#This Row],[Postage]] -> 0.3 | K34: Y | L34: Y
A35: 45135 | B35: fire 8 | C35: 25.45 | D35: 3.56 | E35: 3.45 | F35: =Table1[[#This Row],[Money In]]-Table1[[#This Row],[Fee]] -> 21.89 | G35: =Table1[[#This Row],[Money In]]-Table1[[#This Row],[Postage]]-Table1[[#This Row],[Fee]] -> 18.44 | H35: Order details (ebay.co.uk) | I35: 3.95 | J35: =Table1[[#This Row],[Postage Quoted]]-Table1[[#This Row],[Postage]] -> 0.5 | K35: Y | L35: Y
A36: 45135 | B36: R and B | C36: 23.95 | D36: 3.37 | E36: 3.45 | F36: =Table1[[#This Row],[Money In]]-Table1[[#This Row],[Fee]] -> 20.58 | G36: =Table1[[#This Row],[Money In]]-Table1[[#This Row],[Postage]]-Table1[[#This Row],[Fee]] -> 17.13 | H36: Order details (ebay.co.uk) | I36: 3.95 | J36: =Table1[[#This Row],[Postage Quoted]]-Table1[[#This Row],[Postage]] -> 0.5 | K36: Y | L36: Y
A37: 45135 | B37: fire 7 | C37: 15.43 | D37: 2.28 | E37: 3.45 | F37: =Table1[[#This Row],[Money In]]-Table1[[#This Row],[Fee]] -> 13.15 | G37: =Table1[[#This Row],[Money In]]-Table1[[#This Row],[Postage]]-Table1[[#This Row],[Fee]] -> 9.7 | H37: Order details (ebay.co.uk) | I37: 3.93 | J37: =Table1[[#This Row],[Postage Quoted]]-Table1[[#This Row],[Postage]] -> 0.48 | K37: Y | L37: Y
A38: 45135 | B38: Anker | C38: 9.45 | D38: 1.51 | E38: 2.7 | F38: =Table1[[#This Row],[Money In]]-Table1[[#This Row],[Fee]] -> 7.94 | G38: =Table1[[#This Row],[Money In]]-Table1[[#This Row],[Postage]]-Table1[[#This Row],[Fee]] -> 5.24 | H38: Order details (ebay.co.uk) | I38: 3.95 | J38: =Table1[[#This Row],[Postage Quoted]]-Table1[[#This Row],[Postage]] -> 1.25 | K38: Y | L38: Y
A39: 45135 | B39: Beats | C39: 8.2 | D39: 1.35 | E39: 2.7 | F39: =Table1[[#This Row],[Money In]]-Table1[[#This Row],[Fee]] -> 6.85 | G39: =Table1[[#This Row],[Money In]]-Table1[[#This Row],[Postage]]-Table1[[#This Row],[Fee]] -> 4.15 | H39: Order details (ebay.co.uk) | I39: 2.7 | J39: =Table1[[#This Row],[Postage Quoted]]-Table1[[#This Row],[Postage]] -> 0 | K39: Y | L39: Y
... A98: 45149 | B98: EB Fish head plate | C98: 16.95 | D98: 2.47 | E98: 3.45 | F98: =Table1[[#This Row],[Money In]]-Table1[[#This Row],[Fee]] -> 14.48 | G98: =Table1[[#This Row],[Money In]]-Table1[[#This Row],[Postage]]-Table1[[#This Row],[Fee]] -> 11.03 | H98: Order details (ebay.co.uk) | I98: 4.95 | J98: =Table1[[#This Row],[Postage Quoted]]-Table1[[#This Row],[Postage]] -> 1.5 | K98: Y | L98: Y
A99: 45150 | B99: Barbies | C99: 20.95 | D99: 2.98 | E99: 3.45 | F99: =Table1[[#This Row],[Money In]]-Table1[[#This Row],[Fee]] -> 17.97 | G99: =Table1[[#This Row],[Money In]]-Table1[[#This Row],[Postage]]-Table1[[#This Row],[Fee]] -> 14.52 | H99: Order details (ebay.co.uk) | I99: 3.95 | J99: =Table1[[#This Row],[Postage Quoted]]-Table1[[#This Row],[Postage]] -> 0.5 | K99: Y | L99: Y | O99: 236.29
A100: 45156 | B100: Oneplus6 | C100: 95 | D100: 3.95 | E100: 4.65 | F100: =Table1[[#This Row],[Money In]]-Table1[[#This Row],[Fee]] -> 91.05 | G100: =Table1[[#This Row],[Money In]]-Table1[[#This Row],[Postage]]-Table1[[#This Row],[Fee]] -> 86.4 | H100: Order details (ebay.co.uk) | I100: 5 | J100: =Table1[[#This Row],[Postage Quoted]]-Table1[[#This Row],[Postage]] -> 0.35 | K100: Y | L100: Y | O100: =5400-5127.33 -> 272.67
A101: 45157 | B101: NowTV stick | C101: 21.45 | D101: 1.12 | E101: 2.7 | F101: =Table1[[#This Row],[Money In]]-Table1[[#This Row],[Fee]] -> 20.33 | G101: =Table1[[#This Row],[Money In]]-Table1[[#This Row],[Postage]]-Table1[[#This Row],[Fee]] -> 17.63 | H101: Order details (ebay.co.uk) | I101: 3.95 | J101: =Table1[[#This Row],[Postage Quoted]]-Table1[[#This Row],[Postage]] -> 1.25 | K101: Y | L101: Y
A102: 45158 | B102: NowTV Box | C102: 12.2 | D102: 0.77 | E102: 3.45 | F102: =Table1[[#This Row],[Money In]]-Table1[[#This Row],[Fee]] -> 11.43 | G102: =Table1[[#This Row],[Money In]]-Table1[[#This Row],[Postage]]-Table1[[#This Row],[Fee]] -> 7.98 | H102: Order details (ebay.co.uk) | I102: 3.95 | J102: =Table1[[#This Row],[Postage Quoted]]-Table1[[#This Row],[Postage]] -> 0.5 | K102: Y | L102: Y
A103: 45159 | B103: Fitbit | C103: 37.95 | D103: 1.76 | E103: 2.7 | F103: =Table1[[#This Row],[Money In]]-Table1[[#This Row],[Fee]] -> 36.19 | G103: =Table1[[#This Row],[Money In]]-Table1[[#This Row],[Postage]]-Table1[[#This Row],[Fee]] -> 33.49 | H103: Order details (ebay.co.uk) | I103: 3.95 | J103: =Table1[[#This Row],[Postage Quoted]]-Table1[[#This Row],[Postage]] -> 1.25 | K103: Y | L103: Y
A104: 45159 | B104: EB Jug | C104: 24.94 | D104: 1.26 | E104: 3.45 | F104: =Table1[[#This Row],[Money In]]-Table1[[#This Row],[Fee]] -> 23.68 | G104: =Table1[[#This Row],[Money In]]-Table1[[#This Row],[Postage]]-Table1[[#This Row],[Fee]] -> 20.23 | H104: Order details (ebay.co.uk) | I104: 3.95 | J104: =Table1[[#This Row],[Postage Quoted]]-Table1[[#This Row],[Postage]] -> 0.5 | K104: Y | L104: Y
A105: 45159 | B105: Fire 8 HD yellow | C105: 14.45 | D105: 0.85 | E105: 2.7 | F105: =Table1[[#This Row],[Money In]]-Table1[[#This Row],[Fee]] -> 13.6 | G105: =Table1[[#This Row],[Money In]]-Table1[[#This Row],[Postage]]-Table1[[#This Row],[Fee]] -> 10.9 | H105: Order details (ebay.co.uk) | I105: 3.95 | J105: =Table1[[#This Row],[Postage Quoted]]-Table1[[#This Row],[Postage]] -> 1.25 | K105: Y | L105: Y
B106: Fire Stick 2 | C106: 21 | D106: 2.99 | E106: 2.7 | F106: =Table1[[#This Row],[Money In]]-Table1[[#This Row],[Fee]] -> 18.01 | G106: =Table1[[#This Row],[Money In]]-Table1[[#This Row],[Postage]]-Table1[[#This Row],[Fee]] -> 15.31 | H106: Order details (ebay.co.uk) | I106: 3.95 | J106: =Table1[[#This Row],[Postage Quoted]]-Table1[[#This Row],[Postage]] -> 1.25 | K106: y
B107: Fire Stick 1 | C107: 11.5 | D107: 1.77 | E107: 2.7 | F107: =Table1[[#This Row],[Money In]]-Table1[[#This Row],[Fee]] -> 9.73 | G107: =C107-E107-Table1[[#This Row],[Fee]] -> 7.03 | H107: Order details (ebay.co.uk) | I107: 3 | J107: =Table1[[#This Row],[Postage Quoted]]-Table1[[#This Row],[Postage]] -> 0.3 | K107: Y | L107: Y
B108: Fire Stick 1 | C108: 8.5 | D108: 1.39 | E108: 2.7 | F108: =Table1[[#This Row],[Money In]]-Table1[[#This Row],[Fee]] -> 7.11 | G108: =C108-E108-Table1[[#This Row],[Fee]] -> 4.41 | H108: Order details (ebay.co.uk) | I108: 3 | J108: =Table1[[#This Row],[Postage Quoted]]-Table1[[#This Row],[Postage]] -> 0.3 | K108: Y | L108: Y
B109: Plug | C109: 4.94 | D109: 0.93 | E109: 3.45 | F109: =Table1[[#This Row],[Money In]]-Table1[[#This Row],[Fee]] -> 4.01 | G109: =Table1[[#This Row],[Money In]]-Table1[[#This Row],[Postage]]-Table1[[#This Row],[Fee]] -> 0.56 | H109: Order details (ebay.co.uk) | I109: 3.95 | J109: =Table1[[#This Row],[Postage Quoted]]-Table1[[#This Row],[Postage]] -> 0.5 | K109: Y | L109: Y
F110: =Table1[[#This Row],[Money In]]-Table1[[#This Row],[Fee]] -> 0 | G110: =C110-E110-Table1[[#This Row],[Fee]] -> 0 | J110: =Table1[[#This Row],[Postage Quoted]]-Table1[[#This Row],[Postage]] -> 0
F111: =Table1[[#This Row],[Money In]]-Table1[[#This Row],[Fee]] -> 0 | G111: =C111-E111-Table1[[#This Row],[Fee]] -> 0 | J111: =Table1[[#This Row],[Postage Quoted]]-Table1[[#This Row],[Postage]] -> 0
F112: =Table1[[#This Row],[Money In]]-Table1[[#This Row],[Fee]] -> 0 | G112: =C112-E112-Table1[[#This Row],[Fee]] -> 0 | J112: =Table1[[#This Row],[Postage Quoted]]-Table1[[#This Row],[Postage]] -> 0
F113: =Table1[[#This Row],[Money In]]-Table1[[#This Row],[Fee]] -> 0 | G113: =C113-E113-Table1[[#This Row],[Fee]] -> 0 | J113: =Table1[[#This Row],[Postage Quoted]]-Table1[[#This Row],[Postage]] -> 0
F114: =Table1[[#This Row],[Money In]]-Table1[[#This Row],[Fee]] -> 0 | G114: =C114-E114-Table1[[#This Row],[Fee]] -> 0 | J114: =Table1[[#This Row],[Postage Quoted]]-Table1[[#This Row],[Postage]] -> 0
F115: =Table1[[#This Row],[Money In]]-Table1[[#This Row],[Fee]] -> 0 | G115: =C115-E115-Table1[[#This Row],[Fee]] -> 0 | J115: =Table1[[#This Row],[Postage Quoted]]-Table1[[#This Row],[Postage]] -> 0
F116: =Table1[[#This Row],[Money In]]-Table1[[#This Row],[Fee]] -> 0 | G116: =C116-E116-Table1[[#This Row],[Fee]] -> 0 | J116: =Table1[[#This Row],[Postage Quoted]]-Table1[[#This Row],[Postage]] -> 0
F117: =Table1[[#This Row],[Money In]]-Table1[[#This Row],[Fee]] -> 0 | G117: =C117-E117-Table1[[#This Row],[Fee]] -> 0 | J117: =Table1[[#This Row],[Postage Quoted]]-Table1[[#This Row],[Postage]] -> 0
F118: =Table1[[#This Row],[Money In]]-Table1[[#This Row],[Fee]] -> 0 | G118: =C118-E118-Table1[[#This Row],[Fee]] -> 0 | J118: =Table1[[#This Row],[Postage Quoted]]-Table1[[#This Row],[Postage]] -> 0
F119: =Table1[[#This Row],[Money In]]-Table1[[#This Row],[Fee]] -> 0 | G119: =C119-E119-Table1[[#This Row],[Fee]] -> 0 | J119: =Table1[[#This Row],[Postage Quoted]]-Table1[[#This Row],[Postage]] -> 0
F120: =Table1[[#This Row],[Money In]]-Table1[[#This Row],[Fee]] -> 0 | G120: =C120-E120-Table1[[#This Row],[Fee]] -> 0 | J120: =Table1[[#This Row],[Postage Quoted]]-Table1[[#This Row],[Postage]] -> 0
F121: =Table1[[#This Row],[Money In]]-Table1[[#This Row],[Fee]] -> 0 | G121: =C121-E121-Table1[[#This Row],[Fee]] -> 0 | J121: =Table1[[#This Row],[Postage Quoted]]-Table1[[#This Row],[Postage]] -> 0
F122: =Table1[[#This Row],[Money In]]-Table1[[#This Row],[Fee]] -> 0 | G122: =C122-E122-Table1[[#This Row],[Fee]] -> 0 | J122: =Table1[[#This Row],[Postage Quoted]]-Table1[[#This Row],[Postage]] -> 0
F123: =Table1[[#This Row],[Money In]]-Table1[[#This Row],[Fee]] -> 0 | G123: =Table1[[#This Row],[Money In]]-Table1[[#This Row],[Postage]]-Table1[[#This Row],[Fee]] -> 0 | J123: =Table1[[#This Row],[Postage Quoted]]-Table1[[#This Row],[Postage]] -> 0
B125: TOTAL | C125: =SUM(C2:C123) -> 2343.19 | D125: =SUM(D2:D123) -> 197.5 | E125: =SUM(E2:E123) -> 419.31 | F125: =SUM(F2:F123) -> 2145.69 | G125: =SUM(G2:G123) -> 1726.38 | I125: =SUM(I2:I123) -> 497.22 | J125: =SUM(J2:J123) -> 77.91 | K125: =SUMIF(K2:K123,"N",E2:E123) -> 0 | L125: =SUMIF(L2:L123,"N",F2:F123) -> 0
B127: Date | E127: Money In
B128: 45132 | E128: 76
B129: 45135 | E129: 30
B130: 45140 | E130: 91.18
B131: ? | E131: 16.92
B132: 45144 | E132: 67.04
B133: 45147 | E133: 96.18
H134: Current Hyper Jar Balance | I134: 35 | J134: Paid
H135: Door | I135: 56 | J135: Y
B136: To be paid | E136: =SUM(E128:E135)-E125 -> -41.99 | H136: Wires | I136: 66 | J136: Y
H137: Bits | I137: 10 | J137: Y
H138: Door | I138: 350 | J138: Y
B139: postage paid up to the 2nd august | H139: Electrics | I139: 189 | J139: Y
H140: Materials | I140: 521.53 | J140: Y
H141: David stuff | I141: 28 | J141: Y
H142: David stuff | I142: 42 | J142: Y
H143: Flooring | I143: 110 | J143: Y
H144: Glue | I144: 10 | J144: y
H145: Electrics | I145: 189 | J145: Y
H146: Paint | I146: 35 | J146: N
H147: Slabs | I147: 70 | J147: Y
H148: Total To be Paid | I148: =SUMIF(J135:J147,"N",I135:I147) -> 35
H149: Balance after | I149: =I134-I148 -> 0

Sheet emergancy month
C2: Money | I2: Name | J2: Value | K2: Paid? | L2: Who
C3: Paid | D3: 4700 | I3: Mortgage | J3: -1268 | K3: no
C4: Taken Already | D4: =SUMIF(K3:K29,"Yes*",J3:J29) -> 0 | I4: food petrol | J4: -850 | K4: no | L4: f
C5: Balance | D5: 5171 | I5: council tax | J5: -225 | K5: no
C6: To Be Taken | D6: =SUMIF(K3:K48,"No",J3:J48) -> -2890.7 | I6: Gas/Electric | J6: -173 | K6: no
C7: Total | D7: =D6+D5 -> 2280.3 | I7: help to buy | J7: -127 | K7: no
C8: Francesca | D8: =SUMIF(L3:L33,"f",J3:J33) -> -910 | I8: HouseInsurance - Tesco | J8: -35 | K8: no
I9: car insurance lv | J9: -33 | K9: no
I10: gym | J10: -33 | K10: no | L10: f
I11: water | J11: -29 | K11: no
F12: 2890 | I12: LifeInsurance/aviva | J12: -28.4 | K12: no
F13: £9000 needed for e fund | I13: Tesco Mobile | J13: -27 | K13: no | L13: f
I14: internet | J14: -17 | K14: no
I15: TvLicence | J15: -13.2 | K15: no
I16: water | J16: -13 | K16: no
I17: boier | J17: -11.7 | K17: no
I18: greenbelt | J18: -7.4 | K18: no
K19: no | L19: f
K20: no
K21: no
K22: no
K23: no
K24: no
K25: no | L25: f
K26: no
K27: no
K28: no | L28: f
K29: no
K30: no | L30: f
K31: no
K32: no
K33: no
K34: no
K35: no
K36: no

Sheet Sheet3

Sheet min new
A1: Money | D1: Savings Account | G1: Name | H1: Value | I1: Paid? | J1: Who | K1: Category
A2: Paid | B2: 5188.49 | D2: Rainy Day 🌧️ | E2: 100 | G2: Mortgage | H2: -1269 | I2: no | K2: House
A3: Taken Already | B3: =SUMIF(I2:I47,"Yes*",H2:H47) -> 0 | D3: Francesca Birthday | E3: 300 | G3: car payment | I3: no | J3: s | K3: Savings
A4: Balance | B4: 5172 | D4: Dental 🪥 | E4: 89 | G4: LifeInsurance/aviva | H4: -37 | I4: no | K4: Insurance
A5: To Be Taken | B5: =SUMIF(I2:I47,"No",H2:H47) -> -4300.49 | D5: Vet Fund 😺 | E5: 550 | G5: HouseInsurance - Tesco | H5: -39 | I5: no | K5: Insurance
A6: Total | B6: =B5+B4 -> 871.51 | D6: Willow Dinner | E6: 215 | G6: TvLicence | H6: -15 | I6: no | K6: HouseBill
A7: Francesca pt 1 | B7: =SUMIF(J2:J47,"f1",H2:H47) -> -1780 | D7: alison | G7: Gas/Electric | H7: -155 | I7: no | K7: HouseBill
A8: Francesca pt 2 | B8: =SUMIF(J2:J47,"f2",H2:H47) -> -62 | D8: willow bday | E8: 150 | G8: pet insur | H8: -50 | I8: no | J8: s | K8: Insurance
A9: Matt | B9: =SUMIF(J2:J47,"",H2:H47) -> -2353.49 | D9: my face | E9: 220 | G9: spotoify | H9: -20 | I9: no | K9: Subscription
A10: Savings | B10: =SUMIF(J2:J47,"s",H2:H47) -> -105 | D10: Train | E10: 63 | G10: rumpus food | H10: -55 | I10: no | J10: s | K10: Savings
D11: Saving Total | E11: =SUM(E2:E10) -> 1687 | I11: no | K11: Subscription
D12: Emergency Fund | G12: amazon | H12: -8.99 | I12: no | K12: Subscription
A13: Emergency Target | B13: 12000 | D13: francesca Isa | E13: 5145.97 | G13: council tax | H13: -239 | I13: no | K13: HouseBill
A14: Emergency Fund | B14: =E12+E13 -> 5145.97 | D14: FRANNYS MONEY | E14: 1455 | G14: water | H14: -13 | I14: no | K14: HouseBill
A15: Emergency Left | B15: =B13-B14 -> 6854.03 | G15: window clean | I15: no | K15: HouseBill
A16: Percentage | B16: =B14/B13 -> 0.42883083 | D16: nor holiday fund in matt | E16: 595 | G16: water | H16: -30 | I16: no | K16: HouseBill
G17: hp | H17: -1.5 | I17: no | K17: Subscription
A18: Mortgage | D18: holiday | G18: DISHWASHER | H18: -5 | I18: no | K18: Insurance
A19: Main | B19: 153458.32 | G19: money for month | H19: -800 | I19: no | J19: f1 | K19: Francesca
A20: Extra | B20: 81199.44 | G20: tesco mobiles | H20: -29 | I20: no | J20: f2 | K20: Mobile
A21: Total Due | B21: =SUM(B19:B20) -> 234657.76 | G21: credit card | I21: no | J21: f1 | K21: Francesca
A22: H2B paybak | B22: =B23*0.2 -> 90000 | D22: JL092865B | G22: food petrol | H22: -900 | I22: no | J22: f1 | K22: Food
A23: Sold Price | B23: 450000 | G23: phone | H23: -11 | I23: no | K23: Mobile
A24: Equity | B24: =B23-SUM(B21:B22) -> 125342.24 | G24: greenbelt | H24: -14 | I24: no | K24: HouseBill
G25: next | I25: no | J25: s | K25: Savings
G26: car insurance lv | H26: -35 | I26: no | K26: Insurance
G27: child benefit shit | H27: -80 | I27: no | J27: f1 | K27: Francesca
G28: zoom | H28: -18 | I28: no | K28: HouseBill
G29: gym | H29: -33 | I29: no | J29: f2 | K29: Francesca
A30: NW | G30: boiler | H30: -12 | I30: no | K30: HouseBill
A31: 1104841580 | G31: service | H31: -33 | I31: no | K31: Savings
G32: matt | H32: -100 | I32: no | K32: Spending
G33: pocket money | H33: -20 | I33: no | K33: Medical
G34: help to by | H34: -138 | I34: no | K34: House
G35: lunch | H35: -20 | I35: no | K35: Savings
I36: no | K36: Francesca
G37: dental | H37: -20 | I37: no | K37: Francesca
G38: week fund | H38: -100 | I38: no
I39: no
I40: no
I41: no
I42: no
I43: no
I44: no
I45: no
I46: no
I47: no

Sheet Goals
A1: plan
A2: 1 | B2: put 500.00 in to emergancy fund
B3: put any cash from fec consultancy large amounts) into emergancy fund
A4: 2 | B4: reach 10000
A5: 3 | B5: put money into money box pension
A6: 4 | B6: may 2026 evalutate paying work pension

Sheet Sheet5
A1: willows birthday | C1: march
A2: my birthdat=y 40th | C2: april
A3: annerverary | C3: april
A4: car service | C4: auguat
A5: christmas | C5: dec
G18: 4791
G19: 4830
G20: 4714
G21: 4665
G22: 4706
G23: 4868
G24: 4850
G25: 5196
G26: 5038
G27: 4911
G28: 4954
G29: 4982

Sheet dec21
C2: Money | F2: Savings Account | I2: Name | J2: Value | K2: Paid? | L2: Who
C3: Paid | D3: 4342.71 | F3: Savings Account | G3: 10 | I3: Mortgage | J3: -852.98 | K3: yes
C4: Taken Already | D4: =SUMIF(K3:K29,"Yes*",J3:J29) -> -3728.71 | F4: matt christmas | G4: 85 | I4: Car | J4: -244.8 | K4: yes | L4: f
C5: Balance | D5: 37.7 | F5: train | I5: LifeInsurance/aviva | J5: -25.56 | K5: yes
C6: To Be Taken | D6: =SUMIF(K3:K48,"No",J3:J48) -> 0 | F6: christmas food | I6: HouseInsurance - Tesco | J6: -24.82 | K6: yes
C7: Total | D7: =D6+D5 -> 37.7 | F7: rumpus vet fund | G7: 81 | I7: TvLicence | J7: -13.2 | K7: yes
C8: Francesca | D8: =SUMIF(L3:L33,"f",J3:J33) -> -1740.3 | I8: Gas/Electric | J8: -127 | K8: yes
I9: pet insur | J9: -27 | K9: yes
F10: francesca cashback | I10: spotoify | J10: -16.99 | K10: yes
F11: Saving Total | G11: =SUM(G3:G10) -> 176 | I11: loan | J11: -395 | K11: yes
I12: netflix | J12: -13.99 | K12: yes
F13: Botox | G13: 290 | I13: plus net | J13: -28.22 | K13: yes
I14: council tax | J14: -198 | K14: yes
C15: Mortgage | I15: water | J15: -16 | K15: yes
C16: Main | D16: 167660.11 | I16: GARDEN | J16: -6.25 | K16: yes
C17: Extra | D17: 87559.93 | I17: water | J17: -35 | K17: yes
C18: Total Due | D18: =SUM(D16:D17) -> 255220.04 | I18: hp | J18: -2 | K18: yes
C19: H2B paybak | D19: =D20*0.2 -> 84000 | F19: loan is 2600.00 | G19: 1082 | I19: HSBC CC | J19: -685 | K19: yes | L19: f
C20: Sold Price | D20: 420000 | F20: Paid 1 | G20: 160 | I20: swimming | J20: -24 | K20: yes
C21: Equity | D21: =SUM(D18:D19)-D20 -> -80779.96 | F21: Paid 1 | I21: Tesco Mobile | J21: -12.5 | K21: yes | L21: f
F22: Paid 1 | I22: train | K22: no
F23: Paid 1 | I23: food petrol | J23: -750 | K23: yes | L23: f
G24: =SUM(G20:G23)-G19 -> -922 | I24: christmas | J24: -120 | K24: yes
C25: christmas | I25: greenbelt | J25: -7.4 | K25: yes
C26: mum and dad | D26: 60 | I26: next | J26: -18 | K26: yes | L26: f
C27: nana and eric | I27: car insurance lv | J27: -35 | K27: yes
C28: ben and lou | K28: no
C29: food | I29: cash bak savings | J29: -50 | K29: yes
C30: beth | I30: gym | J30: -30 | K30: yes | L30: f
C31: willows friend | I31: matts credit | J31: -293 | K31: yes
C32: teacher | I32: tyres | J32: -200 | K32: yes
D33: =SUM(D26:D32) -> 60 | I33: dentist | J33: -50 | K33: yes
I34: boiler | J34: -60 | K34: yes

Sheet Nov21
C2: Money | F2: Savings Account | I2: Name | J2: Value | K2: Paid? | L2: Who
C3: Paid | D3: 3878.72 | F3: Savings Account | G3: 10 | I3: Mortgage | J3: -852.98 | K3: yes
C4: Taken Already | D4: =SUMIF(K3:K29,"Yes*",J3:J29) -> -3772.49 | F4: christmas | G4: 60 | I4: Car | J4: -244.8 | K4: yes | L4: f
C5: Balance | D5: 69.93 | F5: train | I5: LifeInsurance/aviva | J5: -25.56 | K5: yes
C6: To Be Taken | D6: =SUMIF(K3:K33,"No",J3:J33) -> -60 | F6: francesca christmas | I6: HouseInsurance - Tesco | J6: -24.82 | K6: yes
C7: Total | D7: =D6+D5 -> 9.93 | F7: rumpus vet fund | G7: 54 | I7: TvLicence | J7: -13.2 | K7: yes
C8: Francesca | D8: =SUMIF(L3:L33,"f",J3:J33) -> -1847.3 | F8: 60 in teapot | I8: Gas/Electric | J8: -127 | K8: yes
I9: pet insur | J9: -27 | K9: yes
F10: francesca cashback | I10: spotoify | J10: -16.99 | K10: yes
F11: Saving Total | G11: =SUM(G3:G10) -> 124 | I11: loan | J11: -395 | K11: yes
I12: netflix | J12: -13.99 | K12: yes
F13: Botox | G13: 290 | I13: plus net | J13: -25 | K13: yes
I14: council tax | J14: -198 | K14: yes
C15: Mortgage | I15: water | J15: -16 | K15: yes
C16: Main | D16: 167660.11 | I16: GARDEN | J16: -6.25 | K16: yes
C17: Extra | D17: 87559.93 | I17: water | J17: -35 | K17: yes
C18: Total Due | D18: =SUM(D16:D17) -> 255220.04 | I18: hp | J18: -2 | K18: yes
C19: H2B paybak | D19: =D20*0.2 -> 84000 | F19: loan is 2600.00 | G19: 1082 | I19: HSBC CC | J19: -655 | K19: yes | L19: f
C20: Sold Price | D20: 420000 | F20: Paid 1 | G20: 160 | I20: swimming | J20: -24 | K20: yes
C21: Equity | D21: =SUM(D18:D19)-D20 -> -80779.96 | F21: Paid 1 | I21: Tesco Mobile | J21: -12.5 | K21: yes | L21: f
F22: Paid 1 | I22: train | K22: no
F23: Paid 1 | I23: food petrol | J23: -900 | K23: yes | L23: f
G24: =SUM(G20:G23)-G19 -> -922 | I24: christmas | J24: -90 | K24: yes
C25: christmas | I25: greenbelt | J25: -7.4 | K25: yes
C26: mum and dad | D26: 60 | I26: next | J26: -5 | K26: yes | L26: f
C27: nana and eric | I27: car insurance lv | J27: -35 | K27: yes
C28: ben and lou | I28: boiler | J28: -60 | K28: no
C29: food | I29: Birthday | J29: -20 | K29: yes
C30: beth | I30: gym | J30: -30 | K30: yes | L30: f
C31: willows friend | I31: matts credit | J31: -7 | K31: yes
C32: teacher | K32: no
D33: =SUM(D26:D32) -> 60 | K33: no

Sheet Oct21
C2: Money | F2: Savings Account | I2: Name | J2: Value | K2: Paid? | L2: Who
C3: Paid | D3: 4110.71 | F3: Savings Account | G3: 10 | I3: Mortgage | J3: -852.98 | K3: yes
C4: Taken Already | D4: =SUMIF(K3:K29,"Yes*",J3:J29) -> -3675.49 | F4: christmas | G4: 144 | I4: Car | J4: -244.8 | K4: yes | L4: f
C5: Balance | D5: 82.28 | F5: train | I5: LifeInsurance/aviva | J5: -25.56 | K5: yes
C6: To Be Taken | D6: =SUMIF(K3:K33,"No",J3:J33) -> -74 | F6: francesca christmas | I6: HouseInsurance - Tesco | J6: -24.82 | K6: yes
C7: Total | D7: =D6+D5 -> 8.28 | F7: rumpus vet do not touch | I7: TvLicence | J7: -13.2 | K7: yes
C8: Francesca | D8: =SUMIF(L3:L33,"f",J3:J33) -> -1913.3 | I8: Gas/Electric | J8: -85 | K8: yes
I9: pet insur | J9: -27 | K9: no
F10: francesca cashback | G10: 15 | I10: spotoify | J10: -16.99 | K10: yes
F11: Saving Total | G11: =SUM(G3:G10) -> 169 | I11: loan | J11: -395 | K11: yes
I12: netflix | J12: -13.99 | K12: yes
F13: Botox | G13: 290 | I13: plus net | J13: -25 | K13: yes
I14: council tax | J14: -198 | K14: yes
C15: Mortgage | I15: water | J15: -16 | K15: YES
C16: Main | D16: 167660.11 | I16: GARDEN | J16: -6.25 | K16: yes
C17: Extra | D17: 87559.93 | I17: water | J17: -35 | K17: yes
C18: Total Due | D18: =SUM(D16:D17) -> 255220.04 | I18: hp | J18: -2 | K18: yes
C19: H2B paybak | D19: =D20*0.2 -> 84000 | F19: loan is 2600.00 | G19: 1082 | I19: HSBC CC | J19: -615 | K19: yes | L19: f
C20: Sold Price | D20: 420000 | F20: Paid 1 | G20: 160 | I20: cat | J20: -50 | K20: yes | L20: f
C21: Equity | D21: =SUM(D18:D19)-D20 -> -80779.96 | F21: Paid 1 | I21: Tesco Mobile | J21: -12.5 | K21: yes | L21: f
F22: Paid 1 | I22: train | J22: -47 | K22: no
F23: Paid 1 | I23: food petrol | J23: -750 | K23: yes | L23: f
G24: =SUM(G20:G23)-G19 -> -922 | I24: willow swim | J24: -24 | K24: yes | L24: f
C25: christmas | I25: greenbelt | J25: -7.4 | K25: yes
C26: mum and dad | D26: 60 | I26: next | J26: -32 | K26: yes | L26: f
C27: nana and eric | D27: 30 | I27: car insurance lv | J27: -35 | K27: yes
C28: ben and lou | D28: 30 | I28: car tax | J28: -155 | K28: yes | L28: f
C29: willow | I29: Birthday | J29: -40 | K29: yes
C30: beth | D30: 15 | I30: gym | J30: -30 | K30: yes | L30: f
C31: willows friend | D31: 10 | K31: no
C32: teacher | I32: christmas | J32: -25 | K32: yes
D33: =SUM(D26:D32) -> 145 | I33: money for next month pay | J33: -246 | K33: yes

Sheet Sept21
C2: Money | F2: Savings Account | I2: Name | J2: Value | K2: Paid? | L2: Who
C3: Paid | D3: 3864.31 | F3: Savings Account | G3: 19 | I3: Mortgage | J3: -852.98 | K3: no
C4: Taken Already | D4: =SUMIF(K3:K29,"Yes*",J3:J29) -> 0 | I4: Car | J4: -244.8 | K4: no | L4: f
C5: Balance | D5: 63.84 | F5: train | G5: 8 | I5: LifeInsurance/aviva | J5: -25.56 | K5: no
C6: To Be Taken | D6: =SUMIF(K3:K33,"No",J3:J33) -> -5547.49 | F6: francescas cash back | G6: 50 | I6: HouseInsurance - Tesco | J6: -24.82 | K6: no
C7: Total | D7: =D6+D5 -> -5483.65 | F7: christmas | G7: 350 | I7: TvLicence | J7: -13.2 | K7: no
C8: Francesca | D8: =SUMIF(L3:L33,"f",J3:J33) -> -2104.3 | F8: Saving Total | G8: =SUM(G3:G7) -> 427 | I8: Gas/Electric | J8: -85 | K8: no
I9: pet insur | J9: -27 | K9: no
I10: spotoify | J10: -16.99 | K10: no
I11: loan | J11: -300 | K11: no
I12: netflix | J12: -13.99 | K12: no
I13: plus net | J13: -25 | K13: no
I14: council tax | J14: -198 | K14: no
C15: Mortgage | I15: water | J15: -16 | K15: no
C16: Main | D16: 167660.11 | I16: GARDEN | J16: -6.25 | K16: no
C17: Extra | D17: 87559.93 | I17: water | J17: -28 | K17: no
C18: Total Due | D18: =SUM(D16:D17) -> 255220.04 | I18: hp | J18: -2 | K18: no
C19: H2B paybak | D19: =D20*0.2 -> 84000 | F19: loan is 2600.00 | G19: 1082 | I19: HSBC CC | J19: -700 | K19: no | L19: f
C20: Sold Price | D20: 420000 | F20: Paid 1 | G20: 160 | I20: tesco bank patio | J20: -25 | K20: no | L20: f
C21: Equity | D21: =SUM(D18:D19)-D20 -> -80779.96 | F21: Paid 1 | I21: Tesco Mobile | J21: -12.5 | K21: no | L21: f
F22: Paid 1 | I22: train | J22: -37 | K22: no
F23: Paid 1 | I23: food petrol | J23: -750 | K23: no | L23: f
G24: =SUM(G20:G23)-G19 -> -922 | I24: Service | J24: -282 | K24: no | L24: f
I25: greenbelt | J25: -7.4 | K25: no
I26: next | J26: -60 | K26: no | L26: f
I27: car insurance lv | J27: -35 | K27: no
I28: Anniversary | J28: -20 | K28: no
I29: willow swim | J29: -24 | K29: no
I30: gym | J30: -30 | K30: no | L30: f
I31: window | J31: -10 | K31: no
I32: willow bedroom | J32: -50 | K32: no
I33: tesco | J33: -1625 | K33: no
K34: no
K35: no

Sheet Aug21
C2: Money | F2: Savings Account | I2: Name | J2: Value | K2: Paid? | L2: Who
C3: Paid | D3: 3882.31 | F3: Savings Account | G3: 40 | I3: Mortgage | J3: -852.98 | K3: yes
C4: Taken Already | D4: =SUMIF(K3:K29,"Yes*",J3:J29) -> -3784.59 | F4: car | I4: Car | J4: -244.8 | K4: yes | L4: f
C5: Balance | D5: 34.8 | F5: train | G5: 67 | I5: LifeInsurance/aviva | J5: -25.56 | K5: yes
C6: To Be Taken | D6: =SUMIF(K3:K33,"No",J3:J33) -> -34.4 | F6: tax money | I6: HouseInsurance - Tesco | J6: -24.82 | K6: yes
C7: Total | D7: =D6+D5 -> 0.4 | F7: Saving Total | G7: =SUM(G3:G6) -> 107 | I7: TvLicence | J7: -13.2 | K7: yes
C8: Francesca | D8: =SUMIF(L3:L33,"f",J3:J33) -> -2157.3 | I8: Gas/Electric | J8: -85 | K8: yes
I9: pet insur | J9: -27 | K9: no
I10: spotoify | J10: -16.99 | K10: yes
I11: loan | J11: -300 | K11: yes
I12: netflix | J12: -13.99 | K12: yes
I13: plus net | J13: -0.5 | K13: yes
I14: council tax | J14: -198 | K14: yes
C15: Mortgage | I15: water | J15: -16 | K15: yes
C16: Main | D16: 167660.11 | I16: GARDEN | J16: -6.25 | K16: yes
C17: Extra | D17: 87559.93 | I17: water | J17: -28 | K17: yes
C18: Total Due | D18: =SUM(D16:D17) -> 255220.04 | I18: hp | J18: -2 | K18: yes
C19: H2B paybak | D19: =D20*0.2 -> 84000 | F19: loan is 2600.00 | G19: 2600 | I19: HSBC CC | J19: -610 | K19: yes | L19: f
C20: Sold Price | D20: 420000 | F20: Paid 1 | G20: 580 | I20: tesco bank patio | J20: -300 | K20: yes | L20: f
C21: Equity | D21: =SUM(D18:D19)-D20 -> -80779.96 | F21: Paid 1 | G21: 400 | I21: Tesco Mobile | J21: -12.5 | K21: yes | L21: f
F22: Paid 1 | G22: 500 | I22: train | J22: -39 | K22: yes
F23: Paid 1 | I23: food petrol | J23: -900 | K23: yes | L23: f
G24: =SUM(G20:G23)-G19 -> -1120 | I24: nationaltrust | K24: no | L24: f
I25: greenbelt | J25: -7.4 | K25: no
I26: next | J26: -60 | K26: yes | L26: f
I27: car insurance lv | J27: -35 | K27: yes
I28: disney | K28: no
I29: savings | K29: no
I30: gym | J30: -30 | K30: yes | L30: f
I31: going out | J31: -75 | K31: yes
I32: tom | K32: no
K33: no

Sheet july21
C2: Money | F2: Savings Account | I2: Name | J2: Value | K2: Paid? | L2: Who
C3: Paid | D3: 3882.31 | F3: Savings Account | G3: 45 | I3: Mortgage | J3: -852.98 | K3: yes
C4: Taken Already | D4: =SUMIF(K3:K29,"Yes*",J3:J29) -> -3651.07 | F4: cash back | I4: Car | J4: -244.8 | K4: yes | L4: f
C5: Balance | D5: 77.4 | F5: botox | I5: LifeInsurance/aviva | J5: -25.56 | K5: yes
C6: To Be Taken | D6: =SUMIF(K3:K40,"No",J3:J40) -> 0 | F6: tax money | I6: HouseInsurance - Tesco | J6: -24.82 | K6: yes
C7: Total | D7: =D6+D5 -> 77.4 | F7: Saving Total | G7: =SUM(G3:G6) -> 45 | I7: TvLicence | J7: -13.2 | K7: yes
I8: Gas/Electric | J8: -85 | K8: yes
I9: pet insur | J9: -27 | K9: yes
C10: Francesca | D10: =SUMIF(L3:L40,"f",J3:J40) -> -1960.3 | I10: spotoify | J10: -16.99 | K10: yes
G11: =G3-250 -> -205 | I11: loan | J11: -300 | K11: yes
I12: netflix | J12: -13.99 | K12: yes
I13: plus net | J13: -38.58 | K13: yes
I14: council tax | J14: -198 | K14: yes
C15: Mortgage | I15: water | J15: -16 | K15: yes
C16: Main | D16: 167660.11 | I16: GARDEN | J16: -6.25 | K16: yes
C17: Extra | D17: 87559.93 | I17: water | J17: -28 | K17: yes
C18: Total Due | D18: =SUM(D16:D17) -> 255220.04 | I18: hp | J18: -2 | K18: yes
C19: H2B paybak | D19: =D20*0.2 -> 84000 | F19: loan is 2600.00 | G19: 2600 | I19: HSBC CC | J19: -600 | K19: yes | L19: f
C20: Sold Price | D20: 420000 | F20: Paid 1 | G20: 580 | I20: tesco bank patio | J20: -255 | K20: yes | L20: f
C21: Equity | D21: =SUM(D18:D19)-D20 -> -80779.96 | F21: Paid 1 | G21: 400 | I21: Tesco Mobile | J21: -12.5 | K21: yes | L21: f
F22: Paid 1 | G22: 500 | I22: train | J22: -30 | K22: yes
F23: Paid 1 | I23: food petrol | J23: -750 | K23: yes | L23: f
G24: =SUM(G20:G23)-G19 -> -1120 | I24: nationaltrust | J24: -10 | K24: yes | L24: f
I25: greenbelt | J25: -7.4 | K25: yes
I26: next | J26: -58 | K26: yes | L26: f
I27: car insurance lv | J27: -35 | K27: yes
I28: disney | K28: no
G29: in saving | I29: savings | K29: no
I30: gym | J30: -30 | K30: yes | L30: f
G31: 73.00 in my sav | I31: window | J31: -10 | K31: yes
I32: tom | J32: -10 | K32: yes
K33: no
K34: no
K35: no
K36: no
K37: no
K38: no
K39: no
K40: no

Sheet NewMoney
C2: Money | F2: Savings Account | I2: Name | J2: Value | K2: Paid? | L2: Who
C3: Paid | D3: 5316.06 | F3: Savings Account | G3: 108 | I3: Mortgage | J3: -852.98 | K3: no
C4: Taken Already | D4: =SUMIF(K3:K29,"Yes*",J3:J29) -> 0 | F4: birthday | I4: Car | J4: -244.8 | K4: no | L4: f
C5: Balance | D5: 5316.06 | F5: botox | I5: LifeInsurance/aviva | J5: -25.56 | K5: no
C6: To Be Taken | D6: =SUMIF(K3:K40,"No",J3:J40) -> -3615.97 | F6: tax money | I6: HouseInsurance - Tesco | J6: -16.3 | K6: no
C7: Total | D7: =D6+D5 -> 1700.09 | F7: Saving Total | G7: =SUM(G3:G6) -> 108 | I7: TvLicence | J7: -13.2 | K7: no
I8: Gas/Electric | J8: -85 | K8: no
I9: pet insur | J9: -27 | K9: no
C10: Francesca | D10: =SUMIF(L3:L40,"f",J3:J40) -> -1943.3 | I10: spotoify | J10: -15 | K10: no
G11: =G3-250 -> -142 | I11: loan | J11: -300 | K11: no
C12: Old Money | D12: 3787.38 | F12: Train | I12: netflix | J12: -13.99 | K12: no
C13: NewMoney(noPens) | D13: 3997.36 | F13: Year | G13: 496 | I13: plus net | J13: -25 | K13: no
C14: 75 | D14: 4349.4 | F14: week | G14: 129.2 | I14: council tax | J14: -198 | K14: no
C15: Mortgage | F15: day | G15: 69 | I15: water | J15: -16 | K15: no
C16: Main | D16: 167660.11 | I16: GARDEN | J16: -6.25 | K16: no
C17: Extra | D17: 87559.93 | I17: water | J17: -28 | K17: no
C18: Total Due | D18: =SUM(D16:D17) -> 255220.04 | I18: hp | J18: -2 | K18: no
C19: H2B paybak | D19: =D20*0.2 -> 84000 | F19: loan is 2600.00 | G19: 2600 | I19: HSBC CC | J19: -400 | K19: no | L19: f
C20: Sold Price | D20: 420000 | F20: Paid 1 | G20: 580 | I20: Train | J20: -496 | K20: no | L20: f
C21: Equity | D21: =SUM(D18:D19)-D20 -> -80779.96 | F21: Paid 1 | G21: 400 | I21: Tesco Mobile | J21: -12.5 | K21: no | L21: f
F22: Paid 1 | I22: train | K22: no
F23: Paid 1 | I23: food petrol | J23: -750 | K23: no | L23: f
G24: =SUM(G20:G23)-G19 -> -1620 | I24: nationaltrust | J24: -10 | K24: no | L24: f
I25: greenbelt | J25: -7.4 | K25: no
I26: next | K26: no | L26: f
I27: car insurance lv | J27: -35 | K27: no
I28: disney | J28: -5.99 | K28: no
G29: in saving | I29: savings | K29: no
I30: gym | J30: -30 | K30: no | L30: f
G31: 73.00 in my sav | I31: denplan | K31: no
I32: green bel | K32: no
K33: no
K34: no
K35: no
K36: no
K37: no
K38: no
K39: no
K40: no

Sheet june21
C2: Money | F2: Savings Account | I2: Name | J2: Value | K2: Paid? | L2: Who
C3: Paid | D3: 4317.31 | F3: Savings Account | G3: 90 | I3: Mortgage | J3: -852.98 | K3: yes
C4: Taken Already | D4: =SUMIF(K3:K29,"Yes*",J3:J29) -> -4139.26 | F4: cash back | G4: 50 | I4: Car | J4: -244.8 | K4: yes | L4: f
C5: Balance | D5: 78.67 | F5: botox | I5: LifeInsurance/aviva | J5: -25.56 | K5: yes
